{"model": {"model0": {"criterion": "gini", "max_features": "sqrt", "min_samples_leaf": 1, "min_samples_split": 2, "n_estimators": 3}, "model1": {"criterion": "gini", "max_features": "sqrt", "min_samples_leaf": 1, "min_samples_split": 2, "n_estimators": 5}, "model2": {"criterion": "gini", "max_features": "sqrt", "min_samples_leaf": 1, "min_samples_split": 2, "n_estimators": 10}, "model3": {"criterion": "gini", "max_features": "sqrt", "min_samples_leaf": 1, "min_samples_split": 2, "n_estimators": 15}, "model4": {"criterion": "gini", "max_features": "sqrt", "min_samples_leaf": 1, "min_samples_split": 2, "n_estimators": 20}, "model5": {"criterion": "gini", "max_features": "sqrt", "min_samples_leaf": 1, "min_samples_split": 2, "n_estimators": 30}, "model6": {"criterion": "gini", "max_features": "sqrt", "min_samples_leaf": 1, "min_samples_split": 2, "n_estimators": 50}, "model7": {"criterion": "gini", "max_features": "sqrt", "min_samples_leaf": 1, "min_samples_split": 2, "n_estimators": 90}, "model8": {"criterion": "gini", "max_features": "sqrt", "min_samples_leaf": 1, "min_samples_split": 2, "n_estimators": 95}, "model9": {"criterion": "gini", "max_features": "sqrt", "min_samples_leaf": 1, "min_samples_split": 2, "n_estimators": 100}, "model10": {"criterion": "gini", "max_features": "sqrt", "min_samples_leaf": 1, "min_samples_split": 2, "n_estimators": 125}, "model11": {"criterion": "gini", "max_features": "sqrt", "min_samples_leaf": 1, "min_samples_split": 2, "n_estimators": 130}, "model12": {"criterion": "gini", "max_features": "sqrt", "min_samples_leaf": 1, "min_samples_split": 2, "n_estimators": 150}, "model13": {"criterion": "gini", "max_features": "sqrt", "min_samples_leaf": 1, "min_samples_split": 4, "n_estimators": 3}, "model14": {"criterion": "gini", "max_features": "sqrt", "min_samples_leaf": 1, "min_samples_split": 4, "n_estimators": 5}, "model15": {"criterion": "gini", "max_features": "sqrt", "min_samples_leaf": 1, "min_samples_split": 4, "n_estimators": 10}, "model16": {"criterion": "gini", "max_features": "sqrt", "min_samples_leaf": 1, "min_samples_split": 4, "n_estimators": 15}, "model17": {"criterion": "gini", "max_features": "sqrt", "min_samples_leaf": 1, "min_samples_split": 4, "n_estimators": 20}, "model18": {"criterion": "gini", "max_features": "sqrt", "min_samples_leaf": 1, "min_samples_split": 4, "n_estimators": 30}, "model19": {"criterion": "gini", "max_features": "sqrt", "min_samples_leaf": 1, "min_samples_split": 4, "n_estimators": 50}, "model20": {"criterion": "gini", "max_features": "sqrt", "min_samples_leaf": 1, "min_samples_split": 4, "n_estimators": 90}, "model21": {"criterion": "gini", "max_features": "sqrt", "min_samples_leaf": 1, "min_samples_split": 4, "n_estimators": 95}, "model22": {"criterion": "gini", "max_features": "sqrt", "min_samples_leaf": 1, "min_samples_split": 4, "n_estimators": 100}, "model23": {"criterion": "gini", "max_features": "sqrt", "min_samples_leaf": 1, "min_samples_split": 4, "n_estimators": 125}, "model24": {"criterion": "gini", "max_features": "sqrt", "min_samples_leaf": 1, "min_samples_split": 4, "n_estimators": 130}, "model25": {"criterion": "gini", "max_features": "sqrt", "min_samples_leaf": 1, "min_samples_split": 4, "n_estimators": 150}, "model26": {"criterion": "gini", "max_features": "sqrt", "min_samples_leaf": 3, "min_samples_split": 2, "n_estimators": 3}, "model27": {"criterion": "gini", "max_features": "sqrt", "min_samples_leaf": 3, "min_samples_split": 2, "n_estimators": 5}, "model28": {"criterion": "gini", "max_features": "sqrt", "min_samples_leaf": 3, "min_samples_split": 2, "n_estimators": 10}, "model29": {"criterion": "gini", "max_features": "sqrt", "min_samples_leaf": 3, "min_samples_split": 2, "n_estimators": 15}, "model30": {"criterion": "gini", "max_features": "sqrt", "min_samples_leaf": 3, "min_samples_split": 2, "n_estimators": 20}, "model31": {"criterion": "gini", "max_features": "sqrt", "min_samples_leaf": 3, "min_samples_split": 2, "n_estimators": 30}, "model32": {"criterion": "gini", "max_features": "sqrt", "min_samples_leaf": 3, "min_samples_split": 2, "n_estimators": 50}, "model33": {"criterion": "gini", "max_features": "sqrt", "min_samples_leaf": 3, "min_samples_split": 2, "n_estimators": 90}, "model34": {"criterion": "gini", "max_features": "sqrt", "min_samples_leaf": 3, "min_samples_split": 2, "n_estimators": 95}, "model35": {"criterion": "gini", "max_features": "sqrt", "min_samples_leaf": 3, "min_samples_split": 2, "n_estimators": 100}, "model36": {"criterion": "gini", "max_features": "sqrt", "min_samples_leaf": 3, "min_samples_split": 2, "n_estimators": 125}, "model37": {"criterion": "gini", "max_features": "sqrt", "min_samples_leaf": 3, "min_samples_split": 2, "n_estimators": 130}, "model38": {"criterion": "gini", "max_features": "sqrt", "min_samples_leaf": 3, "min_samples_split": 2, "n_estimators": 150}, "model39": {"criterion": "gini", "max_features": "sqrt", "min_samples_leaf": 3, "min_samples_split": 4, "n_estimators": 3}, "model40": {"criterion": "gini", "max_features": "sqrt", "min_samples_leaf": 3, "min_samples_split": 4, "n_estimators": 5}, "model41": {"criterion": "gini", "max_features": "sqrt", "min_samples_leaf": 3, "min_samples_split": 4, "n_estimators": 10}, "model42": {"criterion": "gini", "max_features": "sqrt", "min_samples_leaf": 3, "min_samples_split": 4, "n_estimators": 15}, "model43": {"criterion": "gini", "max_features": "sqrt", "min_samples_leaf": 3, "min_samples_split": 4, "n_estimators": 20}, "model44": {"criterion": "gini", "max_features": "sqrt", "min_samples_leaf": 3, "min_samples_split": 4, "n_estimators": 30}, "model45": {"criterion": "gini", "max_features": "sqrt", "min_samples_leaf": 3, "min_samples_split": 4, "n_estimators": 50}, "model46": {"criterion": "gini", "max_features": "sqrt", "min_samples_leaf": 3, "min_samples_split": 4, "n_estimators": 90}, "model47": {"criterion": "gini", "max_features": "sqrt", "min_samples_leaf": 3, "min_samples_split": 4, "n_estimators": 95}, "model48": {"criterion": "gini", "max_features": "sqrt", "min_samples_leaf": 3, "min_samples_split": 4, "n_estimators": 100}, "model49": {"criterion": "gini", "max_features": "sqrt", "min_samples_leaf": 3, "min_samples_split": 4, "n_estimators": 125}, "model50": {"criterion": "gini", "max_features": "sqrt", "min_samples_leaf": 3, "min_samples_split": 4, "n_estimators": 130}, "model51": {"criterion": "gini", "max_features": "sqrt", "min_samples_leaf": 3, "min_samples_split": 4, "n_estimators": 150}, "model52": {"criterion": "gini", "max_features": "log2", "min_samples_leaf": 1, "min_samples_split": 2, "n_estimators": 3}, "model53": {"criterion": "gini", "max_features": "log2", "min_samples_leaf": 1, "min_samples_split": 2, "n_estimators": 5}, "model54": {"criterion": "gini", "max_features": "log2", "min_samples_leaf": 1, "min_samples_split": 2, "n_estimators": 10}, "model55": {"criterion": "gini", "max_features": "log2", "min_samples_leaf": 1, "min_samples_split": 2, "n_estimators": 15}, "model56": {"criterion": "gini", "max_features": "log2", "min_samples_leaf": 1, "min_samples_split": 2, "n_estimators": 20}, "model57": {"criterion": "gini", "max_features": "log2", "min_samples_leaf": 1, "min_samples_split": 2, "n_estimators": 30}, "model58": {"criterion": "gini", "max_features": "log2", "min_samples_leaf": 1, "min_samples_split": 2, "n_estimators": 50}, "model59": {"criterion": "gini", "max_features": "log2", "min_samples_leaf": 1, "min_samples_split": 2, "n_estimators": 90}, "model60": {"criterion": "gini", "max_features": "log2", "min_samples_leaf": 1, "min_samples_split": 2, "n_estimators": 95}, "model61": {"criterion": "gini", "max_features": "log2", "min_samples_leaf": 1, "min_samples_split": 2, "n_estimators": 100}, "model62": {"criterion": "gini", "max_features": "log2", "min_samples_leaf": 1, "min_samples_split": 2, "n_estimators": 125}, "model63": {"criterion": "gini", "max_features": "log2", "min_samples_leaf": 1, "min_samples_split": 2, "n_estimators": 130}, "model64": {"criterion": "gini", "max_features": "log2", "min_samples_leaf": 1, "min_samples_split": 2, "n_estimators": 150}, "model65": {"criterion": "gini", "max_features": "log2", "min_samples_leaf": 1, "min_samples_split": 4, "n_estimators": 3}, "model66": {"criterion": "gini", "max_features": "log2", "min_samples_leaf": 1, "min_samples_split": 4, "n_estimators": 5}, "model67": {"criterion": "gini", "max_features": "log2", "min_samples_leaf": 1, "min_samples_split": 4, "n_estimators": 10}, "model68": {"criterion": "gini", "max_features": "log2", "min_samples_leaf": 1, "min_samples_split": 4, "n_estimators": 15}, "model69": {"criterion": "gini", "max_features": "log2", "min_samples_leaf": 1, "min_samples_split": 4, "n_estimators": 20}, "model70": {"criterion": "gini", "max_features": "log2", "min_samples_leaf": 1, "min_samples_split": 4, "n_estimators": 30}, "model71": {"criterion": "gini", "max_features": "log2", "min_samples_leaf": 1, "min_samples_split": 4, "n_estimators": 50}, "model72": {"criterion": "gini", "max_features": "log2", "min_samples_leaf": 1, "min_samples_split": 4, "n_estimators": 90}, "model73": {"criterion": "gini", "max_features": "log2", "min_samples_leaf": 1, "min_samples_split": 4, "n_estimators": 95}, "model74": {"criterion": "gini", "max_features": "log2", "min_samples_leaf": 1, "min_samples_split": 4, "n_estimators": 100}, "model75": {"criterion": "gini", "max_features": "log2", "min_samples_leaf": 1, "min_samples_split": 4, "n_estimators": 125}, "model76": {"criterion": "gini", "max_features": "log2", "min_samples_leaf": 1, "min_samples_split": 4, "n_estimators": 130}, "model77": {"criterion": "gini", "max_features": "log2", "min_samples_leaf": 1, "min_samples_split": 4, "n_estimators": 150}, "model78": {"criterion": "gini", "max_features": "log2", "min_samples_leaf": 3, "min_samples_split": 2, "n_estimators": 3}, "model79": {"criterion": "gini", "max_features": "log2", "min_samples_leaf": 3, "min_samples_split": 2, "n_estimators": 5}, "model80": {"criterion": "gini", "max_features": "log2", "min_samples_leaf": 3, "min_samples_split": 2, "n_estimators": 10}, "model81": {"criterion": "gini", "max_features": "log2", "min_samples_leaf": 3, "min_samples_split": 2, "n_estimators": 15}, "model82": {"criterion": "gini", "max_features": "log2", "min_samples_leaf": 3, "min_samples_split": 2, "n_estimators": 20}, "model83": {"criterion": "gini", "max_features": "log2", "min_samples_leaf": 3, "min_samples_split": 2, "n_estimators": 30}, "model84": {"criterion": "gini", "max_features": "log2", "min_samples_leaf": 3, "min_samples_split": 2, "n_estimators": 50}, "model85": {"criterion": "gini", "max_features": "log2", "min_samples_leaf": 3, "min_samples_split": 2, "n_estimators": 90}, "model86": {"criterion": "gini", "max_features": "log2", "min_samples_leaf": 3, "min_samples_split": 2, "n_estimators": 95}, "model87": {"criterion": "gini", "max_features": "log2", "min_samples_leaf": 3, "min_samples_split": 2, "n_estimators": 100}, "model88": {"criterion": "gini", "max_features": "log2", "min_samples_leaf": 3, "min_samples_split": 2, "n_estimators": 125}, "model89": {"criterion": "gini", "max_features": "log2", "min_samples_leaf": 3, "min_samples_split": 2, "n_estimators": 130}, "model90": {"criterion": "gini", "max_features": "log2", "min_samples_leaf": 3, "min_samples_split": 2, "n_estimators": 150}, "model91": {"criterion": "gini", "max_features": "log2", "min_samples_leaf": 3, "min_samples_split": 4, "n_estimators": 3}, "model92": {"criterion": "gini", "max_features": "log2", "min_samples_leaf": 3, "min_samples_split": 4, "n_estimators": 5}, "model93": {"criterion": "gini", "max_features": "log2", "min_samples_leaf": 3, "min_samples_split": 4, "n_estimators": 10}, "model94": {"criterion": "gini", "max_features": "log2", "min_samples_leaf": 3, "min_samples_split": 4, "n_estimators": 15}, "model95": {"criterion": "gini", "max_features": "log2", "min_samples_leaf": 3, "min_samples_split": 4, "n_estimators": 20}, "model96": {"criterion": "gini", "max_features": "log2", "min_samples_leaf": 3, "min_samples_split": 4, "n_estimators": 30}, "model97": {"criterion": "gini", "max_features": "log2", "min_samples_leaf": 3, "min_samples_split": 4, "n_estimators": 50}, "model98": {"criterion": "gini", "max_features": "log2", "min_samples_leaf": 3, "min_samples_split": 4, "n_estimators": 90}, "model99": {"criterion": "gini", "max_features": "log2", "min_samples_leaf": 3, "min_samples_split": 4, "n_estimators": 95}, "model100": {"criterion": "gini", "max_features": "log2", "min_samples_leaf": 3, "min_samples_split": 4, "n_estimators": 100}, "model101": {"criterion": "gini", "max_features": "log2", "min_samples_leaf": 3, "min_samples_split": 4, "n_estimators": 125}, "model102": {"criterion": "gini", "max_features": "log2", "min_samples_leaf": 3, "min_samples_split": 4, "n_estimators": 130}, "model103": {"criterion": "gini", "max_features": "log2", "min_samples_leaf": 3, "min_samples_split": 4, "n_estimators": 150}}, "precision": {"model0": [0.6, 0.6923076923076923, 0.5, 0.6666666666666666, 0.5333333333333333], "model1": [0.6666666666666666, 0.6666666666666666, 0.5555555555555556, 0.75, 0.5384615384615384], "model2": [0.6666666666666666, 0.6666666666666666, 0.6666666666666666, 0.75, 0.5714285714285714], "model3": [0.6, 0.6923076923076923, 0.6666666666666666, 0.75, 0.5333333333333333], "model4": [0.6666666666666666, 0.6666666666666666, 0.8, 0.7142857142857143, 0.5], "model5": [0.625, 0.6428571428571429, 0.8, 0.7142857142857143, 0.5714285714285714], "model6": [0.625, 0.6, 0.8, 0.75, 0.5], "model7": [0.6666666666666666, 0.5454545454545454, 0.6666666666666666, 0.7142857142857143, 0.5333333333333333], "model8": [0.6666666666666666, 0.6666666666666666, 0.6666666666666666, 0.7142857142857143, 0.5333333333333333], "model9": [0.6666666666666666, 0.6153846153846154, 0.6, 0.7142857142857143, 0.5], "model10": [0.6666666666666666, 0.5833333333333334, 0.75, 0.7142857142857143, 0.5], "model11": [0.6666666666666666, 0.5833333333333334, 0.75, 0.7142857142857143, 0.5], "model12": [0.6666666666666666, 0.5833333333333334, 0.6, 0.6666666666666666, 0.5384615384615384], "model13": [0.5, 0.8181818181818182, 0.5555555555555556, 0.7272727272727273, 0.5333333333333333], "model14": [0.6, 0.6923076923076923, 0.5, 0.8, 0.5384615384615384], "model15": [0.8, 0.75, 0.5, 0.7777777777777778, 0.5333333333333333], "model16": [0.7142857142857143, 0.75, 0.6, 0.7777777777777778, 0.5333333333333333], "model17": [0.625, 0.6923076923076923, 0.6666666666666666, 0.75, 0.5333333333333333], "model18": [0.625, 0.6923076923076923, 0.6, 0.7777777777777778, 0.5333333333333333], "model19": [0.625, 0.6923076923076923, 0.6, 0.7777777777777778, 0.5333333333333333], "model20": [0.5714285714285714, 0.6666666666666666, 0.75, 0.7142857142857143, 0.5333333333333333], "model21": [0.5714285714285714, 0.6666666666666666, 0.75, 0.6666666666666666, 0.5333333333333333], "model22": [0.5714285714285714, 0.6923076923076923, 0.75, 0.7142857142857143, 0.5333333333333333], "model23": [0.5714285714285714, 0.7272727272727273, 0.75, 0.7142857142857143, 0.5333333333333333], "model24": [0.5714285714285714, 0.7272727272727273, 0.75, 0.7142857142857143, 0.5333333333333333], "model25": [0.6666666666666666, 0.7272727272727273, 0.75, 0.7142857142857143, 0.5333333333333333], "model26": [0.7142857142857143, 0.6153846153846154, 0.6666666666666666, 0.8571428571428571, 0.5], "model27": [0.4, 0.6153846153846154, 0.6, 0.8333333333333334, 0.5333333333333333], "model28": [0.6666666666666666, 0.6428571428571429, 0.8, 1.0, 0.5384615384615384], "model29": [0.6666666666666666, 0.6923076923076923, 0.8, 0.8333333333333334, 0.5], "model30": [0.6666666666666666, 0.6923076923076923, 0.8333333333333334, 0.8333333333333334, 0.5333333333333333], "model31": [0.6666666666666666, 0.6666666666666666, 0.75, 0.6666666666666666, 0.5714285714285714], "model32": [0.5, 0.6363636363636364, 0.75, 0.8, 0.5333333333333333], "model33": [0.5714285714285714, 0.6363636363636364, 0.75, 0.8571428571428571, 0.5333333333333333], "model34": [0.5714285714285714, 0.6363636363636364, 0.75, 0.75, 0.5333333333333333], "model35": [0.5714285714285714, 0.6363636363636364, 0.75, 0.75, 0.5333333333333333], "model36": [0.5, 0.6153846153846154, 0.75, 0.7142857142857143, 0.5333333333333333], "model37": [0.5, 0.6153846153846154, 0.75, 0.7142857142857143, 0.5333333333333333], "model38": [0.5, 0.6666666666666666, 0.75, 0.75, 0.5333333333333333], "model39": [0.7142857142857143, 0.6153846153846154, 0.6666666666666666, 0.8571428571428571, 0.5], "model40": [0.4, 0.6153846153846154, 0.6, 0.8333333333333334, 0.5333333333333333], "model41": [0.6666666666666666, 0.6428571428571429, 0.8, 1.0, 0.5384615384615384], "model42": [0.6666666666666666, 0.6923076923076923, 0.8, 0.8333333333333334, 0.5], "model43": [0.6666666666666666, 0.6923076923076923, 0.8333333333333334, 0.8333333333333334, 0.5333333333333333], "model44": [0.6666666666666666, 0.6666666666666666, 0.75, 0.6666666666666666, 0.5714285714285714], "model45": [0.5, 0.6363636363636364, 0.75, 0.8, 0.5333333333333333], "model46": [0.5714285714285714, 0.6363636363636364, 0.75, 0.8571428571428571, 0.5333333333333333], "model47": [0.5714285714285714, 0.6363636363636364, 0.75, 0.75, 0.5333333333333333], "model48": [0.5714285714285714, 0.6363636363636364, 0.75, 0.75, 0.5333333333333333], "model49": [0.5, 0.6153846153846154, 0.75, 0.7142857142857143, 0.5333333333333333], "model50": [0.5, 0.6153846153846154, 0.75, 0.7142857142857143, 0.5333333333333333], "model51": [0.5, 0.6666666666666666, 0.75, 0.75, 0.5333333333333333], "model52": [0.5, 0.6428571428571429, 0.6666666666666666, 0.6, 0.4166666666666667], "model53": [0.5555555555555556, 0.5714285714285714, 0.8571428571428571, 0.5, 0.46153846153846156], "model54": [0.5, 0.5833333333333334, 0.75, 0.625, 0.5384615384615384], "model55": [0.4444444444444444, 0.6666666666666666, 0.625, 0.625, 0.5], "model56": [0.5, 0.6153846153846154, 0.5, 0.7142857142857143, 0.5333333333333333], "model57": [0.5, 0.6363636363636364, 0.625, 0.6666666666666666, 0.5333333333333333], "model58": [0.5, 0.6, 0.6666666666666666, 0.7142857142857143, 0.5], "model59": [0.6666666666666666, 0.5833333333333334, 0.6666666666666666, 0.7142857142857143, 0.5], "model60": [0.6666666666666666, 0.5833333333333334, 0.6666666666666666, 0.7142857142857143, 0.5], "model61": [0.5714285714285714, 0.5833333333333334, 0.6666666666666666, 0.7142857142857143, 0.5], "model62": [0.6666666666666666, 0.5833333333333334, 0.6666666666666666, 0.7142857142857143, 0.5], "model63": [0.6666666666666666, 0.5833333333333334, 0.6666666666666666, 0.7142857142857143, 0.5], "model64": [0.6666666666666666, 0.5833333333333334, 0.6666666666666666, 0.7142857142857143, 0.5], "model65": [0.6666666666666666, 0.6153846153846154, 0.625, 0.625, 0.4444444444444444], "model66": [0.625, 0.5833333333333334, 0.6666666666666666, 0.6, 0.25], "model67": [0.6666666666666666, 0.5714285714285714, 0.6666666666666666, 0.625, 0.5384615384615384], "model68": [0.6666666666666666, 0.6153846153846154, 0.75, 0.75, 0.5333333333333333], "model69": [0.5714285714285714, 0.6153846153846154, 0.8, 0.75, 0.5], "model70": [0.6666666666666666, 0.6153846153846154, 0.75, 0.75, 0.5], "model71": [0.5714285714285714, 0.6428571428571429, 0.75, 0.7142857142857143, 0.5333333333333333], "model72": [0.6666666666666666, 0.6666666666666666, 0.8, 0.7142857142857143, 0.5333333333333333], "model73": [0.6666666666666666, 0.6666666666666666, 0.75, 0.6666666666666666, 0.5333333333333333], "model74": [0.6666666666666666, 0.6666666666666666, 0.8, 0.7142857142857143, 0.5333333333333333], "model75": [0.6666666666666666, 0.6666666666666666, 0.8, 0.6666666666666666, 0.5333333333333333], "model76": [0.6666666666666666, 0.6666666666666666, 0.75, 0.6666666666666666, 0.5333333333333333], "model77": [0.6666666666666666, 0.6666666666666666, 0.8, 0.6666666666666666, 0.5333333333333333], "model78": [0.6666666666666666, 0.6153846153846154, 0.75, 0.8181818181818182, 0.46153846153846156], "model79": [0.7142857142857143, 0.6428571428571429, 0.6, 0.7272727272727273, 0.46153846153846156], "model80": [0.6666666666666666, 0.5714285714285714, 0.8, 1.0, 0.5333333333333333], "model81": [0.6666666666666666, 0.5714285714285714, 0.6666666666666666, 0.7142857142857143, 0.5333333333333333], "model82": [0.6666666666666666, 0.5384615384615384, 0.5, 1.0, 0.5333333333333333], "model83": [0.6666666666666666, 0.5384615384615384, 0.5, 1.0, 0.5333333333333333], "model84": [0.6666666666666666, 0.5833333333333334, 0.5, 0.8333333333333334, 0.5333333333333333], "model85": [0.6666666666666666, 0.6363636363636364, 0.6666666666666666, 0.875, 0.5], "model86": [0.6666666666666666, 0.5833333333333334, 0.6666666666666666, 0.8571428571428571, 0.5], "model87": [0.6666666666666666, 0.5833333333333334, 0.6666666666666666, 0.8571428571428571, 0.5], "model88": [0.6666666666666666, 0.6666666666666666, 0.6666666666666666, 0.8333333333333334, 0.5], "model89": [0.6666666666666666, 0.6666666666666666, 0.6666666666666666, 0.8333333333333334, 0.5], "model90": [0.6666666666666666, 0.6666666666666666, 0.5714285714285714, 0.8333333333333334, 0.5], "model91": [0.6666666666666666, 0.6153846153846154, 0.75, 0.8181818181818182, 0.46153846153846156], "model92": [0.7142857142857143, 0.6428571428571429, 0.6, 0.7272727272727273, 0.46153846153846156], "model93": [0.6666666666666666, 0.5714285714285714, 0.8, 1.0, 0.5333333333333333], "model94": [0.6666666666666666, 0.5714285714285714, 0.6666666666666666, 0.7142857142857143, 0.5333333333333333], "model95": [0.6666666666666666, 0.5384615384615384, 0.5, 1.0, 0.5333333333333333], "model96": [0.6666666666666666, 0.5384615384615384, 0.5, 1.0, 0.5333333333333333], "model97": [0.6666666666666666, 0.5833333333333334, 0.5, 0.8333333333333334, 0.5333333333333333], "model98": [0.6666666666666666, 0.6363636363636364, 0.6666666666666666, 0.875, 0.5], "model99": [0.6666666666666666, 0.5833333333333334, 0.6666666666666666, 0.8571428571428571, 0.5], "model100": [0.6666666666666666, 0.5833333333333334, 0.6666666666666666, 0.8571428571428571, 0.5], "model101": [0.6666666666666666, 0.6666666666666666, 0.6666666666666666, 0.8333333333333334, 0.5], "model102": [0.6666666666666666, 0.6666666666666666, 0.6666666666666666, 0.8333333333333334, 0.5], "model103": [0.6666666666666666, 0.6666666666666666, 0.5714285714285714, 0.8333333333333334, 0.5]}, "recall": {"model0": [0.3333333333333333, 1.0, 0.4444444444444444, 0.6666666666666666, 1.0], "model1": [0.4444444444444444, 0.8888888888888888, 0.5555555555555556, 0.6666666666666666, 0.875], "model2": [0.4444444444444444, 0.8888888888888888, 0.4444444444444444, 0.6666666666666666, 1.0], "model3": [0.3333333333333333, 1.0, 0.4444444444444444, 0.6666666666666666, 1.0], "model4": [0.4444444444444444, 0.8888888888888888, 0.4444444444444444, 0.5555555555555556, 0.875], "model5": [0.5555555555555556, 1.0, 0.4444444444444444, 0.5555555555555556, 1.0], "model6": [0.5555555555555556, 0.6666666666666666, 0.4444444444444444, 0.6666666666666666, 0.875], "model7": [0.4444444444444444, 0.6666666666666666, 0.4444444444444444, 0.5555555555555556, 1.0], "model8": [0.4444444444444444, 0.8888888888888888, 0.4444444444444444, 0.5555555555555556, 1.0], "model9": [0.4444444444444444, 0.8888888888888888, 0.3333333333333333, 0.5555555555555556, 0.875], "model10": [0.4444444444444444, 0.7777777777777778, 0.3333333333333333, 0.5555555555555556, 0.875], "model11": [0.4444444444444444, 0.7777777777777778, 0.3333333333333333, 0.5555555555555556, 0.875], "model12": [0.4444444444444444, 0.7777777777777778, 0.3333333333333333, 0.4444444444444444, 0.875], "model13": [0.2222222222222222, 1.0, 0.5555555555555556, 0.8888888888888888, 1.0], "model14": [0.3333333333333333, 1.0, 0.4444444444444444, 0.8888888888888888, 0.875], "model15": [0.4444444444444444, 1.0, 0.3333333333333333, 0.7777777777777778, 1.0], "model16": [0.5555555555555556, 1.0, 0.3333333333333333, 0.7777777777777778, 1.0], "model17": [0.5555555555555556, 1.0, 0.4444444444444444, 0.6666666666666666, 1.0], "model18": [0.5555555555555556, 1.0, 0.3333333333333333, 0.7777777777777778, 1.0], "model19": [0.5555555555555556, 1.0, 0.3333333333333333, 0.7777777777777778, 1.0], "model20": [0.4444444444444444, 0.8888888888888888, 0.3333333333333333, 0.5555555555555556, 1.0], "model21": [0.4444444444444444, 0.8888888888888888, 0.3333333333333333, 0.4444444444444444, 1.0], "model22": [0.4444444444444444, 1.0, 0.3333333333333333, 0.5555555555555556, 1.0], "model23": [0.4444444444444444, 0.8888888888888888, 0.3333333333333333, 0.5555555555555556, 1.0], "model24": [0.4444444444444444, 0.8888888888888888, 0.3333333333333333, 0.5555555555555556, 1.0], "model25": [0.4444444444444444, 0.8888888888888888, 0.3333333333333333, 0.5555555555555556, 1.0], "model26": [0.5555555555555556, 0.8888888888888888, 0.6666666666666666, 0.6666666666666666, 0.875], "model27": [0.2222222222222222, 0.8888888888888888, 0.6666666666666666, 0.5555555555555556, 1.0], "model28": [0.4444444444444444, 1.0, 0.4444444444444444, 0.4444444444444444, 0.875], "model29": [0.4444444444444444, 1.0, 0.4444444444444444, 0.5555555555555556, 0.875], "model30": [0.4444444444444444, 1.0, 0.5555555555555556, 0.5555555555555556, 1.0], "model31": [0.4444444444444444, 0.8888888888888888, 0.3333333333333333, 0.4444444444444444, 1.0], "model32": [0.4444444444444444, 0.7777777777777778, 0.3333333333333333, 0.4444444444444444, 1.0], "model33": [0.4444444444444444, 0.7777777777777778, 0.3333333333333333, 0.6666666666666666, 1.0], "model34": [0.4444444444444444, 0.7777777777777778, 0.3333333333333333, 0.6666666666666666, 1.0], "model35": [0.4444444444444444, 0.7777777777777778, 0.3333333333333333, 0.6666666666666666, 1.0], "model36": [0.4444444444444444, 0.8888888888888888, 0.3333333333333333, 0.5555555555555556, 1.0], "model37": [0.4444444444444444, 0.8888888888888888, 0.3333333333333333, 0.5555555555555556, 1.0], "model38": [0.4444444444444444, 0.8888888888888888, 0.3333333333333333, 0.6666666666666666, 1.0], "model39": [0.5555555555555556, 0.8888888888888888, 0.6666666666666666, 0.6666666666666666, 0.875], "model40": [0.2222222222222222, 0.8888888888888888, 0.6666666666666666, 0.5555555555555556, 1.0], "model41": [0.4444444444444444, 1.0, 0.4444444444444444, 0.4444444444444444, 0.875], "model42": [0.4444444444444444, 1.0, 0.4444444444444444, 0.5555555555555556, 0.875], "model43": [0.4444444444444444, 1.0, 0.5555555555555556, 0.5555555555555556, 1.0], "model44": [0.4444444444444444, 0.8888888888888888, 0.3333333333333333, 0.4444444444444444, 1.0], "model45": [0.4444444444444444, 0.7777777777777778, 0.3333333333333333, 0.4444444444444444, 1.0], "model46": [0.4444444444444444, 0.7777777777777778, 0.3333333333333333, 0.6666666666666666, 1.0], "model47": [0.4444444444444444, 0.7777777777777778, 0.3333333333333333, 0.6666666666666666, 1.0], "model48": [0.4444444444444444, 0.7777777777777778, 0.3333333333333333, 0.6666666666666666, 1.0], "model49": [0.4444444444444444, 0.8888888888888888, 0.3333333333333333, 0.5555555555555556, 1.0], "model50": [0.4444444444444444, 0.8888888888888888, 0.3333333333333333, 0.5555555555555556, 1.0], "model51": [0.4444444444444444, 0.8888888888888888, 0.3333333333333333, 0.6666666666666666, 1.0], "model52": [0.4444444444444444, 1.0, 0.4444444444444444, 0.6666666666666666, 0.625], "model53": [0.5555555555555556, 0.8888888888888888, 0.6666666666666666, 0.5555555555555556, 0.75], "model54": [0.4444444444444444, 0.7777777777777778, 0.3333333333333333, 0.5555555555555556, 0.875], "model55": [0.4444444444444444, 0.8888888888888888, 0.5555555555555556, 0.5555555555555556, 0.875], "model56": [0.4444444444444444, 0.8888888888888888, 0.3333333333333333, 0.5555555555555556, 1.0], "model57": [0.4444444444444444, 0.7777777777777778, 0.5555555555555556, 0.4444444444444444, 1.0], "model58": [0.4444444444444444, 0.6666666666666666, 0.4444444444444444, 0.5555555555555556, 0.875], "model59": [0.4444444444444444, 0.7777777777777778, 0.4444444444444444, 0.5555555555555556, 0.875], "model60": [0.4444444444444444, 0.7777777777777778, 0.4444444444444444, 0.5555555555555556, 0.875], "model61": [0.4444444444444444, 0.7777777777777778, 0.4444444444444444, 0.5555555555555556, 0.875], "model62": [0.4444444444444444, 0.7777777777777778, 0.4444444444444444, 0.5555555555555556, 0.875], "model63": [0.4444444444444444, 0.7777777777777778, 0.4444444444444444, 0.5555555555555556, 0.875], "model64": [0.4444444444444444, 0.7777777777777778, 0.4444444444444444, 0.5555555555555556, 0.875], "model65": [0.4444444444444444, 0.8888888888888888, 0.5555555555555556, 0.5555555555555556, 0.5], "model66": [0.5555555555555556, 0.7777777777777778, 0.4444444444444444, 0.6666666666666666, 0.25], "model67": [0.4444444444444444, 0.8888888888888888, 0.4444444444444444, 0.5555555555555556, 0.875], "model68": [0.4444444444444444, 0.8888888888888888, 0.3333333333333333, 0.6666666666666666, 1.0], "model69": [0.4444444444444444, 0.8888888888888888, 0.4444444444444444, 0.6666666666666666, 0.875], "model70": [0.4444444444444444, 0.8888888888888888, 0.3333333333333333, 0.6666666666666666, 0.875], "model71": [0.4444444444444444, 1.0, 0.3333333333333333, 0.5555555555555556, 1.0], "model72": [0.4444444444444444, 0.8888888888888888, 0.4444444444444444, 0.5555555555555556, 1.0], "model73": [0.4444444444444444, 0.8888888888888888, 0.3333333333333333, 0.4444444444444444, 1.0], "model74": [0.4444444444444444, 0.8888888888888888, 0.4444444444444444, 0.5555555555555556, 1.0], "model75": [0.4444444444444444, 0.8888888888888888, 0.4444444444444444, 0.4444444444444444, 1.0], "model76": [0.4444444444444444, 0.8888888888888888, 0.3333333333333333, 0.4444444444444444, 1.0], "model77": [0.4444444444444444, 0.8888888888888888, 0.4444444444444444, 0.4444444444444444, 1.0], "model78": [0.4444444444444444, 0.8888888888888888, 0.3333333333333333, 1.0, 0.75], "model79": [0.5555555555555556, 1.0, 0.3333333333333333, 0.8888888888888888, 0.75], "model80": [0.4444444444444444, 0.8888888888888888, 0.4444444444444444, 0.5555555555555556, 1.0], "model81": [0.4444444444444444, 0.8888888888888888, 0.4444444444444444, 0.5555555555555556, 1.0], "model82": [0.4444444444444444, 0.7777777777777778, 0.3333333333333333, 0.6666666666666666, 1.0], "model83": [0.4444444444444444, 0.7777777777777778, 0.2222222222222222, 0.6666666666666666, 1.0], "model84": [0.4444444444444444, 0.7777777777777778, 0.3333333333333333, 0.5555555555555556, 1.0], "model85": [0.4444444444444444, 0.7777777777777778, 0.4444444444444444, 0.7777777777777778, 0.875], "model86": [0.4444444444444444, 0.7777777777777778, 0.4444444444444444, 0.6666666666666666, 0.875], "model87": [0.4444444444444444, 0.7777777777777778, 0.4444444444444444, 0.6666666666666666, 0.875], "model88": [0.4444444444444444, 0.8888888888888888, 0.4444444444444444, 0.5555555555555556, 0.875], "model89": [0.4444444444444444, 0.8888888888888888, 0.4444444444444444, 0.5555555555555556, 0.875], "model90": [0.4444444444444444, 0.8888888888888888, 0.4444444444444444, 0.5555555555555556, 0.875], "model91": [0.4444444444444444, 0.8888888888888888, 0.3333333333333333, 1.0, 0.75], "model92": [0.5555555555555556, 1.0, 0.3333333333333333, 0.8888888888888888, 0.75], "model93": [0.4444444444444444, 0.8888888888888888, 0.4444444444444444, 0.5555555555555556, 1.0], "model94": [0.4444444444444444, 0.8888888888888888, 0.4444444444444444, 0.5555555555555556, 1.0], "model95": [0.4444444444444444, 0.7777777777777778, 0.3333333333333333, 0.6666666666666666, 1.0], "model96": [0.4444444444444444, 0.7777777777777778, 0.2222222222222222, 0.6666666666666666, 1.0], "model97": [0.4444444444444444, 0.7777777777777778, 0.3333333333333333, 0.5555555555555556, 1.0], "model98": [0.4444444444444444, 0.7777777777777778, 0.4444444444444444, 0.7777777777777778, 0.875], "model99": [0.4444444444444444, 0.7777777777777778, 0.4444444444444444, 0.6666666666666666, 0.875], "model100": [0.4444444444444444, 0.7777777777777778, 0.4444444444444444, 0.6666666666666666, 0.875], "model101": [0.4444444444444444, 0.8888888888888888, 0.4444444444444444, 0.5555555555555556, 0.875], "model102": [0.4444444444444444, 0.8888888888888888, 0.4444444444444444, 0.5555555555555556, 0.875], "model103": [0.4444444444444444, 0.8888888888888888, 0.4444444444444444, 0.5555555555555556, 0.875]}, "f1": {"model0": [0.42857142857142855, 0.8181818181818182, 0.47058823529411764, 0.6666666666666666, 0.6956521739130435], "model1": [0.5333333333333333, 0.7619047619047619, 0.5555555555555556, 0.7058823529411765, 0.6666666666666666], "model2": [0.5333333333333333, 0.7619047619047619, 0.5333333333333333, 0.7058823529411765, 0.7272727272727273], "model3": [0.42857142857142855, 0.8181818181818182, 0.5333333333333333, 0.7058823529411765, 0.6956521739130435], "model4": [0.5333333333333333, 0.7619047619047619, 0.5714285714285714, 0.625, 0.6363636363636364], "model5": [0.5882352941176471, 0.782608695652174, 0.5714285714285714, 0.625, 0.7272727272727273], "model6": [0.5882352941176471, 0.631578947368421, 0.5714285714285714, 0.7058823529411765, 0.6363636363636364], "model7": [0.5333333333333333, 0.6, 0.5333333333333333, 0.625, 0.6956521739130435], "model8": [0.5333333333333333, 0.7619047619047619, 0.5333333333333333, 0.625, 0.6956521739130435], "model9": [0.5333333333333333, 0.7272727272727273, 0.42857142857142855, 0.625, 0.6363636363636364], "model10": [0.5333333333333333, 0.6666666666666666, 0.46153846153846156, 0.625, 0.6363636363636364], "model11": [0.5333333333333333, 0.6666666666666666, 0.46153846153846156, 0.625, 0.6363636363636364], "model12": [0.5333333333333333, 0.6666666666666666, 0.42857142857142855, 0.5333333333333333, 0.6666666666666666], "model13": [0.3076923076923077, 0.9, 0.5555555555555556, 0.8, 0.6956521739130435], "model14": [0.42857142857142855, 0.8181818181818182, 0.47058823529411764, 0.8421052631578947, 0.6666666666666666], "model15": [0.5714285714285714, 0.8571428571428571, 0.4, 0.7777777777777778, 0.6956521739130435], "model16": [0.625, 0.8571428571428571, 0.42857142857142855, 0.7777777777777778, 0.6956521739130435], "model17": [0.5882352941176471, 0.8181818181818182, 0.5333333333333333, 0.7058823529411765, 0.6956521739130435], "model18": [0.5882352941176471, 0.8181818181818182, 0.42857142857142855, 0.7777777777777778, 0.6956521739130435], "model19": [0.5882352941176471, 0.8181818181818182, 0.42857142857142855, 0.7777777777777778, 0.6956521739130435], "model20": [0.5, 0.7619047619047619, 0.46153846153846156, 0.625, 0.6956521739130435], "model21": [0.5, 0.7619047619047619, 0.46153846153846156, 0.5333333333333333, 0.6956521739130435], "model22": [0.5, 0.8181818181818182, 0.46153846153846156, 0.625, 0.6956521739130435], "model23": [0.5, 0.8, 0.46153846153846156, 0.625, 0.6956521739130435], "model24": [0.5, 0.8, 0.46153846153846156, 0.625, 0.6956521739130435], "model25": [0.5333333333333333, 0.8, 0.46153846153846156, 0.625, 0.6956521739130435], "model26": [0.625, 0.7272727272727273, 0.6666666666666666, 0.75, 0.6363636363636364], "model27": [0.2857142857142857, 0.7272727272727273, 0.631578947368421, 0.6666666666666666, 0.6956521739130435], "model28": [0.5333333333333333, 0.782608695652174, 0.5714285714285714, 0.6153846153846154, 0.6666666666666666], "model29": [0.5333333333333333, 0.8181818181818182, 0.5714285714285714, 0.6666666666666666, 0.6363636363636364], "model30": [0.5333333333333333, 0.8181818181818182, 0.6666666666666666, 0.6666666666666666, 0.6956521739130435], "model31": [0.5333333333333333, 0.7619047619047619, 0.46153846153846156, 0.5333333333333333, 0.7272727272727273], "model32": [0.47058823529411764, 0.7, 0.46153846153846156, 0.5714285714285714, 0.6956521739130435], "model33": [0.5, 0.7, 0.46153846153846156, 0.75, 0.6956521739130435], "model34": [0.5, 0.7, 0.46153846153846156, 0.7058823529411765, 0.6956521739130435], "model35": [0.5, 0.7, 0.46153846153846156, 0.7058823529411765, 0.6956521739130435], "model36": [0.47058823529411764, 0.7272727272727273, 0.46153846153846156, 0.625, 0.6956521739130435], "model37": [0.47058823529411764, 0.7272727272727273, 0.46153846153846156, 0.625, 0.6956521739130435], "model38": [0.47058823529411764, 0.7619047619047619, 0.46153846153846156, 0.7058823529411765, 0.6956521739130435], "model39": [0.625, 0.7272727272727273, 0.6666666666666666, 0.75, 0.6363636363636364], "model40": [0.2857142857142857, 0.7272727272727273, 0.631578947368421, 0.6666666666666666, 0.6956521739130435], "model41": [0.5333333333333333, 0.782608695652174, 0.5714285714285714, 0.6153846153846154, 0.6666666666666666], "model42": [0.5333333333333333, 0.8181818181818182, 0.5714285714285714, 0.6666666666666666, 0.6363636363636364], "model43": [0.5333333333333333, 0.8181818181818182, 0.6666666666666666, 0.6666666666666666, 0.6956521739130435], "model44": [0.5333333333333333, 0.7619047619047619, 0.46153846153846156, 0.5333333333333333, 0.7272727272727273], "model45": [0.47058823529411764, 0.7, 0.46153846153846156, 0.5714285714285714, 0.6956521739130435], "model46": [0.5, 0.7, 0.46153846153846156, 0.75, 0.6956521739130435], "model47": [0.5, 0.7, 0.46153846153846156, 0.7058823529411765, 0.6956521739130435], "model48": [0.5, 0.7, 0.46153846153846156, 0.7058823529411765, 0.6956521739130435], "model49": [0.47058823529411764, 0.7272727272727273, 0.46153846153846156, 0.625, 0.6956521739130435], "model50": [0.47058823529411764, 0.7272727272727273, 0.46153846153846156, 0.625, 0.6956521739130435], "model51": [0.47058823529411764, 0.7619047619047619, 0.46153846153846156, 0.7058823529411765, 0.6956521739130435], "model52": [0.47058823529411764, 0.782608695652174, 0.5333333333333333, 0.631578947368421, 0.5], "model53": [0.5555555555555556, 0.6956521739130435, 0.75, 0.5263157894736842, 0.5714285714285714], "model54": [0.47058823529411764, 0.6666666666666666, 0.46153846153846156, 0.5882352941176471, 0.6666666666666666], "model55": [0.4444444444444444, 0.7619047619047619, 0.5882352941176471, 0.5882352941176471, 0.6363636363636364], "model56": [0.47058823529411764, 0.7272727272727273, 0.4, 0.625, 0.6956521739130435], "model57": [0.47058823529411764, 0.7, 0.5882352941176471, 0.5333333333333333, 0.6956521739130435], "model58": [0.47058823529411764, 0.631578947368421, 0.5333333333333333, 0.625, 0.6363636363636364], "model59": [0.5333333333333333, 0.6666666666666666, 0.5333333333333333, 0.625, 0.6363636363636364], "model60": [0.5333333333333333, 0.6666666666666666, 0.5333333333333333, 0.625, 0.6363636363636364], "model61": [0.5, 0.6666666666666666, 0.5333333333333333, 0.625, 0.6363636363636364], "model62": [0.5333333333333333, 0.6666666666666666, 0.5333333333333333, 0.625, 0.6363636363636364], "model63": [0.5333333333333333, 0.6666666666666666, 0.5333333333333333, 0.625, 0.6363636363636364], "model64": [0.5333333333333333, 0.6666666666666666, 0.5333333333333333, 0.625, 0.6363636363636364], "model65": [0.5333333333333333, 0.7272727272727273, 0.5882352941176471, 0.5882352941176471, 0.47058823529411764], "model66": [0.5882352941176471, 0.6666666666666666, 0.5333333333333333, 0.631578947368421, 0.25], "model67": [0.5333333333333333, 0.6956521739130435, 0.5333333333333333, 0.5882352941176471, 0.6666666666666666], "model68": [0.5333333333333333, 0.7272727272727273, 0.46153846153846156, 0.7058823529411765, 0.6956521739130435], "model69": [0.5, 0.7272727272727273, 0.5714285714285714, 0.7058823529411765, 0.6363636363636364], "model70": [0.5333333333333333, 0.7272727272727273, 0.46153846153846156, 0.7058823529411765, 0.6363636363636364], "model71": [0.5, 0.782608695652174, 0.46153846153846156, 0.625, 0.6956521739130435], "model72": [0.5333333333333333, 0.7619047619047619, 0.5714285714285714, 0.625, 0.6956521739130435], "model73": [0.5333333333333333, 0.7619047619047619, 0.46153846153846156, 0.5333333333333333, 0.6956521739130435], "model74": [0.5333333333333333, 0.7619047619047619, 0.5714285714285714, 0.625, 0.6956521739130435], "model75": [0.5333333333333333, 0.7619047619047619, 0.5714285714285714, 0.5333333333333333, 0.6956521739130435], "model76": [0.5333333333333333, 0.7619047619047619, 0.46153846153846156, 0.5333333333333333, 0.6956521739130435], "model77": [0.5333333333333333, 0.7619047619047619, 0.5714285714285714, 0.5333333333333333, 0.6956521739130435], "model78": [0.5333333333333333, 0.7272727272727273, 0.46153846153846156, 0.9, 0.5714285714285714], "model79": [0.625, 0.782608695652174, 0.42857142857142855, 0.8, 0.5714285714285714], "model80": [0.5333333333333333, 0.6956521739130435, 0.5714285714285714, 0.7142857142857143, 0.6956521739130435], "model81": [0.5333333333333333, 0.6956521739130435, 0.5333333333333333, 0.625, 0.6956521739130435], "model82": [0.5333333333333333, 0.6363636363636364, 0.4, 0.8, 0.6956521739130435], "model83": [0.5333333333333333, 0.6363636363636364, 0.3076923076923077, 0.8, 0.6956521739130435], "model84": [0.5333333333333333, 0.6666666666666666, 0.4, 0.6666666666666666, 0.6956521739130435], "model85": [0.5333333333333333, 0.7, 0.5333333333333333, 0.8235294117647058, 0.6363636363636364], "model86": [0.5333333333333333, 0.6666666666666666, 0.5333333333333333, 0.75, 0.6363636363636364], "model87": [0.5333333333333333, 0.6666666666666666, 0.5333333333333333, 0.75, 0.6363636363636364], "model88": [0.5333333333333333, 0.7619047619047619, 0.5333333333333333, 0.6666666666666666, 0.6363636363636364], "model89": [0.5333333333333333, 0.7619047619047619, 0.5333333333333333, 0.6666666666666666, 0.6363636363636364], "model90": [0.5333333333333333, 0.7619047619047619, 0.5, 0.6666666666666666, 0.6363636363636364], "model91": [0.5333333333333333, 0.7272727272727273, 0.46153846153846156, 0.9, 0.5714285714285714], "model92": [0.625, 0.782608695652174, 0.42857142857142855, 0.8, 0.5714285714285714], "model93": [0.5333333333333333, 0.6956521739130435, 0.5714285714285714, 0.7142857142857143, 0.6956521739130435], "model94": [0.5333333333333333, 0.6956521739130435, 0.5333333333333333, 0.625, 0.6956521739130435], "model95": [0.5333333333333333, 0.6363636363636364, 0.4, 0.8, 0.6956521739130435], "model96": [0.5333333333333333, 0.6363636363636364, 0.3076923076923077, 0.8, 0.6956521739130435], "model97": [0.5333333333333333, 0.6666666666666666, 0.4, 0.6666666666666666, 0.6956521739130435], "model98": [0.5333333333333333, 0.7, 0.5333333333333333, 0.8235294117647058, 0.6363636363636364], "model99": [0.5333333333333333, 0.6666666666666666, 0.5333333333333333, 0.75, 0.6363636363636364], "model100": [0.5333333333333333, 0.6666666666666666, 0.5333333333333333, 0.75, 0.6363636363636364], "model101": [0.5333333333333333, 0.7619047619047619, 0.5333333333333333, 0.6666666666666666, 0.6363636363636364], "model102": [0.5333333333333333, 0.7619047619047619, 0.5333333333333333, 0.6666666666666666, 0.6363636363636364], "model103": [0.5333333333333333, 0.7619047619047619, 0.5, 0.6666666666666666, 0.6363636363636364]}, "accuracy": {"model0": [0.5, 0.75, 0.4, 0.6, 0.5333333333333333], "model1": [0.5625, 0.6875, 0.4666666666666667, 0.6666666666666666, 0.5333333333333333], "model2": [0.5625, 0.6875, 0.5333333333333333, 0.6666666666666666, 0.6], "model3": [0.5, 0.75, 0.5333333333333333, 0.6666666666666666, 0.5333333333333333], "model4": [0.5625, 0.6875, 0.6, 0.6, 0.4666666666666667], "model5": [0.5625, 0.6875, 0.6, 0.6, 0.6], "model6": [0.5625, 0.5625, 0.6, 0.6666666666666666, 0.4666666666666667], "model7": [0.5625, 0.5, 0.5333333333333333, 0.6, 0.5333333333333333], "model8": [0.5625, 0.6875, 0.5333333333333333, 0.6, 0.5333333333333333], "model9": [0.5625, 0.625, 0.4666666666666667, 0.6, 0.4666666666666667], "model10": [0.5625, 0.5625, 0.5333333333333333, 0.6, 0.4666666666666667], "model11": [0.5625, 0.5625, 0.5333333333333333, 0.6, 0.4666666666666667], "model12": [0.5625, 0.5625, 0.4666666666666667, 0.5333333333333333, 0.5333333333333333], "model13": [0.4375, 0.875, 0.4666666666666667, 0.7333333333333333, 0.5333333333333333], "model14": [0.5, 0.75, 0.4, 0.8, 0.5333333333333333], "model15": [0.625, 0.8125, 0.4, 0.7333333333333333, 0.5333333333333333], "model16": [0.625, 0.8125, 0.4666666666666667, 0.7333333333333333, 0.5333333333333333], "model17": [0.5625, 0.75, 0.5333333333333333, 0.6666666666666666, 0.5333333333333333], "model18": [0.5625, 0.75, 0.4666666666666667, 0.7333333333333333, 0.5333333333333333], "model19": [0.5625, 0.75, 0.4666666666666667, 0.7333333333333333, 0.5333333333333333], "model20": [0.5, 0.6875, 0.5333333333333333, 0.6, 0.5333333333333333], "model21": [0.5, 0.6875, 0.5333333333333333, 0.5333333333333333, 0.5333333333333333], "model22": [0.5, 0.75, 0.5333333333333333, 0.6, 0.5333333333333333], "model23": [0.5, 0.75, 0.5333333333333333, 0.6, 0.5333333333333333], "model24": [0.5, 0.75, 0.5333333333333333, 0.6, 0.5333333333333333], "model25": [0.5625, 0.75, 0.5333333333333333, 0.6, 0.5333333333333333], "model26": [0.625, 0.625, 0.6, 0.7333333333333333, 0.4666666666666667], "model27": [0.375, 0.625, 0.5333333333333333, 0.6666666666666666, 0.5333333333333333], "model28": [0.5625, 0.6875, 0.6, 0.6666666666666666, 0.5333333333333333], "model29": [0.5625, 0.75, 0.6, 0.6666666666666666, 0.4666666666666667], "model30": [0.5625, 0.75, 0.6666666666666666, 0.6666666666666666, 0.5333333333333333], "model31": [0.5625, 0.6875, 0.5333333333333333, 0.5333333333333333, 0.6], "model32": [0.4375, 0.625, 0.5333333333333333, 0.6, 0.5333333333333333], "model33": [0.5, 0.625, 0.5333333333333333, 0.7333333333333333, 0.5333333333333333], "model34": [0.5, 0.625, 0.5333333333333333, 0.6666666666666666, 0.5333333333333333], "model35": [0.5, 0.625, 0.5333333333333333, 0.6666666666666666, 0.5333333333333333], "model36": [0.4375, 0.625, 0.5333333333333333, 0.6, 0.5333333333333333], "model37": [0.4375, 0.625, 0.5333333333333333, 0.6, 0.5333333333333333], "model38": [0.4375, 0.6875, 0.5333333333333333, 0.6666666666666666, 0.5333333333333333], "model39": [0.625, 0.625, 0.6, 0.7333333333333333, 0.4666666666666667], "model40": [0.375, 0.625, 0.5333333333333333, 0.6666666666666666, 0.5333333333333333], "model41": [0.5625, 0.6875, 0.6, 0.6666666666666666, 0.5333333333333333], "model42": [0.5625, 0.75, 0.6, 0.6666666666666666, 0.4666666666666667], "model43": [0.5625, 0.75, 0.6666666666666666, 0.6666666666666666, 0.5333333333333333], "model44": [0.5625, 0.6875, 0.5333333333333333, 0.5333333333333333, 0.6], "model45": [0.4375, 0.625, 0.5333333333333333, 0.6, 0.5333333333333333], "model46": [0.5, 0.625, 0.5333333333333333, 0.7333333333333333, 0.5333333333333333], "model47": [0.5, 0.625, 0.5333333333333333, 0.6666666666666666, 0.5333333333333333], "model48": [0.5, 0.625, 0.5333333333333333, 0.6666666666666666, 0.5333333333333333], "model49": [0.4375, 0.625, 0.5333333333333333, 0.6, 0.5333333333333333], "model50": [0.4375, 0.625, 0.5333333333333333, 0.6, 0.5333333333333333], "model51": [0.4375, 0.6875, 0.5333333333333333, 0.6666666666666666, 0.5333333333333333], "model52": [0.4375, 0.6875, 0.5333333333333333, 0.5333333333333333, 0.3333333333333333], "model53": [0.5, 0.5625, 0.7333333333333333, 0.4, 0.4], "model54": [0.4375, 0.5625, 0.5333333333333333, 0.5333333333333333, 0.5333333333333333], "model55": [0.375, 0.6875, 0.5333333333333333, 0.5333333333333333, 0.4666666666666667], "model56": [0.4375, 0.625, 0.4, 0.6, 0.5333333333333333], "model57": [0.4375, 0.625, 0.5333333333333333, 0.5333333333333333, 0.5333333333333333], "model58": [0.4375, 0.5625, 0.5333333333333333, 0.6, 0.4666666666666667], "model59": [0.5625, 0.5625, 0.5333333333333333, 0.6, 0.4666666666666667], "model60": [0.5625, 0.5625, 0.5333333333333333, 0.6, 0.4666666666666667], "model61": [0.5, 0.5625, 0.5333333333333333, 0.6, 0.4666666666666667], "model62": [0.5625, 0.5625, 0.5333333333333333, 0.6, 0.4666666666666667], "model63": [0.5625, 0.5625, 0.5333333333333333, 0.6, 0.4666666666666667], "model64": [0.5625, 0.5625, 0.5333333333333333, 0.6, 0.4666666666666667], "model65": [0.5625, 0.625, 0.5333333333333333, 0.5333333333333333, 0.4], "model66": [0.5625, 0.5625, 0.5333333333333333, 0.5333333333333333, 0.2], "model67": [0.5625, 0.5625, 0.5333333333333333, 0.5333333333333333, 0.5333333333333333], "model68": [0.5625, 0.625, 0.5333333333333333, 0.6666666666666666, 0.5333333333333333], "model69": [0.5, 0.625, 0.6, 0.6666666666666666, 0.4666666666666667], "model70": [0.5625, 0.625, 0.5333333333333333, 0.6666666666666666, 0.4666666666666667], "model71": [0.5, 0.6875, 0.5333333333333333, 0.6, 0.5333333333333333], "model72": [0.5625, 0.6875, 0.6, 0.6, 0.5333333333333333], "model73": [0.5625, 0.6875, 0.5333333333333333, 0.5333333333333333, 0.5333333333333333], "model74": [0.5625, 0.6875, 0.6, 0.6, 0.5333333333333333], "model75": [0.5625, 0.6875, 0.6, 0.5333333333333333, 0.5333333333333333], "model76": [0.5625, 0.6875, 0.5333333333333333, 0.5333333333333333, 0.5333333333333333], "model77": [0.5625, 0.6875, 0.6, 0.5333333333333333, 0.5333333333333333], "model78": [0.5625, 0.625, 0.5333333333333333, 0.8666666666666667, 0.4], "model79": [0.625, 0.6875, 0.4666666666666667, 0.7333333333333333, 0.4], "model80": [0.5625, 0.5625, 0.6, 0.7333333333333333, 0.5333333333333333], "model81": [0.5625, 0.5625, 0.5333333333333333, 0.6, 0.5333333333333333], "model82": [0.5625, 0.5, 0.4, 0.8, 0.5333333333333333], "model83": [0.5625, 0.5, 0.4, 0.8, 0.5333333333333333], "model84": [0.5625, 0.5625, 0.4, 0.6666666666666666, 0.5333333333333333], "model85": [0.5625, 0.625, 0.5333333333333333, 0.8, 0.4666666666666667], "model86": [0.5625, 0.5625, 0.5333333333333333, 0.7333333333333333, 0.4666666666666667], "model87": [0.5625, 0.5625, 0.5333333333333333, 0.7333333333333333, 0.4666666666666667], "model88": [0.5625, 0.6875, 0.5333333333333333, 0.6666666666666666, 0.4666666666666667], "model89": [0.5625, 0.6875, 0.5333333333333333, 0.6666666666666666, 0.4666666666666667], "model90": [0.5625, 0.6875, 0.4666666666666667, 0.6666666666666666, 0.4666666666666667], "model91": [0.5625, 0.625, 0.5333333333333333, 0.8666666666666667, 0.4], "model92": [0.625, 0.6875, 0.4666666666666667, 0.7333333333333333, 0.4], "model93": [0.5625, 0.5625, 0.6, 0.7333333333333333, 0.5333333333333333], "model94": [0.5625, 0.5625, 0.5333333333333333, 0.6, 0.5333333333333333], "model95": [0.5625, 0.5, 0.4, 0.8, 0.5333333333333333], "model96": [0.5625, 0.5, 0.4, 0.8, 0.5333333333333333], "model97": [0.5625, 0.5625, 0.4, 0.6666666666666666, 0.5333333333333333], "model98": [0.5625, 0.625, 0.5333333333333333, 0.8, 0.4666666666666667], "model99": [0.5625, 0.5625, 0.5333333333333333, 0.7333333333333333, 0.4666666666666667], "model100": [0.5625, 0.5625, 0.5333333333333333, 0.7333333333333333, 0.4666666666666667], "model101": [0.5625, 0.6875, 0.5333333333333333, 0.6666666666666666, 0.4666666666666667], "model102": [0.5625, 0.6875, 0.5333333333333333, 0.6666666666666666, 0.4666666666666667], "model103": [0.5625, 0.6875, 0.4666666666666667, 0.6666666666666666, 0.4666666666666667]}, "roc_auc": {"model0": [0.5793650793650794, 0.634920634920635, 0.41666666666666663, 0.5833333333333334, 0.4285714285714286], "model1": [0.6825396825396826, 0.6746031746031746, 0.3796296296296296, 0.6203703703703703, 0.34821428571428575], "model2": [0.5793650793650793, 0.7380952380952381, 0.4629629629629629, 0.7037037037037037, 0.5714285714285714], "model3": [0.5952380952380952, 0.6746031746031746, 0.43518518518518523, 0.7592592592592593, 0.3839285714285715], "model4": [0.5476190476190477, 0.6507936507936509, 0.46296296296296297, 0.7777777777777779, 0.41964285714285715], "model5": [0.5634920634920635, 0.6190476190476191, 0.4907407407407407, 0.7592592592592593, 0.5], "model6": [0.5793650793650793, 0.5873015873015873, 0.5185185185185185, 0.7407407407407407, 0.5357142857142856], "model7": [0.5555555555555556, 0.5793650793650794, 0.5092592592592593, 0.7314814814814814, 0.5357142857142858], "model8": [0.5396825396825398, 0.6190476190476191, 0.5092592592592592, 0.7592592592592593, 0.5714285714285714], "model9": [0.5396825396825398, 0.6111111111111112, 0.5, 0.7592592592592593, 0.5535714285714286], "model10": [0.5396825396825398, 0.5952380952380952, 0.5277777777777778, 0.7407407407407407, 0.5625], "model11": [0.5476190476190477, 0.611111111111111, 0.5185185185185186, 0.75, 0.5446428571428572], "model12": [0.5555555555555556, 0.611111111111111, 0.5, 0.7407407407407407, 0.5446428571428572], "model13": [0.6428571428571429, 0.746031746031746, 0.4629629629629629, 0.7037037037037037, 0.625], "model14": [0.6111111111111112, 0.6984126984126984, 0.3611111111111111, 0.7592592592592593, 0.4732142857142857], "model15": [0.7222222222222223, 0.753968253968254, 0.39814814814814814, 0.7222222222222222, 0.6607142857142857], "model16": [0.6825396825396826, 0.7619047619047619, 0.4907407407407407, 0.7592592592592593, 0.5178571428571429], "model17": [0.5873015873015873, 0.6904761904761905, 0.4814814814814815, 0.7777777777777778, 0.41071428571428575], "model18": [0.6031746031746033, 0.7142857142857143, 0.5185185185185185, 0.7777777777777778, 0.5089285714285714], "model19": [0.6031746031746033, 0.6666666666666666, 0.4814814814814815, 0.7222222222222223, 0.5178571428571428], "model20": [0.6190476190476191, 0.6666666666666667, 0.5185185185185185, 0.7777777777777778, 0.6428571428571429], "model21": [0.6190476190476191, 0.6666666666666667, 0.537037037037037, 0.7777777777777778, 0.6428571428571429], "model22": [0.6031746031746033, 0.6666666666666667, 0.5185185185185185, 0.7592592592592593, 0.625], "model23": [0.6031746031746033, 0.6507936507936508, 0.5925925925925926, 0.7407407407407407, 0.6607142857142858], "model24": [0.5873015873015873, 0.6507936507936508, 0.5555555555555556, 0.7407407407407407, 0.6785714285714286], "model25": [0.5873015873015873, 0.6349206349206349, 0.537037037037037, 0.7592592592592593, 0.6071428571428572], "model26": [0.6031746031746033, 0.6111111111111112, 0.5833333333333334, 0.6759259259259259, 0.4375], "model27": [0.5079365079365079, 0.5079365079365079, 0.601851851851852, 0.7407407407407407, 0.3392857142857143], "model28": [0.5873015873015872, 0.6825396825396826, 0.5277777777777778, 0.6851851851851851, 0.5714285714285714], "model29": [0.6349206349206349, 0.7301587301587301, 0.5185185185185186, 0.7129629629629629, 0.4107142857142857], "model30": [0.6349206349206349, 0.6190476190476191, 0.5185185185185185, 0.7407407407407407, 0.4285714285714286], "model31": [0.6031746031746033, 0.6666666666666667, 0.4814814814814815, 0.7407407407407407, 0.5357142857142858], "model32": [0.6031746031746033, 0.6190476190476191, 0.462962962962963, 0.7777777777777778, 0.5714285714285714], "model33": [0.6190476190476191, 0.6031746031746031, 0.4629629629629629, 0.8148148148148149, 0.5892857142857143], "model34": [0.6190476190476191, 0.6349206349206349, 0.4814814814814815, 0.8148148148148149, 0.6071428571428572], "model35": [0.6190476190476191, 0.6349206349206349, 0.4814814814814815, 0.7962962962962963, 0.6428571428571428], "model36": [0.6190476190476191, 0.6349206349206349, 0.46296296296296297, 0.7962962962962963, 0.5892857142857143], "model37": [0.6190476190476191, 0.6349206349206349, 0.46296296296296297, 0.7777777777777778, 0.5714285714285714], "model38": [0.6190476190476191, 0.6349206349206349, 0.4444444444444444, 0.7777777777777778, 0.5892857142857143], "model39": [0.6031746031746033, 0.6111111111111112, 0.5833333333333334, 0.6759259259259259, 0.4375], "model40": [0.5079365079365079, 0.5079365079365079, 0.601851851851852, 0.7407407407407407, 0.3392857142857143], "model41": [0.5873015873015872, 0.6825396825396826, 0.5277777777777778, 0.6851851851851851, 0.5714285714285714], "model42": [0.6349206349206349, 0.7301587301587301, 0.5185185185185186, 0.7129629629629629, 0.4107142857142857], "model43": [0.6349206349206349, 0.6190476190476191, 0.5185185185185185, 0.7407407407407407, 0.4285714285714286], "model44": [0.6031746031746033, 0.6666666666666667, 0.4814814814814815, 0.7407407407407407, 0.5357142857142858], "model45": [0.6031746031746033, 0.6190476190476191, 0.462962962962963, 0.7777777777777778, 0.5714285714285714], "model46": [0.6190476190476191, 0.6031746031746031, 0.4629629629629629, 0.8148148148148149, 0.5892857142857143], "model47": [0.6190476190476191, 0.6349206349206349, 0.4814814814814815, 0.8148148148148149, 0.6071428571428572], "model48": [0.6190476190476191, 0.6349206349206349, 0.4814814814814815, 0.7962962962962963, 0.6428571428571428], "model49": [0.6190476190476191, 0.6349206349206349, 0.46296296296296297, 0.7962962962962963, 0.5892857142857143], "model50": [0.6190476190476191, 0.6349206349206349, 0.46296296296296297, 0.7777777777777778, 0.5714285714285714], "model51": [0.6190476190476191, 0.6349206349206349, 0.4444444444444444, 0.7777777777777778, 0.5892857142857143], "model52": [0.5079365079365079, 0.7063492063492064, 0.5740740740740742, 0.3888888888888889, 0.3482142857142857], "model53": [0.5158730158730158, 0.5793650793650794, 0.6203703703703703, 0.33333333333333326, 0.35714285714285715], "model54": [0.47619047619047616, 0.5952380952380952, 0.6111111111111112, 0.5648148148148148, 0.49107142857142855], "model55": [0.4920634920634921, 0.6349206349206349, 0.5648148148148148, 0.638888888888889, 0.4642857142857143], "model56": [0.5079365079365079, 0.5634920634920635, 0.5185185185185185, 0.6944444444444444, 0.4017857142857143], "model57": [0.5158730158730158, 0.5238095238095238, 0.5185185185185186, 0.712962962962963, 0.4017857142857143], "model58": [0.5158730158730158, 0.5317460317460319, 0.5, 0.7407407407407407, 0.4732142857142857], "model59": [0.5555555555555556, 0.5476190476190477, 0.5, 0.787037037037037, 0.5535714285714286], "model60": [0.5634920634920635, 0.5634920634920635, 0.5, 0.7592592592592593, 0.5535714285714286], "model61": [0.5317460317460317, 0.5317460317460317, 0.49074074074074076, 0.7685185185185185, 0.5], "model62": [0.5238095238095237, 0.5793650793650794, 0.49074074074074076, 0.7685185185185186, 0.5357142857142857], "model63": [0.5238095238095237, 0.5634920634920635, 0.4814814814814815, 0.7407407407407407, 0.4821428571428571], "model64": [0.5238095238095237, 0.5952380952380952, 0.4814814814814815, 0.7685185185185186, 0.5267857142857143], "model65": [0.7142857142857143, 0.5634920634920635, 0.5277777777777778, 0.5462962962962963, 0.42857142857142855], "model66": [0.5793650793650794, 0.46031746031746035, 0.4444444444444445, 0.6666666666666667, 0.2410714285714286], "model67": [0.5238095238095238, 0.5873015873015873, 0.4814814814814815, 0.6481481481481481, 0.3660714285714286], "model68": [0.5079365079365079, 0.6031746031746033, 0.5, 0.6481481481481481, 0.3928571428571429], "model69": [0.5158730158730158, 0.5396825396825398, 0.5, 0.7222222222222223, 0.4642857142857143], "model70": [0.5079365079365079, 0.6031746031746033, 0.462962962962963, 0.6851851851851851, 0.4642857142857143], "model71": [0.5238095238095238, 0.6666666666666667, 0.5185185185185186, 0.7222222222222222, 0.5714285714285714], "model72": [0.5555555555555556, 0.6190476190476191, 0.5370370370370371, 0.7037037037037037, 0.5892857142857143], "model73": [0.5555555555555556, 0.6349206349206349, 0.5, 0.7037037037037037, 0.625], "model74": [0.5555555555555556, 0.6349206349206349, 0.5185185185185185, 0.7037037037037037, 0.6607142857142858], "model75": [0.5714285714285714, 0.6349206349206349, 0.5370370370370371, 0.7407407407407407, 0.5357142857142858], "model76": [0.5714285714285714, 0.6349206349206349, 0.5185185185185185, 0.7407407407407407, 0.5178571428571428], "model77": [0.5714285714285714, 0.6507936507936508, 0.5185185185185185, 0.7592592592592593, 0.5535714285714286], "model78": [0.6349206349206349, 0.4920634920634921, 0.5925925925925926, 0.9537037037037037, 0.44642857142857145], "model79": [0.6666666666666666, 0.6190476190476191, 0.6481481481481483, 0.8981481481481481, 0.3392857142857143], "model80": [0.6825396825396826, 0.6111111111111112, 0.6666666666666666, 0.9074074074074074, 0.4821428571428571], "model81": [0.6666666666666667, 0.6031746031746033, 0.5, 0.8333333333333334, 0.5178571428571428], "model82": [0.6031746031746033, 0.5714285714285714, 0.5, 0.8703703703703703, 0.375], "model83": [0.6190476190476191, 0.6031746031746033, 0.37037037037037035, 0.9074074074074074, 0.4821428571428571], "model84": [0.6190476190476191, 0.6031746031746033, 0.5, 0.9074074074074074, 0.6071428571428572], "model85": [0.6190476190476191, 0.5396825396825398, 0.4814814814814815, 0.888888888888889, 0.6607142857142857], "model86": [0.6031746031746033, 0.5714285714285714, 0.46296296296296297, 0.9074074074074074, 0.6785714285714286], "model87": [0.6031746031746033, 0.5873015873015873, 0.462962962962963, 0.888888888888889, 0.6785714285714286], "model88": [0.6190476190476191, 0.6190476190476191, 0.5185185185185185, 0.888888888888889, 0.6428571428571428], "model89": [0.6190476190476191, 0.6190476190476191, 0.5185185185185185, 0.888888888888889, 0.6607142857142857], "model90": [0.6507936507936508, 0.6031746031746033, 0.5185185185185186, 0.8703703703703705, 0.6785714285714286], "model91": [0.6349206349206349, 0.4920634920634921, 0.5925925925925926, 0.9537037037037037, 0.44642857142857145], "model92": [0.6666666666666666, 0.6190476190476191, 0.6481481481481483, 0.8981481481481481, 0.3392857142857143], "model93": [0.6825396825396826, 0.6111111111111112, 0.6666666666666666, 0.9074074074074074, 0.4821428571428571], "model94": [0.6666666666666667, 0.6031746031746033, 0.5, 0.8333333333333334, 0.5178571428571428], "model95": [0.6031746031746033, 0.5714285714285714, 0.5, 0.8703703703703703, 0.375], "model96": [0.6190476190476191, 0.6031746031746033, 0.37037037037037035, 0.9074074074074074, 0.4821428571428571], "model97": [0.6190476190476191, 0.6031746031746033, 0.5, 0.9074074074074074, 0.6071428571428572], "model98": [0.6190476190476191, 0.5396825396825398, 0.4814814814814815, 0.888888888888889, 0.6607142857142857], "model99": [0.6031746031746033, 0.5714285714285714, 0.46296296296296297, 0.9074074074074074, 0.6785714285714286], "model100": [0.6031746031746033, 0.5873015873015873, 0.462962962962963, 0.888888888888889, 0.6785714285714286], "model101": [0.6190476190476191, 0.6190476190476191, 0.5185185185185185, 0.888888888888889, 0.6428571428571428], "model102": [0.6190476190476191, 0.6190476190476191, 0.5185185185185185, 0.888888888888889, 0.6607142857142857], "model103": [0.6507936507936508, 0.6031746031746033, 0.5185185185185186, 0.8703703703703705, 0.6785714285714286]}}