{"model": {"model0": {"C": 0.1, "penalty": "l1", "solver": "liblinear"}, "model1": {"C": 0.1, "penalty": "l1", "solver": "saga"}, "model2": {"C": 0.1, "penalty": "l2", "solver": "liblinear"}, "model3": {"C": 0.1, "penalty": "l2", "solver": "saga"}, "model4": {"C": 0.2, "penalty": "l1", "solver": "liblinear"}, "model5": {"C": 0.2, "penalty": "l1", "solver": "saga"}, "model6": {"C": 0.2, "penalty": "l2", "solver": "liblinear"}, "model7": {"C": 0.2, "penalty": "l2", "solver": "saga"}, "model8": {"C": 0.3, "penalty": "l1", "solver": "liblinear"}, "model9": {"C": 0.3, "penalty": "l1", "solver": "saga"}, "model10": {"C": 0.3, "penalty": "l2", "solver": "liblinear"}, "model11": {"C": 0.3, "penalty": "l2", "solver": "saga"}, "model12": {"C": 0.4, "penalty": "l1", "solver": "liblinear"}, "model13": {"C": 0.4, "penalty": "l1", "solver": "saga"}, "model14": {"C": 0.4, "penalty": "l2", "solver": "liblinear"}, "model15": {"C": 0.4, "penalty": "l2", "solver": "saga"}, "model16": {"C": 0.5, "penalty": "l1", "solver": "liblinear"}, "model17": {"C": 0.5, "penalty": "l1", "solver": "saga"}, "model18": {"C": 0.5, "penalty": "l2", "solver": "liblinear"}, "model19": {"C": 0.5, "penalty": "l2", "solver": "saga"}, "model20": {"C": 0.6, "penalty": "l1", "solver": "liblinear"}, "model21": {"C": 0.6, "penalty": "l1", "solver": "saga"}, "model22": {"C": 0.6, "penalty": "l2", "solver": "liblinear"}, "model23": {"C": 0.6, "penalty": "l2", "solver": "saga"}, "model24": {"C": 0.7, "penalty": "l1", "solver": "liblinear"}, "model25": {"C": 0.7, "penalty": "l1", "solver": "saga"}, "model26": {"C": 0.7, "penalty": "l2", "solver": "liblinear"}, "model27": {"C": 0.7, "penalty": "l2", "solver": "saga"}, "model28": {"C": 0.8, "penalty": "l1", "solver": "liblinear"}, "model29": {"C": 0.8, "penalty": "l1", "solver": "saga"}, "model30": {"C": 0.8, "penalty": "l2", "solver": "liblinear"}, "model31": {"C": 0.8, "penalty": "l2", "solver": "saga"}, "model32": {"C": 0.9, "penalty": "l1", "solver": "liblinear"}, "model33": {"C": 0.9, "penalty": "l1", "solver": "saga"}, "model34": {"C": 0.9, "penalty": "l2", "solver": "liblinear"}, "model35": {"C": 0.9, "penalty": "l2", "solver": "saga"}, "model36": {"C": 1, "penalty": "l1", "solver": "liblinear"}, "model37": {"C": 1, "penalty": "l1", "solver": "saga"}, "model38": {"C": 1, "penalty": "l2", "solver": "liblinear"}, "model39": {"C": 1, "penalty": "l2", "solver": "saga"}, "model40": {"C": 2, "penalty": "l1", "solver": "liblinear"}, "model41": {"C": 2, "penalty": "l1", "solver": "saga"}, "model42": {"C": 2, "penalty": "l2", "solver": "liblinear"}, "model43": {"C": 2, "penalty": "l2", "solver": "saga"}, "model44": {"C": 3, "penalty": "l1", "solver": "liblinear"}, "model45": {"C": 3, "penalty": "l1", "solver": "saga"}, "model46": {"C": 3, "penalty": "l2", "solver": "liblinear"}, "model47": {"C": 3, "penalty": "l2", "solver": "saga"}, "model48": {"C": 4, "penalty": "l1", "solver": "liblinear"}, "model49": {"C": 4, "penalty": "l1", "solver": "saga"}, "model50": {"C": 4, "penalty": "l2", "solver": "liblinear"}, "model51": {"C": 4, "penalty": "l2", "solver": "saga"}, "model52": {"C": 5, "penalty": "l1", "solver": "liblinear"}, "model53": {"C": 5, "penalty": "l1", "solver": "saga"}, "model54": {"C": 5, "penalty": "l2", "solver": "liblinear"}, "model55": {"C": 5, "penalty": "l2", "solver": "saga"}, "model56": {"C": 7, "penalty": "l1", "solver": "liblinear"}, "model57": {"C": 7, "penalty": "l1", "solver": "saga"}, "model58": {"C": 7, "penalty": "l2", "solver": "liblinear"}, "model59": {"C": 7, "penalty": "l2", "solver": "saga"}, "model60": {"C": 9, "penalty": "l1", "solver": "liblinear"}, "model61": {"C": 9, "penalty": "l1", "solver": "saga"}, "model62": {"C": 9, "penalty": "l2", "solver": "liblinear"}, "model63": {"C": 9, "penalty": "l2", "solver": "saga"}, "model64": {"C": 11, "penalty": "l1", "solver": "liblinear"}, "model65": {"C": 11, "penalty": "l1", "solver": "saga"}, "model66": {"C": 11, "penalty": "l2", "solver": "liblinear"}, "model67": {"C": 11, "penalty": "l2", "solver": "saga"}, "model68": {"C": 15, "penalty": "l1", "solver": "liblinear"}, "model69": {"C": 15, "penalty": "l1", "solver": "saga"}, "model70": {"C": 15, "penalty": "l2", "solver": "liblinear"}, "model71": {"C": 15, "penalty": "l2", "solver": "saga"}, "model72": {"C": 20, "penalty": "l1", "solver": "liblinear"}, "model73": {"C": 20, "penalty": "l1", "solver": "saga"}, "model74": {"C": 20, "penalty": "l2", "solver": "liblinear"}, "model75": {"C": 20, "penalty": "l2", "solver": "saga"}, "model76": {"C": 25, "penalty": "l1", "solver": "liblinear"}, "model77": {"C": 25, "penalty": "l1", "solver": "saga"}, "model78": {"C": 25, "penalty": "l2", "solver": "liblinear"}, "model79": {"C": 25, "penalty": "l2", "solver": "saga"}, "model80": {"C": 30, "penalty": "l1", "solver": "liblinear"}, "model81": {"C": 30, "penalty": "l1", "solver": "saga"}, "model82": {"C": 30, "penalty": "l2", "solver": "liblinear"}, "model83": {"C": 30, "penalty": "l2", "solver": "saga"}, "model84": {"C": 35, "penalty": "l1", "solver": "liblinear"}, "model85": {"C": 35, "penalty": "l1", "solver": "saga"}, "model86": {"C": 35, "penalty": "l2", "solver": "liblinear"}, "model87": {"C": 35, "penalty": "l2", "solver": "saga"}, "model88": {"C": 40, "penalty": "l1", "solver": "liblinear"}, "model89": {"C": 40, "penalty": "l1", "solver": "saga"}, "model90": {"C": 40, "penalty": "l2", "solver": "liblinear"}, "model91": {"C": 40, "penalty": "l2", "solver": "saga"}, "model92": {"C": 50, "penalty": "l1", "solver": "liblinear"}, "model93": {"C": 50, "penalty": "l1", "solver": "saga"}, "model94": {"C": 50, "penalty": "l2", "solver": "liblinear"}, "model95": {"C": 50, "penalty": "l2", "solver": "saga"}, "model96": {"C": 100, "penalty": "l1", "solver": "liblinear"}, "model97": {"C": 100, "penalty": "l1", "solver": "saga"}, "model98": {"C": 100, "penalty": "l2", "solver": "liblinear"}, "model99": {"C": 100, "penalty": "l2", "solver": "saga"}}, "precision": {"model0": [0.1368421052631579, 0.0916030534351145, 0.12264150943396226, 0.10679611650485436, 0.06474820143884892], "model1": [0.13829787234042554, 0.09230769230769231, 0.09523809523809523, 0.102803738317757, 0.06802721088435375], "model2": [0.13043478260869565, 0.13636363636363635, 0.16216216216216217, 0.11764705882352941, 0.1262135922330097], "model3": [0.13333333333333333, 0.1348314606741573, 0.16, 0.11594202898550725, 0.11926605504587157], "model4": [0.12790697674418605, 0.1111111111111111, 0.11764705882352941, 0.12345679012345678, 0.08196721311475409], "model5": [0.12941176470588237, 0.11320754716981132, 0.12643678160919541, 0.1111111111111111, 0.088], "model6": [0.140625, 0.14814814814814814, 0.1323529411764706, 0.125, 0.13541666666666666], "model7": [0.125, 0.1411764705882353, 0.16901408450704225, 0.11940298507462686, 0.13], "model8": [0.13253012048192772, 0.12244897959183673, 0.136986301369863, 0.13580246913580246, 0.09433962264150944], "model9": [0.1375, 0.125, 0.13414634146341464, 0.1232876712328767, 0.1], "model10": [0.11475409836065574, 0.15, 0.12121212121212122, 0.13559322033898305, 0.1511627906976744], "model11": [0.1267605633802817, 0.1411764705882353, 0.1323529411764706, 0.11940298507462686, 0.13402061855670103], "model12": [0.125, 0.125, 0.12857142857142856, 0.13513513513513514, 0.10204081632653061], "model13": [0.1375, 0.13953488372093023, 0.13095238095238096, 0.14285714285714285, 0.11214953271028037], "model14": [0.13114754098360656, 0.15384615384615385, 0.12903225806451613, 0.13559322033898305, 0.14942528735632185], "model15": [0.1267605633802817, 0.1411764705882353, 0.1323529411764706, 0.11940298507462686, 0.13402061855670103], "model16": [0.125, 0.11827956989247312, 0.11764705882352941, 0.13043478260869565, 0.11458333333333333], "model17": [0.12162162162162163, 0.14634146341463414, 0.1375, 0.14705882352941177, 0.12149532710280374], "model18": [0.13333333333333333, 0.15584415584415584, 0.12698412698412698, 0.13793103448275862, 0.15555555555555556], "model19": [0.1323529411764706, 0.1411764705882353, 0.1323529411764706, 0.11940298507462686, 0.13541666666666666], "model20": [0.10126582278481013, 0.12359550561797752, 0.11940298507462686, 0.11940298507462686, 0.11578947368421053], "model21": [0.12162162162162163, 0.14814814814814814, 0.13333333333333333, 0.14925373134328357, 0.12745098039215685], "model22": [0.13114754098360656, 0.15789473684210525, 0.125, 0.13793103448275862, 0.1590909090909091], "model23": [0.13636363636363635, 0.1411764705882353, 0.1323529411764706, 0.11940298507462686, 0.13541666666666666], "model24": [0.10256410256410256, 0.12087912087912088, 0.11940298507462686, 0.11940298507462686, 0.11956521739130435], "model25": [0.12162162162162163, 0.14285714285714285, 0.1232876712328767, 0.15151515151515152, 0.13], "model26": [0.12903225806451613, 0.15584415584415584, 0.12307692307692308, 0.14035087719298245, 0.14772727272727273], "model27": [0.13636363636363635, 0.1411764705882353, 0.13432835820895522, 0.12307692307692308, 0.13541666666666666], "model28": [0.10526315789473684, 0.1348314606741573, 0.11764705882352941, 0.12307692307692308, 0.11578947368421053], "model29": [0.12162162162162163, 0.14285714285714285, 0.1232876712328767, 0.13636363636363635, 0.13131313131313133], "model30": [0.14285714285714285, 0.15584415584415584, 0.125, 0.14285714285714285, 0.14942528735632185], "model31": [0.13636363636363635, 0.14285714285714285, 0.13432835820895522, 0.12307692307692308, 0.1368421052631579], "model32": [0.09876543209876543, 0.13636363636363635, 0.1111111111111111, 0.13636363636363635, 0.1276595744680851], "model33": [0.125, 0.13953488372093023, 0.1267605633802817, 0.13636363636363635, 0.1326530612244898], "model34": [0.140625, 0.15584415584415584, 0.12698412698412698, 0.14545454545454545, 0.1511627906976744], "model35": [0.13432835820895522, 0.14285714285714285, 0.13432835820895522, 0.12307692307692308, 0.1368421052631579], "model36": [0.10810810810810811, 0.14942528735632185, 0.11428571428571428, 0.13636363636363635, 0.1276595744680851], "model37": [0.125, 0.14285714285714285, 0.12857142857142856, 0.13432835820895522, 0.1326530612244898], "model38": [0.13846153846153847, 0.14473684210526316, 0.12698412698412698, 0.1509433962264151, 0.15476190476190477], "model39": [0.13432835820895522, 0.14285714285714285, 0.13432835820895522, 0.12307692307692308, 0.1368421052631579], "model40": [0.10810810810810811, 0.13186813186813187, 0.1095890410958904, 0.11475409836065574, 0.12643678160919541], "model41": [0.1323529411764706, 0.14457831325301204, 0.13043478260869565, 0.12307692307692308, 0.1368421052631579], "model42": [0.13846153846153847, 0.13924050632911392, 0.125, 0.12962962962962962, 0.16049382716049382], "model43": [0.13846153846153847, 0.14285714285714285, 0.13432835820895522, 0.12307692307692308, 0.13829787234042554], "model44": [0.11428571428571428, 0.1348314606741573, 0.11267605633802817, 0.11864406779661017, 0.12790697674418605], "model45": [0.13432835820895522, 0.14457831325301204, 0.13432835820895522, 0.12307692307692308, 0.13829787234042554], "model46": [0.140625, 0.12, 0.11666666666666667, 0.1320754716981132, 0.1625], "model47": [0.13846153846153847, 0.14285714285714285, 0.13432835820895522, 0.12307692307692308, 0.13829787234042554], "model48": [0.10810810810810811, 0.13253012048192772, 0.10294117647058823, 0.12962962962962962, 0.125], "model49": [0.13636363636363635, 0.14634146341463414, 0.13432835820895522, 0.12307692307692308, 0.14130434782608695], "model50": [0.140625, 0.12, 0.11864406779661017, 0.125, 0.1625], "model51": [0.13846153846153847, 0.14285714285714285, 0.13432835820895522, 0.12307692307692308, 0.13978494623655913], "model52": [0.1232876712328767, 0.13253012048192772, 0.1, 0.12727272727272726, 0.12222222222222222], "model53": [0.13432835820895522, 0.14457831325301204, 0.13432835820895522, 0.12307692307692308, 0.14285714285714285], "model54": [0.14516129032258066, 0.125, 0.11864406779661017, 0.125, 0.1625], "model55": [0.13846153846153847, 0.14457831325301204, 0.13432835820895522, 0.12307692307692308, 0.14130434782608695], "model56": [0.1232876712328767, 0.12222222222222222, 0.09722222222222222, 0.1206896551724138, 0.125], "model57": [0.13636363636363635, 0.14285714285714285, 0.13432835820895522, 0.12307692307692308, 0.14285714285714285], "model58": [0.14516129032258066, 0.1232876712328767, 0.11475409836065574, 0.1206896551724138, 0.15853658536585366], "model59": [0.140625, 0.14457831325301204, 0.13432835820895522, 0.12307692307692308, 0.14130434782608695], "model60": [0.12857142857142856, 0.125, 0.0958904109589041, 0.125, 0.12790697674418605], "model61": [0.140625, 0.14285714285714285, 0.13432835820895522, 0.12307692307692308, 0.14285714285714285], "model62": [0.14516129032258066, 0.11688311688311688, 0.11864406779661017, 0.13559322033898305, 0.15853658536585366], "model63": [0.140625, 0.14457831325301204, 0.13432835820895522, 0.12307692307692308, 0.14285714285714285], "model64": [0.13043478260869565, 0.12658227848101267, 0.09722222222222222, 0.12903225806451613, 0.12790697674418605], "model65": [0.13846153846153847, 0.14285714285714285, 0.13432835820895522, 0.12307692307692308, 0.14285714285714285], "model66": [0.14285714285714285, 0.12658227848101267, 0.12280701754385964, 0.13559322033898305, 0.15476190476190477], "model67": [0.140625, 0.14457831325301204, 0.13432835820895522, 0.12307692307692308, 0.14285714285714285], "model68": [0.140625, 0.12658227848101267, 0.1044776119402985, 0.13114754098360656, 0.11494252873563218], "model69": [0.13846153846153847, 0.14285714285714285, 0.13432835820895522, 0.12307692307692308, 0.14285714285714285], "model70": [0.13846153846153847, 0.1282051282051282, 0.12727272727272726, 0.14035087719298245, 0.15853658536585366], "model71": [0.140625, 0.14457831325301204, 0.13432835820895522, 0.12307692307692308, 0.14285714285714285], "model72": [0.11940298507462686, 0.13095238095238096, 0.10606060606060606, 0.12698412698412698, 0.12941176470588237], "model73": [0.13846153846153847, 0.14457831325301204, 0.13432835820895522, 0.12307692307692308, 0.14285714285714285], "model74": [0.13846153846153847, 0.12658227848101267, 0.11475409836065574, 0.14035087719298245, 0.16049382716049382], "model75": [0.140625, 0.14457831325301204, 0.13432835820895522, 0.12307692307692308, 0.14285714285714285], "model76": [0.11764705882352941, 0.11764705882352941, 0.1044776119402985, 0.11538461538461539, 0.11764705882352941], "model77": [0.13846153846153847, 0.14457831325301204, 0.13432835820895522, 0.12307692307692308, 0.14285714285714285], "model78": [0.140625, 0.12658227848101267, 0.11864406779661017, 0.13559322033898305, 0.1566265060240964], "model79": [0.140625, 0.14457831325301204, 0.13432835820895522, 0.12307692307692308, 0.14285714285714285], "model80": [0.11940298507462686, 0.125, 0.10294117647058823, 0.1111111111111111, 0.12643678160919541], "model81": [0.13846153846153847, 0.14457831325301204, 0.13432835820895522, 0.12307692307692308, 0.14285714285714285], "model82": [0.15625, 0.125, 0.11864406779661017, 0.13793103448275862, 0.1566265060240964], "model83": [0.140625, 0.14457831325301204, 0.13432835820895522, 0.12307692307692308, 0.14285714285714285], "model84": [0.1323529411764706, 0.11764705882352941, 0.11764705882352941, 0.12698412698412698, 0.12345679012345678], "model85": [0.13846153846153847, 0.14457831325301204, 0.13432835820895522, 0.12307692307692308, 0.14285714285714285], "model86": [0.14285714285714285, 0.12345679012345678, 0.1206896551724138, 0.13333333333333333, 0.16049382716049382], "model87": [0.140625, 0.14457831325301204, 0.13432835820895522, 0.12307692307692308, 0.14285714285714285], "model88": [0.11428571428571428, 0.11764705882352941, 0.10606060606060606, 0.12698412698412698, 0.12345679012345678], "model89": [0.13846153846153847, 0.14457831325301204, 0.13432835820895522, 0.12307692307692308, 0.14285714285714285], "model90": [0.140625, 0.12987012987012986, 0.11864406779661017, 0.13114754098360656, 0.16049382716049382], "model91": [0.140625, 0.14457831325301204, 0.13432835820895522, 0.12307692307692308, 0.14285714285714285], "model92": [0.13043478260869565, 0.12195121951219512, 0.1, 0.10526315789473684, 0.12195121951219512], "model93": [0.13846153846153847, 0.14457831325301204, 0.13432835820895522, 0.12307692307692308, 0.14285714285714285], "model94": [0.14925373134328357, 0.125, 0.11475409836065574, 0.13333333333333333, 0.16049382716049382], "model95": [0.140625, 0.14457831325301204, 0.13432835820895522, 0.12307692307692308, 0.14285714285714285], "model96": [0.1267605633802817, 0.1125, 0.11594202898550725, 0.10526315789473684, 0.12941176470588237], "model97": [0.140625, 0.14457831325301204, 0.13432835820895522, 0.12307692307692308, 0.14285714285714285], "model98": [0.13043478260869565, 0.12658227848101267, 0.1111111111111111, 0.12698412698412698, 0.1566265060240964], "model99": [0.140625, 0.14457831325301204, 0.13432835820895522, 0.12307692307692308, 0.14285714285714285]}, "recall": {"model0": [0.3939393939393939, 0.36363636363636365, 0.3939393939393939, 0.3333333333333333, 0.2727272727272727], "model1": [0.3939393939393939, 0.36363636363636365, 0.30303030303030304, 0.3333333333333333, 0.30303030303030304], "model2": [0.2727272727272727, 0.36363636363636365, 0.36363636363636365, 0.24242424242424243, 0.3939393939393939], "model3": [0.30303030303030304, 0.36363636363636365, 0.36363636363636365, 0.24242424242424243, 0.3939393939393939], "model4": [0.3333333333333333, 0.36363636363636365, 0.30303030303030304, 0.30303030303030304, 0.30303030303030304], "model5": [0.3333333333333333, 0.36363636363636365, 0.3333333333333333, 0.2727272727272727, 0.3333333333333333], "model6": [0.2727272727272727, 0.36363636363636365, 0.2727272727272727, 0.24242424242424243, 0.3939393939393939], "model7": [0.2727272727272727, 0.36363636363636365, 0.36363636363636365, 0.24242424242424243, 0.3939393939393939], "model8": [0.3333333333333333, 0.36363636363636365, 0.30303030303030304, 0.3333333333333333, 0.30303030303030304], "model9": [0.3333333333333333, 0.36363636363636365, 0.3333333333333333, 0.2727272727272727, 0.36363636363636365], "model10": [0.21212121212121213, 0.36363636363636365, 0.24242424242424243, 0.24242424242424243, 0.3939393939393939], "model11": [0.2727272727272727, 0.36363636363636365, 0.2727272727272727, 0.24242424242424243, 0.3939393939393939], "model12": [0.30303030303030304, 0.36363636363636365, 0.2727272727272727, 0.30303030303030304, 0.30303030303030304], "model13": [0.3333333333333333, 0.36363636363636365, 0.3333333333333333, 0.30303030303030304, 0.36363636363636365], "model14": [0.24242424242424243, 0.36363636363636365, 0.24242424242424243, 0.24242424242424243, 0.3939393939393939], "model15": [0.2727272727272727, 0.36363636363636365, 0.2727272727272727, 0.24242424242424243, 0.3939393939393939], "model16": [0.30303030303030304, 0.3333333333333333, 0.24242424242424243, 0.2727272727272727, 0.3333333333333333], "model17": [0.2727272727272727, 0.36363636363636365, 0.3333333333333333, 0.30303030303030304, 0.3939393939393939], "model18": [0.24242424242424243, 0.36363636363636365, 0.24242424242424243, 0.24242424242424243, 0.42424242424242425], "model19": [0.2727272727272727, 0.36363636363636365, 0.2727272727272727, 0.24242424242424243, 0.3939393939393939], "model20": [0.24242424242424243, 0.3333333333333333, 0.24242424242424243, 0.24242424242424243, 0.3333333333333333], "model21": [0.2727272727272727, 0.36363636363636365, 0.30303030303030304, 0.30303030303030304, 0.3939393939393939], "model22": [0.24242424242424243, 0.36363636363636365, 0.24242424242424243, 0.24242424242424243, 0.42424242424242425], "model23": [0.2727272727272727, 0.36363636363636365, 0.2727272727272727, 0.24242424242424243, 0.3939393939393939], "model24": [0.24242424242424243, 0.3333333333333333, 0.24242424242424243, 0.24242424242424243, 0.3333333333333333], "model25": [0.2727272727272727, 0.36363636363636365, 0.2727272727272727, 0.30303030303030304, 0.3939393939393939], "model26": [0.24242424242424243, 0.36363636363636365, 0.24242424242424243, 0.24242424242424243, 0.3939393939393939], "model27": [0.2727272727272727, 0.36363636363636365, 0.2727272727272727, 0.24242424242424243, 0.3939393939393939], "model28": [0.24242424242424243, 0.36363636363636365, 0.24242424242424243, 0.24242424242424243, 0.3333333333333333], "model29": [0.2727272727272727, 0.36363636363636365, 0.2727272727272727, 0.2727272727272727, 0.3939393939393939], "model30": [0.2727272727272727, 0.36363636363636365, 0.24242424242424243, 0.24242424242424243, 0.3939393939393939], "model31": [0.2727272727272727, 0.36363636363636365, 0.2727272727272727, 0.24242424242424243, 0.3939393939393939], "model32": [0.24242424242424243, 0.36363636363636365, 0.24242424242424243, 0.2727272727272727, 0.36363636363636365], "model33": [0.2727272727272727, 0.36363636363636365, 0.2727272727272727, 0.2727272727272727, 0.3939393939393939], "model34": [0.2727272727272727, 0.36363636363636365, 0.24242424242424243, 0.24242424242424243, 0.3939393939393939], "model35": [0.2727272727272727, 0.36363636363636365, 0.2727272727272727, 0.24242424242424243, 0.3939393939393939], "model36": [0.24242424242424243, 0.3939393939393939, 0.24242424242424243, 0.2727272727272727, 0.36363636363636365], "model37": [0.2727272727272727, 0.36363636363636365, 0.2727272727272727, 0.2727272727272727, 0.3939393939393939], "model38": [0.2727272727272727, 0.3333333333333333, 0.24242424242424243, 0.24242424242424243, 0.3939393939393939], "model39": [0.2727272727272727, 0.36363636363636365, 0.2727272727272727, 0.24242424242424243, 0.3939393939393939], "model40": [0.24242424242424243, 0.36363636363636365, 0.24242424242424243, 0.21212121212121213, 0.3333333333333333], "model41": [0.2727272727272727, 0.36363636363636365, 0.2727272727272727, 0.24242424242424243, 0.3939393939393939], "model42": [0.2727272727272727, 0.3333333333333333, 0.24242424242424243, 0.21212121212121213, 0.3939393939393939], "model43": [0.2727272727272727, 0.36363636363636365, 0.2727272727272727, 0.24242424242424243, 0.3939393939393939], "model44": [0.24242424242424243, 0.36363636363636365, 0.24242424242424243, 0.21212121212121213, 0.3333333333333333], "model45": [0.2727272727272727, 0.36363636363636365, 0.2727272727272727, 0.24242424242424243, 0.3939393939393939], "model46": [0.2727272727272727, 0.2727272727272727, 0.21212121212121213, 0.21212121212121213, 0.3939393939393939], "model47": [0.2727272727272727, 0.36363636363636365, 0.2727272727272727, 0.24242424242424243, 0.3939393939393939], "model48": [0.24242424242424243, 0.3333333333333333, 0.21212121212121213, 0.21212121212121213, 0.3333333333333333], "model49": [0.2727272727272727, 0.36363636363636365, 0.2727272727272727, 0.24242424242424243, 0.3939393939393939], "model50": [0.2727272727272727, 0.2727272727272727, 0.21212121212121213, 0.21212121212121213, 0.3939393939393939], "model51": [0.2727272727272727, 0.36363636363636365, 0.2727272727272727, 0.24242424242424243, 0.3939393939393939], "model52": [0.2727272727272727, 0.3333333333333333, 0.21212121212121213, 0.21212121212121213, 0.3333333333333333], "model53": [0.2727272727272727, 0.36363636363636365, 0.2727272727272727, 0.24242424242424243, 0.3939393939393939], "model54": [0.2727272727272727, 0.2727272727272727, 0.21212121212121213, 0.21212121212121213, 0.3939393939393939], "model55": [0.2727272727272727, 0.36363636363636365, 0.2727272727272727, 0.24242424242424243, 0.3939393939393939], "model56": [0.2727272727272727, 0.3333333333333333, 0.21212121212121213, 0.21212121212121213, 0.3333333333333333], "model57": [0.2727272727272727, 0.36363636363636365, 0.2727272727272727, 0.24242424242424243, 0.3939393939393939], "model58": [0.2727272727272727, 0.2727272727272727, 0.21212121212121213, 0.21212121212121213, 0.3939393939393939], "model59": [0.2727272727272727, 0.36363636363636365, 0.2727272727272727, 0.24242424242424243, 0.3939393939393939], "model60": [0.2727272727272727, 0.3333333333333333, 0.21212121212121213, 0.21212121212121213, 0.3333333333333333], "model61": [0.2727272727272727, 0.36363636363636365, 0.2727272727272727, 0.24242424242424243, 0.3939393939393939], "model62": [0.2727272727272727, 0.2727272727272727, 0.21212121212121213, 0.24242424242424243, 0.3939393939393939], "model63": [0.2727272727272727, 0.36363636363636365, 0.2727272727272727, 0.24242424242424243, 0.3939393939393939], "model64": [0.2727272727272727, 0.30303030303030304, 0.21212121212121213, 0.24242424242424243, 0.3333333333333333], "model65": [0.2727272727272727, 0.36363636363636365, 0.2727272727272727, 0.24242424242424243, 0.3939393939393939], "model66": [0.2727272727272727, 0.30303030303030304, 0.21212121212121213, 0.24242424242424243, 0.3939393939393939], "model67": [0.2727272727272727, 0.36363636363636365, 0.2727272727272727, 0.24242424242424243, 0.3939393939393939], "model68": [0.2727272727272727, 0.30303030303030304, 0.21212121212121213, 0.24242424242424243, 0.30303030303030304], "model69": [0.2727272727272727, 0.36363636363636365, 0.2727272727272727, 0.24242424242424243, 0.3939393939393939], "model70": [0.2727272727272727, 0.30303030303030304, 0.21212121212121213, 0.24242424242424243, 0.3939393939393939], "model71": [0.2727272727272727, 0.36363636363636365, 0.2727272727272727, 0.24242424242424243, 0.3939393939393939], "model72": [0.24242424242424243, 0.3333333333333333, 0.21212121212121213, 0.24242424242424243, 0.3333333333333333], "model73": [0.2727272727272727, 0.36363636363636365, 0.2727272727272727, 0.24242424242424243, 0.3939393939393939], "model74": [0.2727272727272727, 0.30303030303030304, 0.21212121212121213, 0.24242424242424243, 0.3939393939393939], "model75": [0.2727272727272727, 0.36363636363636365, 0.2727272727272727, 0.24242424242424243, 0.3939393939393939], "model76": [0.24242424242424243, 0.30303030303030304, 0.21212121212121213, 0.18181818181818182, 0.30303030303030304], "model77": [0.2727272727272727, 0.36363636363636365, 0.2727272727272727, 0.24242424242424243, 0.3939393939393939], "model78": [0.2727272727272727, 0.30303030303030304, 0.21212121212121213, 0.24242424242424243, 0.3939393939393939], "model79": [0.2727272727272727, 0.36363636363636365, 0.2727272727272727, 0.24242424242424243, 0.3939393939393939], "model80": [0.24242424242424243, 0.2727272727272727, 0.21212121212121213, 0.18181818181818182, 0.3333333333333333], "model81": [0.2727272727272727, 0.36363636363636365, 0.2727272727272727, 0.24242424242424243, 0.3939393939393939], "model82": [0.30303030303030304, 0.30303030303030304, 0.21212121212121213, 0.24242424242424243, 0.3939393939393939], "model83": [0.2727272727272727, 0.36363636363636365, 0.2727272727272727, 0.24242424242424243, 0.3939393939393939], "model84": [0.2727272727272727, 0.30303030303030304, 0.24242424242424243, 0.24242424242424243, 0.30303030303030304], "model85": [0.2727272727272727, 0.36363636363636365, 0.2727272727272727, 0.24242424242424243, 0.3939393939393939], "model86": [0.2727272727272727, 0.30303030303030304, 0.21212121212121213, 0.24242424242424243, 0.3939393939393939], "model87": [0.2727272727272727, 0.36363636363636365, 0.2727272727272727, 0.24242424242424243, 0.3939393939393939], "model88": [0.24242424242424243, 0.30303030303030304, 0.21212121212121213, 0.24242424242424243, 0.30303030303030304], "model89": [0.2727272727272727, 0.36363636363636365, 0.2727272727272727, 0.24242424242424243, 0.3939393939393939], "model90": [0.2727272727272727, 0.30303030303030304, 0.21212121212121213, 0.24242424242424243, 0.3939393939393939], "model91": [0.2727272727272727, 0.36363636363636365, 0.2727272727272727, 0.24242424242424243, 0.3939393939393939], "model92": [0.2727272727272727, 0.30303030303030304, 0.21212121212121213, 0.18181818181818182, 0.30303030303030304], "model93": [0.2727272727272727, 0.36363636363636365, 0.2727272727272727, 0.24242424242424243, 0.3939393939393939], "model94": [0.30303030303030304, 0.30303030303030304, 0.21212121212121213, 0.24242424242424243, 0.3939393939393939], "model95": [0.2727272727272727, 0.36363636363636365, 0.2727272727272727, 0.24242424242424243, 0.3939393939393939], "model96": [0.2727272727272727, 0.2727272727272727, 0.24242424242424243, 0.18181818181818182, 0.3333333333333333], "model97": [0.2727272727272727, 0.36363636363636365, 0.2727272727272727, 0.24242424242424243, 0.3939393939393939], "model98": [0.2727272727272727, 0.30303030303030304, 0.21212121212121213, 0.24242424242424243, 0.3939393939393939], "model99": [0.2727272727272727, 0.36363636363636365, 0.2727272727272727, 0.24242424242424243, 0.3939393939393939]}, "f1": {"model0": [0.203125, 0.14634146341463414, 0.18705035971223022, 0.16176470588235295, 0.10465116279069768], "model1": [0.2047244094488189, 0.147239263803681, 0.14492753623188406, 0.15714285714285714, 0.1111111111111111], "model2": [0.17647058823529413, 0.19834710743801653, 0.22429906542056074, 0.15841584158415842, 0.19117647058823528], "model3": [0.18518518518518517, 0.19672131147540983, 0.2222222222222222, 0.1568627450980392, 0.18309859154929578], "model4": [0.18487394957983194, 0.1702127659574468, 0.1694915254237288, 0.17543859649122806, 0.12903225806451613], "model5": [0.1864406779661017, 0.17266187050359713, 0.18333333333333332, 0.15789473684210525, 0.13924050632911392], "model6": [0.18556701030927836, 0.21052631578947367, 0.1782178217821782, 0.16494845360824742, 0.20155038759689922], "model7": [0.17142857142857143, 0.2033898305084746, 0.23076923076923078, 0.16, 0.19548872180451127], "model8": [0.1896551724137931, 0.183206106870229, 0.18867924528301888, 0.19298245614035087, 0.14388489208633093], "model9": [0.19469026548672566, 0.18604651162790697, 0.19130434782608696, 0.16981132075471697, 0.1568627450980392], "model10": [0.14893617021276595, 0.21238938053097345, 0.16161616161616163, 0.17391304347826086, 0.2184873949579832], "model11": [0.17307692307692307, 0.2033898305084746, 0.1782178217821782, 0.16, 0.2], "model12": [0.17699115044247787, 0.18604651162790697, 0.17475728155339806, 0.18691588785046728, 0.15267175572519084], "model13": [0.19469026548672566, 0.20168067226890757, 0.18803418803418803, 0.1941747572815534, 0.17142857142857143], "model14": [0.1702127659574468, 0.21621621621621623, 0.16842105263157894, 0.17391304347826086, 0.21666666666666667], "model15": [0.17307692307692307, 0.2033898305084746, 0.1782178217821782, 0.16, 0.2], "model16": [0.17699115044247787, 0.1746031746031746, 0.15841584158415842, 0.17647058823529413, 0.17054263565891473], "model17": [0.16822429906542055, 0.20869565217391303, 0.19469026548672566, 0.19801980198019803, 0.18571428571428572], "model18": [0.17204301075268819, 0.21818181818181817, 0.16666666666666666, 0.17582417582417584, 0.22764227642276422], "model19": [0.1782178217821782, 0.2033898305084746, 0.1782178217821782, 0.16, 0.20155038759689922], "model20": [0.14285714285714285, 0.18032786885245902, 0.16, 0.16, 0.171875], "model21": [0.16822429906542055, 0.21052631578947367, 0.18518518518518517, 0.2, 0.1925925925925926], "model22": [0.1702127659574468, 0.22018348623853212, 0.16494845360824742, 0.17582417582417584, 0.23140495867768596], "model23": [0.18181818181818182, 0.2033898305084746, 0.1782178217821782, 0.16, 0.20155038759689922], "model24": [0.14414414414414414, 0.1774193548387097, 0.16, 0.16, 0.176], "model25": [0.16822429906542055, 0.20512820512820512, 0.16981132075471697, 0.20202020202020202, 0.19548872180451127], "model26": [0.16842105263157894, 0.21818181818181817, 0.16326530612244897, 0.17777777777777778, 0.21487603305785125], "model27": [0.18181818181818182, 0.2033898305084746, 0.18, 0.16326530612244897, 0.20155038759689922], "model28": [0.14678899082568808, 0.19672131147540983, 0.15841584158415842, 0.16326530612244897, 0.171875], "model29": [0.16822429906542055, 0.20512820512820512, 0.16981132075471697, 0.18181818181818182, 0.19696969696969696], "model30": [0.1875, 0.21818181818181817, 0.16494845360824742, 0.1797752808988764, 0.21666666666666667], "model31": [0.18181818181818182, 0.20512820512820512, 0.18, 0.16326530612244897, 0.203125], "model32": [0.14035087719298245, 0.19834710743801653, 0.1523809523809524, 0.18181818181818182, 0.1889763779527559], "model33": [0.17142857142857143, 0.20168067226890757, 0.17307692307692307, 0.18181818181818182, 0.1984732824427481], "model34": [0.18556701030927836, 0.21818181818181817, 0.16666666666666666, 0.18181818181818182, 0.2184873949579832], "model35": [0.18, 0.20512820512820512, 0.18, 0.16326530612244897, 0.203125], "model36": [0.14953271028037382, 0.21666666666666667, 0.1553398058252427, 0.18181818181818182, 0.1889763779527559], "model37": [0.17142857142857143, 0.20512820512820512, 0.17475728155339806, 0.18, 0.1984732824427481], "model38": [0.1836734693877551, 0.2018348623853211, 0.16666666666666666, 0.18604651162790697, 0.2222222222222222], "model39": [0.18, 0.20512820512820512, 0.18, 0.16326530612244897, 0.203125], "model40": [0.14953271028037382, 0.1935483870967742, 0.1509433962264151, 0.14893617021276595, 0.18333333333333332], "model41": [0.1782178217821782, 0.20689655172413793, 0.17647058823529413, 0.16326530612244897, 0.203125], "model42": [0.1836734693877551, 0.19642857142857142, 0.16494845360824742, 0.16091954022988506, 0.22807017543859648], "model43": [0.1836734693877551, 0.20512820512820512, 0.18, 0.16326530612244897, 0.2047244094488189], "model44": [0.1553398058252427, 0.19672131147540983, 0.15384615384615385, 0.15217391304347827, 0.18487394957983194], "model45": [0.18, 0.20689655172413793, 0.18, 0.16326530612244897, 0.2047244094488189], "model46": [0.18556701030927836, 0.16666666666666666, 0.15053763440860216, 0.16279069767441862, 0.23008849557522124], "model47": [0.1836734693877551, 0.20512820512820512, 0.18, 0.16326530612244897, 0.2047244094488189], "model48": [0.14953271028037382, 0.1896551724137931, 0.13861386138613863, 0.16091954022988506, 0.18181818181818182], "model49": [0.18181818181818182, 0.20869565217391303, 0.18, 0.16326530612244897, 0.208], "model50": [0.18556701030927836, 0.16666666666666666, 0.15217391304347827, 0.15730337078651685, 0.23008849557522124], "model51": [0.1836734693877551, 0.20512820512820512, 0.18, 0.16326530612244897, 0.20634920634920634], "model52": [0.16981132075471697, 0.1896551724137931, 0.13592233009708737, 0.1590909090909091, 0.17886178861788618], "model53": [0.18, 0.20689655172413793, 0.18, 0.16326530612244897, 0.20967741935483872], "model54": [0.18947368421052632, 0.17142857142857143, 0.15217391304347827, 0.15730337078651685, 0.23008849557522124], "model55": [0.1836734693877551, 0.20689655172413793, 0.18, 0.16326530612244897, 0.208], "model56": [0.16981132075471697, 0.17886178861788618, 0.13333333333333333, 0.15384615384615385, 0.18181818181818182], "model57": [0.18181818181818182, 0.20512820512820512, 0.18, 0.16326530612244897, 0.20967741935483872], "model58": [0.18947368421052632, 0.16981132075471697, 0.14893617021276595, 0.15384615384615385, 0.22608695652173913], "model59": [0.18556701030927836, 0.20689655172413793, 0.18, 0.16326530612244897, 0.208], "model60": [0.17475728155339806, 0.18181818181818182, 0.1320754716981132, 0.15730337078651685, 0.18487394957983194], "model61": [0.18556701030927836, 0.20512820512820512, 0.18, 0.16326530612244897, 0.20967741935483872], "model62": [0.18947368421052632, 0.16363636363636364, 0.15217391304347827, 0.17391304347826086, 0.22608695652173913], "model63": [0.18556701030927836, 0.20689655172413793, 0.18, 0.16326530612244897, 0.20967741935483872], "model64": [0.17647058823529413, 0.17857142857142858, 0.13333333333333333, 0.16842105263157894, 0.18487394957983194], "model65": [0.1836734693877551, 0.20512820512820512, 0.18, 0.16326530612244897, 0.20967741935483872], "model66": [0.1875, 0.17857142857142858, 0.15555555555555556, 0.17391304347826086, 0.2222222222222222], "model67": [0.18556701030927836, 0.20689655172413793, 0.18, 0.16326530612244897, 0.20967741935483872], "model68": [0.18556701030927836, 0.17857142857142858, 0.14, 0.1702127659574468, 0.16666666666666666], "model69": [0.1836734693877551, 0.20512820512820512, 0.18, 0.16326530612244897, 0.20967741935483872], "model70": [0.1836734693877551, 0.18018018018018017, 0.1590909090909091, 0.17777777777777778, 0.22608695652173913], "model71": [0.18556701030927836, 0.20689655172413793, 0.18, 0.16326530612244897, 0.20967741935483872], "model72": [0.16, 0.18803418803418803, 0.1414141414141414, 0.16666666666666666, 0.1864406779661017], "model73": [0.1836734693877551, 0.20689655172413793, 0.18, 0.16326530612244897, 0.20967741935483872], "model74": [0.1836734693877551, 0.17857142857142858, 0.14893617021276595, 0.17777777777777778, 0.22807017543859648], "model75": [0.18556701030927836, 0.20689655172413793, 0.18, 0.16326530612244897, 0.20967741935483872], "model76": [0.15841584158415842, 0.1694915254237288, 0.14, 0.1411764705882353, 0.1694915254237288], "model77": [0.1836734693877551, 0.20689655172413793, 0.18, 0.16326530612244897, 0.20967741935483872], "model78": [0.18556701030927836, 0.17857142857142858, 0.15217391304347827, 0.17391304347826086, 0.22413793103448276], "model79": [0.18556701030927836, 0.20689655172413793, 0.18, 0.16326530612244897, 0.20967741935483872], "model80": [0.16, 0.17142857142857143, 0.13861386138613863, 0.13793103448275862, 0.18333333333333332], "model81": [0.1836734693877551, 0.20689655172413793, 0.18, 0.16326530612244897, 0.20967741935483872], "model82": [0.20618556701030927, 0.17699115044247787, 0.15217391304347827, 0.17582417582417584, 0.22413793103448276], "model83": [0.18556701030927836, 0.20689655172413793, 0.18, 0.16326530612244897, 0.20967741935483872], "model84": [0.1782178217821782, 0.1694915254237288, 0.15841584158415842, 0.16666666666666666, 0.17543859649122806], "model85": [0.1836734693877551, 0.20689655172413793, 0.18, 0.16326530612244897, 0.20967741935483872], "model86": [0.1875, 0.17543859649122806, 0.15384615384615385, 0.17204301075268819, 0.22807017543859648], "model87": [0.18556701030927836, 0.20689655172413793, 0.18, 0.16326530612244897, 0.20967741935483872], "model88": [0.1553398058252427, 0.1694915254237288, 0.1414141414141414, 0.16666666666666666, 0.17543859649122806], "model89": [0.1836734693877551, 0.20689655172413793, 0.18, 0.16326530612244897, 0.20967741935483872], "model90": [0.18556701030927836, 0.18181818181818182, 0.15217391304347827, 0.1702127659574468, 0.22807017543859648], "model91": [0.18556701030927836, 0.20689655172413793, 0.18, 0.16326530612244897, 0.20967741935483872], "model92": [0.17647058823529413, 0.17391304347826086, 0.13592233009708737, 0.13333333333333333, 0.17391304347826086], "model93": [0.1836734693877551, 0.20689655172413793, 0.18, 0.16326530612244897, 0.20967741935483872], "model94": [0.2, 0.17699115044247787, 0.14893617021276595, 0.17204301075268819, 0.22807017543859648], "model95": [0.18556701030927836, 0.20689655172413793, 0.18, 0.16326530612244897, 0.20967741935483872], "model96": [0.17307692307692307, 0.1592920353982301, 0.1568627450980392, 0.13333333333333333, 0.1864406779661017], "model97": [0.18556701030927836, 0.20689655172413793, 0.18, 0.16326530612244897, 0.20967741935483872], "model98": [0.17647058823529413, 0.17857142857142858, 0.14583333333333334, 0.16666666666666666, 0.22413793103448276], "model99": [0.18556701030927836, 0.20689655172413793, 0.18, 0.16326530612244897, 0.20967741935483872]}, "accuracy": {"model0": [0.911993097497843, 0.8792062122519413, 0.9024179620034543, 0.9015544041450777, 0.8670120898100173], "model1": [0.9128559102674719, 0.8800690250215704, 0.8981001727115717, 0.8981001727115717, 0.8618307426597582], "model2": [0.9275237273511648, 0.9163071613459879, 0.9283246977547496, 0.9265975820379966, 0.9050086355785838], "model3": [0.9240724762726489, 0.9154443485763589, 0.927461139896373, 0.92573402417962, 0.8998272884283247], "model4": [0.9163071613459879, 0.8990509059534081, 0.9153713298791019, 0.918825561312608, 0.883419689119171], "model5": [0.917169974115617, 0.9007765314926661, 0.9153713298791019, 0.917098445595855, 0.8825561312607945], "model6": [0.9318377911993098, 0.9223468507333908, 0.9283246977547496, 0.9300518134715026, 0.9110535405872193], "model7": [0.9249352890422778, 0.9188955996548749, 0.9309153713298791, 0.927461139896373, 0.9075993091537133], "model8": [0.9188955996548749, 0.907679033649698, 0.92573402417962, 0.9205526770293609, 0.8972366148531952], "model9": [0.9214840379637619, 0.909404659188956, 0.9196891191709845, 0.924006908462867, 0.8886010362694301], "model10": [0.9309749784296808, 0.9232096635030198, 0.9283246977547496, 0.9343696027633851, 0.9196891191709845], "model11": [0.9257981018119068, 0.9188955996548749, 0.9283246977547496, 0.927461139896373, 0.9101899827288429], "model12": [0.9197584124245038, 0.909404659188956, 0.9265975820379966, 0.9248704663212435, 0.9041450777202072], "model13": [0.9214840379637619, 0.9180327868852459, 0.9179620034542314, 0.9283246977547496, 0.8998272884283247], "model14": [0.9327006039689387, 0.9249352890422778, 0.9317789291882557, 0.9343696027633851, 0.918825561312608], "model15": [0.9257981018119068, 0.9188955996548749, 0.9283246977547496, 0.927461139896373, 0.9101899827288429], "model16": [0.9197584124245038, 0.910267471958585, 0.9265975820379966, 0.927461139896373, 0.9075993091537133], "model17": [0.9232096635030198, 0.9214840379637619, 0.9214162348877375, 0.9300518134715026, 0.9015544041450777], "model18": [0.9335634167385677, 0.9257981018119068, 0.9309153713298791, 0.9352331606217616, 0.9179620034542314], "model19": [0.9283865401207938, 0.9188955996548749, 0.9283246977547496, 0.927461139896373, 0.9110535405872193], "model20": [0.917169974115617, 0.913718723037101, 0.927461139896373, 0.927461139896373, 0.9084628670120898], "model21": [0.9232096635030198, 0.9223468507333908, 0.924006908462867, 0.9309153713298791, 0.9058721934369602], "model22": [0.9327006039689387, 0.9266609145815358, 0.9300518134715026, 0.9352331606217616, 0.9196891191709845], "model23": [0.9301121656600517, 0.9188955996548749, 0.9283246977547496, 0.927461139896373, 0.9110535405872193], "model24": [0.9180327868852459, 0.911993097497843, 0.927461139896373, 0.927461139896373, 0.9110535405872193], "model25": [0.9232096635030198, 0.9197584124245038, 0.924006908462867, 0.9317789291882557, 0.9075993091537133], "model26": [0.9318377911993098, 0.9257981018119068, 0.9291882556131261, 0.9360967184801382, 0.9179620034542314], "model27": [0.9301121656600517, 0.9188955996548749, 0.9291882556131261, 0.9291882556131261, 0.9110535405872193], "model28": [0.9197584124245038, 0.9154443485763589, 0.9265975820379966, 0.9291882556131261, 0.9084628670120898], "model29": [0.9232096635030198, 0.9197584124245038, 0.924006908462867, 0.9300518134715026, 0.9084628670120898], "model30": [0.9327006039689387, 0.9257981018119068, 0.9300518134715026, 0.9369602763385146, 0.918825561312608], "model31": [0.9301121656600517, 0.9197584124245038, 0.9291882556131261, 0.9291882556131261, 0.9119170984455959], "model32": [0.9154443485763589, 0.9163071613459879, 0.9231433506044905, 0.9300518134715026, 0.9110535405872193], "model33": [0.9249352890422778, 0.9180327868852459, 0.92573402417962, 0.9300518134715026, 0.9093264248704663], "model34": [0.9318377911993098, 0.9257981018119068, 0.9309153713298791, 0.9378238341968912, 0.9196891191709845], "model35": [0.9292493528904228, 0.9197584124245038, 0.9291882556131261, 0.9291882556131261, 0.9119170984455959], "model36": [0.9214840379637619, 0.9188955996548749, 0.9248704663212435, 0.9300518134715026, 0.9110535405872193], "model37": [0.9249352890422778, 0.9197584124245038, 0.9265975820379966, 0.9291882556131261, 0.9093264248704663], "model38": [0.9309749784296808, 0.9249352890422778, 0.9309153713298791, 0.9395509499136442, 0.9214162348877375], "model39": [0.9292493528904228, 0.9197584124245038, 0.9291882556131261, 0.9291882556131261, 0.9119170984455959], "model40": [0.9214840379637619, 0.913718723037101, 0.9222797927461139, 0.9309153713298791, 0.9153713298791019], "model41": [0.9283865401207938, 0.9206212251941329, 0.927461139896373, 0.9291882556131261, 0.9119170984455959], "model42": [0.9309749784296808, 0.9223468507333908, 0.9300518134715026, 0.9369602763385146, 0.924006908462867], "model43": [0.9309749784296808, 0.9197584124245038, 0.9291882556131261, 0.9291882556131261, 0.9127806563039723], "model44": [0.9249352890422778, 0.9154443485763589, 0.924006908462867, 0.9326424870466321, 0.9162348877374784], "model45": [0.9292493528904228, 0.9206212251941329, 0.9291882556131261, 0.9291882556131261, 0.9127806563039723], "model46": [0.9318377911993098, 0.9223468507333908, 0.9317789291882557, 0.9378238341968912, 0.9248704663212435], "model47": [0.9309749784296808, 0.9197584124245038, 0.9291882556131261, 0.9291882556131261, 0.9127806563039723], "model48": [0.9214840379637619, 0.9188955996548749, 0.9248704663212435, 0.9369602763385146, 0.9145077720207254], "model49": [0.9301121656600517, 0.9214840379637619, 0.9291882556131261, 0.9291882556131261, 0.9145077720207254], "model50": [0.9318377911993098, 0.9223468507333908, 0.9326424870466321, 0.9352331606217616, 0.9248704663212435], "model51": [0.9309749784296808, 0.9197584124245038, 0.9291882556131261, 0.9291882556131261, 0.9136442141623489], "model52": [0.9240724762726489, 0.9188955996548749, 0.9231433506044905, 0.9360967184801382, 0.9127806563039723], "model53": [0.9292493528904228, 0.9206212251941329, 0.9291882556131261, 0.9291882556131261, 0.9153713298791019], "model54": [0.9335634167385677, 0.9249352890422778, 0.9326424870466321, 0.9352331606217616, 0.9248704663212435], "model55": [0.9309749784296808, 0.9206212251941329, 0.9291882556131261, 0.9291882556131261, 0.9145077720207254], "model56": [0.9240724762726489, 0.9128559102674719, 0.9214162348877375, 0.9335060449050087, 0.9145077720207254], "model57": [0.9301121656600517, 0.9197584124245038, 0.9291882556131261, 0.9291882556131261, 0.9153713298791019], "model58": [0.9335634167385677, 0.9240724762726489, 0.9309153713298791, 0.9335060449050087, 0.9231433506044905], "model59": [0.9318377911993098, 0.9206212251941329, 0.9291882556131261, 0.9291882556131261, 0.9145077720207254], "model60": [0.9266609145815358, 0.91458153580673, 0.9205526770293609, 0.9352331606217616, 0.9162348877374784], "model61": [0.9318377911993098, 0.9197584124245038, 0.9291882556131261, 0.9291882556131261, 0.9153713298791019], "model62": [0.9335634167385677, 0.9206212251941329, 0.9326424870466321, 0.9343696027633851, 0.9231433506044905], "model63": [0.9318377911993098, 0.9206212251941329, 0.9291882556131261, 0.9291882556131261, 0.9153713298791019], "model64": [0.9275237273511648, 0.9206212251941329, 0.9214162348877375, 0.9317789291882557, 0.9162348877374784], "model65": [0.9309749784296808, 0.9197584124245038, 0.9291882556131261, 0.9291882556131261, 0.9153713298791019], "model66": [0.9327006039689387, 0.9206212251941329, 0.9343696027633851, 0.9343696027633851, 0.9214162348877375], "model67": [0.9318377911993098, 0.9206212251941329, 0.9291882556131261, 0.9291882556131261, 0.9153713298791019], "model68": [0.9318377911993098, 0.9206212251941329, 0.92573402417962, 0.9326424870466321, 0.9136442141623489], "model69": [0.9309749784296808, 0.9197584124245038, 0.9291882556131261, 0.9291882556131261, 0.9153713298791019], "model70": [0.9309749784296808, 0.9214840379637619, 0.9360967184801382, 0.9360967184801382, 0.9231433506044905], "model71": [0.9318377911993098, 0.9206212251941329, 0.9291882556131261, 0.9291882556131261, 0.9153713298791019], "model72": [0.9275237273511648, 0.9180327868852459, 0.9265975820379966, 0.9309153713298791, 0.917098445595855], "model73": [0.9309749784296808, 0.9206212251941329, 0.9291882556131261, 0.9291882556131261, 0.9153713298791019], "model74": [0.9309749784296808, 0.9206212251941329, 0.9309153713298791, 0.9360967184801382, 0.924006908462867], "model75": [0.9318377911993098, 0.9206212251941329, 0.9291882556131261, 0.9291882556131261, 0.9153713298791019], "model76": [0.9266609145815358, 0.9154443485763589, 0.92573402417962, 0.9369602763385146, 0.9153713298791019], "model77": [0.9309749784296808, 0.9206212251941329, 0.9291882556131261, 0.9291882556131261, 0.9153713298791019], "model78": [0.9318377911993098, 0.9206212251941329, 0.9326424870466321, 0.9343696027633851, 0.9222797927461139], "model79": [0.9318377911993098, 0.9206212251941329, 0.9291882556131261, 0.9291882556131261, 0.9153713298791019], "model80": [0.9275237273511648, 0.9249352890422778, 0.9248704663212435, 0.9352331606217616, 0.9153713298791019], "model81": [0.9309749784296808, 0.9206212251941329, 0.9291882556131261, 0.9291882556131261, 0.9153713298791019], "model82": [0.9335634167385677, 0.9197584124245038, 0.9326424870466321, 0.9352331606217616, 0.9222797927461139], "model83": [0.9318377911993098, 0.9206212251941329, 0.9291882556131261, 0.9291882556131261, 0.9153713298791019], "model84": [0.9283865401207938, 0.9154443485763589, 0.9265975820379966, 0.9309153713298791, 0.918825561312608], "model85": [0.9309749784296808, 0.9206212251941329, 0.9291882556131261, 0.9291882556131261, 0.9153713298791019], "model86": [0.9327006039689387, 0.9188955996548749, 0.9335060449050087, 0.9335060449050087, 0.924006908462867], "model87": [0.9318377911993098, 0.9206212251941329, 0.9291882556131261, 0.9291882556131261, 0.9153713298791019], "model88": [0.9249352890422778, 0.9154443485763589, 0.9265975820379966, 0.9309153713298791, 0.918825561312608], "model89": [0.9309749784296808, 0.9206212251941329, 0.9291882556131261, 0.9291882556131261, 0.9153713298791019], "model90": [0.9318377911993098, 0.9223468507333908, 0.9326424870466321, 0.9326424870466321, 0.924006908462867], "model91": [0.9318377911993098, 0.9206212251941329, 0.9291882556131261, 0.9291882556131261, 0.9153713298791019], "model92": [0.9275237273511648, 0.9180327868852459, 0.9231433506044905, 0.9326424870466321, 0.9179620034542314], "model93": [0.9309749784296808, 0.9206212251941329, 0.9291882556131261, 0.9291882556131261, 0.9153713298791019], "model94": [0.9309749784296808, 0.9197584124245038, 0.9309153713298791, 0.9335060449050087, 0.924006908462867], "model95": [0.9318377911993098, 0.9206212251941329, 0.9291882556131261, 0.9291882556131261, 0.9153713298791019], "model96": [0.9257981018119068, 0.9180327868852459, 0.92573402417962, 0.9326424870466321, 0.917098445595855], "model97": [0.9318377911993098, 0.9206212251941329, 0.9291882556131261, 0.9291882556131261, 0.9153713298791019], "model98": [0.9275237273511648, 0.9206212251941329, 0.9291882556131261, 0.9309153713298791, 0.9222797927461139], "model99": [0.9318377911993098, 0.9206212251941329, 0.9291882556131261, 0.9291882556131261, 0.9153713298791019]}, "roc_auc": {"model0": [0.6939959093600301, 0.6232574411970505, 0.5797306397306398, 0.6195555555555555, 0.6798518518518518], "model1": [0.6957182840841811, 0.6137305560040907, 0.5806464646464647, 0.6221952861952862, 0.68189898989899], "model2": [0.7214193444211205, 0.624845255395877, 0.5958114478114478, 0.6210505050505051, 0.7074612794612793], "model3": [0.7174363528715215, 0.6239302438236719, 0.5926868686868687, 0.6206195286195285, 0.7058720538720539], "model4": [0.7042763334948059, 0.6120081812799396, 0.5736969696969697, 0.5995824915824916, 0.6969562289562289], "model5": [0.7071559287367458, 0.6135959954787664, 0.5831111111111111, 0.6167676767676769, 0.7000269360269361], "model6": [0.72629043543786, 0.6235803864578288, 0.592956228956229, 0.6155016835016835, 0.7048754208754208], "model7": [0.7177592981323, 0.622746111200818, 0.5909898989898991, 0.6163636363636363, 0.7064915824915825], "model8": [0.7127536465902362, 0.6154260186231767, 0.5673131313131313, 0.5946531986531987, 0.6988417508417508], "model9": [0.7143952849991926, 0.6153183702029172, 0.5847946127946128, 0.6191515151515151, 0.7052794612794614], "model10": [0.7305963722482373, 0.622046396469132, 0.5904242424242424, 0.6135353535353536, 0.7032053872053873], "model11": [0.7180015070778837, 0.6223424296248453, 0.5905589225589226, 0.6155824915824916, 0.7061683501683503], "model12": [0.7155255934119167, 0.6206738791108241, 0.562976430976431, 0.5929023569023568, 0.6993804713804714], "model13": [0.7186473975994403, 0.6169600086118736, 0.58603367003367, 0.6193400673400674, 0.7065993265993267], "model14": [0.7341756822218634, 0.6215350664728996, 0.5885117845117845, 0.6127272727272728, 0.7021548821548822], "model15": [0.7177592981323, 0.6222347812045859, 0.58996632996633, 0.6150841750841751, 0.7058989898989899], "model16": [0.7187550460196996, 0.6221271327843265, 0.5625454545454546, 0.5928484848484847, 0.6992188552188553], "model17": [0.7187281339146349, 0.6175251628182357, 0.5851986531986532, 0.6176026936026936, 0.7056296296296296], "model18": [0.7363017385219871, 0.6206200549006944, 0.5868417508417508, 0.6127272727272728, 0.701104377104377], "model19": [0.7176516497120404, 0.6221540448893913, 0.5896700336700336, 0.6147474747474747, 0.7058181818181818], "model20": [0.7182975402335972, 0.6209699122665375, 0.5601616161616161, 0.593939393939394, 0.6980336700336701], "model21": [0.7193202002260617, 0.6172291296625221, 0.5861144781144781, 0.6174141414141414, 0.7055488215488216], "model22": [0.7378088164056192, 0.6200549006943322, 0.586114478114478, 0.6136161616161617, 0.7002693602693604], "model23": [0.7178400344474944, 0.622396253834975, 0.5893737373737374, 0.6144511784511785, 0.7058720538720539], "model24": [0.7174901770816513, 0.620727703320954, 0.5577643097643097, 0.5958114478114478, 0.6974680134680135], "model25": [0.7187281339146347, 0.6174713386081059, 0.5864915824915824, 0.6179797979797981, 0.705952861952862], "model26": [0.7393966306044458, 0.618951504386673, 0.5848484848484848, 0.6136161616161616, 0.6994612794612795], "model27": [0.7176785618171053, 0.6224231659400398, 0.5890774410774411, 0.6142356902356902, 0.7058451178451178], "model28": [0.7156870660423058, 0.6198665159588783, 0.559057239057239, 0.596188552188552, 0.694154882154882], "model29": [0.7194009365412564, 0.6177135475536897, 0.5865185185185186, 0.6176969696969696, 0.7057912457912457], "model30": [0.7408767963830131, 0.6184132622853761, 0.5837710437710437, 0.6135353535353534, 0.6985993265993266], "model31": [0.7177862102373648, 0.6223155175197804, 0.588996632996633, 0.6141818181818183, 0.7057643097643097], "model32": [0.7203428602185264, 0.6185478228107003, 0.5544511784511785, 0.5972390572390571, 0.6932929292929292], "model33": [0.7193202002260617, 0.6179019322891437, 0.5871111111111111, 0.6180471380471381, 0.7056026936026936], "model34": [0.7426260832122289, 0.6177135475536897, 0.583043771043771, 0.6136969696969696, 0.6979528619528619], "model35": [0.7176785618171054, 0.6224500780451047, 0.5888350168350168, 0.61403367003367, 0.7056835016835017], "model36": [0.7170326712955487, 0.6204585822703053, 0.5516228956228956, 0.59796632996633, 0.6915690235690236], "model37": [0.7193740244361915, 0.6178481080790139, 0.5872457912457913, 0.61789898989899, 0.7053872053872055], "model38": [0.7438102158350826, 0.6175520749233004, 0.5822626262626263, 0.6143973063973064, 0.696983164983165], "model39": [0.7177323860272351, 0.6223693417299101, 0.5888080808080809, 0.6141144781144781, 0.7056835016835017], "model40": [0.7353059906345875, 0.6209968243716024, 0.5445925925925926, 0.6025454545454545, 0.6794478114478115], "model41": [0.7195085849615157, 0.6190053285968029, 0.5881346801346802, 0.6159326599326599, 0.7064915824915825], "model42": [0.7513456052532428, 0.6155605791485009, 0.5798383838383838, 0.6182491582491583, 0.6937777777777778], "model43": [0.7177323860272351, 0.6224500780451047, 0.5885656565656566, 0.6136700336700336, 0.7054410774410774], "model44": [0.7484660100113031, 0.6194897464879703, 0.5473670033670033, 0.6029225589225589, 0.675003367003367], "model45": [0.7189703428602187, 0.6198126917487486, 0.5881346801346801, 0.6152053872053873, 0.7066801346801347], "model46": [0.7561359599547877, 0.6142418860003229, 0.5787340067340068, 0.6197037037037036, 0.692942760942761], "model47": [0.7176785618171053, 0.6225039022552343, 0.5883771043771043, 0.6136161616161616, 0.7054410774410774], "model48": [0.7536062220786911, 0.6117390602292911, 0.5503030303030304, 0.6021414141414141, 0.6717979797979797], "model49": [0.7187819581247645, 0.6201894612196566, 0.5881616161616161, 0.6144781144781145, 0.7066262626262626], "model50": [0.7593923246676354, 0.6139727649496743, 0.5783030303030303, 0.6205117845117846, 0.6923232323232323], "model51": [0.7176247376069756, 0.6224231659400398, 0.5882962962962963, 0.6135353535353536, 0.7053602693602693], "model52": [0.7594999730878949, 0.6129501049572097, 0.5541548821548822, 0.6062356902356902, 0.6707744107744108], "model53": [0.7184590128639863, 0.6205931427956294, 0.5881346801346802, 0.6143973063973064, 0.7062760942760942], "model54": [0.7616260293880188, 0.6132461381129232, 0.5783030303030304, 0.6207272727272727, 0.6921077441077441], "model55": [0.7175978255019109, 0.6223962538349749, 0.5882424242424242, 0.6134949494949495, 0.7054141414141414], "model56": [0.7661741751439798, 0.6176058991334302, 0.5545589225589227, 0.611084175084175, 0.6683232323232323], "model57": [0.7180015070778837, 0.6211582970019914, 0.5882154882154883, 0.6141683501683503, 0.7061952861952862], "model58": [0.7650438667312557, 0.6122234781204586, 0.5774949494949496, 0.6207272727272727, 0.6917845117845118], "model59": [0.7176247376069756, 0.6224500780451047, 0.5881885521885521, 0.6134545454545455, 0.7053333333333334], "model60": [0.7695651003821519, 0.6173367780827816, 0.5583569023569024, 0.6130774410774411, 0.6633400673400672], "model61": [0.7177592981323, 0.6216427148931589, 0.5882693602693603, 0.614074074074074, 0.706195286195286], "model62": [0.7668469777706012, 0.6114430270735777, 0.576956228956229, 0.6201616161616161, 0.6918653198653198], "model63": [0.7175978255019109, 0.6225039022552344, 0.5881885521885521, 0.6134006734006734, 0.7053602693602694], "model64": [0.7724985198342215, 0.6065450239517735, 0.5582760942760943, 0.6150168350168349, 0.6636094276094275], "model65": [0.717732386027235, 0.6217234512083535, 0.5881885521885521, 0.614020202020202, 0.705979797979798], "model66": [0.7681925830238442, 0.6111200818127994, 0.5763097643097643, 0.6205925925925926, 0.6923232323232325], "model67": [0.7176247376069758, 0.6225308143602992, 0.5881346801346802, 0.6134006734006734, 0.7053602693602694], "model68": [0.7576699499434846, 0.5995478766349104, 0.56393265993266, 0.6172255892255891, 0.6676767676767676], "model69": [0.7178131223424297, 0.6220733085741967, 0.5881616161616161, 0.6139259259259259, 0.7058989898989899], "model70": [0.7696189245922817, 0.6097475644544916, 0.5753939393939393, 0.6211851851851852, 0.6926464646464646], "model71": [0.7176516497120405, 0.622557726465364, 0.5881346801346801, 0.6134006734006734, 0.7053602693602694], "model72": [0.7760778298078476, 0.6040691102858066, 0.5635824915824916, 0.6200808080808081, 0.6642558922558923], "model73": [0.7177862102373648, 0.6222886054147155, 0.5882154882154882, 0.6136161616161616, 0.7058451178451178], "model74": [0.7704531998492922, 0.6091285860379999, 0.5739932659932659, 0.6225050505050505, 0.6935353535353537], "model75": [0.7176516497120404, 0.622557726465364, 0.588107744107744, 0.6134006734006734, 0.7053063973063973], "model76": [0.7764007750686259, 0.60054362452231, 0.5623434343434344, 0.5973468013468013, 0.6627744107744108], "model77": [0.7177592981323, 0.6223155175197804, 0.5881616161616162, 0.6134545454545455, 0.7056835016835017], "model78": [0.7707223208999407, 0.6078906292050164, 0.5725117845117844, 0.6203501683501683, 0.694020202020202], "model79": [0.7176785618171053, 0.6226115506754938, 0.588080808080808, 0.6134006734006734, 0.7053333333333334], "model80": [0.7700495182733194, 0.5898595188115614, 0.5653063973063972, 0.5945454545454545, 0.670127946127946], "model81": [0.7177862102373649, 0.6223424296248453, 0.5881616161616162, 0.6134949494949495, 0.7055488215488216], "model82": [0.7710990903708488, 0.6082673986759244, 0.5723232323232325, 0.6212929292929292, 0.6945858585858586], "model83": [0.7176516497120404, 0.6226115506754938, 0.588080808080808, 0.6134006734006734, 0.7053063973063973], "model84": [0.7641557672641154, 0.5979062382259541, 0.5754478114478115, 0.6146127946127946, 0.6624781144781144], "model85": [0.7177592981323, 0.6223693417299101, 0.5882154882154882, 0.6134680134680134, 0.7055218855218854], "model86": [0.7707761451100704, 0.6081866623607298, 0.5727542087542088, 0.6209158249158248, 0.6945050505050505], "model87": [0.7176785618171053, 0.6226115506754938, 0.588080808080808, 0.6133872053872054, 0.7053063973063973], "model88": [0.7622180956994458, 0.5961838635018031, 0.5624511784511784, 0.6143703703703703, 0.6637441077441077], "model89": [0.7177054739221702, 0.6223155175197804, 0.5882154882154882, 0.6135218855218856, 0.7054680134680135], "model90": [0.7705608482695516, 0.6075676839442381, 0.572861952861953, 0.6216161616161616, 0.6959865319865319], "model91": [0.7176785618171053, 0.6226115506754938, 0.588080808080808, 0.6133737373737373, 0.7053063973063973], "model92": [0.76423650357931, 0.5921470477420743, 0.5597037037037036, 0.5936026936026936, 0.6613737373737373], "model93": [0.7177054739221702, 0.6223155175197804, 0.5881616161616161, 0.6135892255892256, 0.7053872053872053], "model94": [0.7705608482695517, 0.6061951665859303, 0.5718922558922559, 0.6190303030303029, 0.6963097643097643], "model95": [0.7175978255019108, 0.6226115506754938, 0.588080808080808, 0.6133737373737373, 0.7053063973063973], "model96": [0.7653129877819043, 0.5854997577910545, 0.5604713804713805, 0.5907205387205388, 0.6668417508417509], "model97": [0.7175978255019109, 0.6224500780451047, 0.5882154882154882, 0.6135622895622896, 0.7052255892255893], "model98": [0.7702379030087734, 0.6042036708111309, 0.5693872053872054, 0.618087542087542, 0.6985993265993267], "model99": [0.7175978255019108, 0.6226115506754938, 0.588080808080808, 0.6134006734006734, 0.7053333333333334]}}