{"model": {"model0": {"booster": "gbtree", "gamma": 0.0, "max_depth": 3, "min_child_weight": 1, "objective": "binary:logistic"}, "model1": {"booster": "gbtree", "gamma": 0.0, "max_depth": 3, "min_child_weight": 2, "objective": "binary:logistic"}, "model2": {"booster": "gbtree", "gamma": 0.0, "max_depth": 3, "min_child_weight": 3, "objective": "binary:logistic"}, "model3": {"booster": "gbtree", "gamma": 0.0, "max_depth": 3, "min_child_weight": 5, "objective": "binary:logistic"}, "model4": {"booster": "gbtree", "gamma": 0.0, "max_depth": 6, "min_child_weight": 1, "objective": "binary:logistic"}, "model5": {"booster": "gbtree", "gamma": 0.0, "max_depth": 6, "min_child_weight": 2, "objective": "binary:logistic"}, "model6": {"booster": "gbtree", "gamma": 0.0, "max_depth": 6, "min_child_weight": 3, "objective": "binary:logistic"}, "model7": {"booster": "gbtree", "gamma": 0.0, "max_depth": 6, "min_child_weight": 5, "objective": "binary:logistic"}, "model8": {"booster": "gbtree", "gamma": 0.0, "max_depth": 9, "min_child_weight": 1, "objective": "binary:logistic"}, "model9": {"booster": "gbtree", "gamma": 0.0, "max_depth": 9, "min_child_weight": 2, "objective": "binary:logistic"}, "model10": {"booster": "gbtree", "gamma": 0.0, "max_depth": 9, "min_child_weight": 3, "objective": "binary:logistic"}, "model11": {"booster": "gbtree", "gamma": 0.0, "max_depth": 9, "min_child_weight": 5, "objective": "binary:logistic"}, "model12": {"booster": "gbtree", "gamma": 0.3333333333333333, "max_depth": 3, "min_child_weight": 1, "objective": "binary:logistic"}, "model13": {"booster": "gbtree", "gamma": 0.3333333333333333, "max_depth": 3, "min_child_weight": 2, "objective": "binary:logistic"}, "model14": {"booster": "gbtree", "gamma": 0.3333333333333333, "max_depth": 3, "min_child_weight": 3, "objective": "binary:logistic"}, "model15": {"booster": "gbtree", "gamma": 0.3333333333333333, "max_depth": 3, "min_child_weight": 5, "objective": "binary:logistic"}, "model16": {"booster": "gbtree", "gamma": 0.3333333333333333, "max_depth": 6, "min_child_weight": 1, "objective": "binary:logistic"}, "model17": {"booster": "gbtree", "gamma": 0.3333333333333333, "max_depth": 6, "min_child_weight": 2, "objective": "binary:logistic"}, "model18": {"booster": "gbtree", "gamma": 0.3333333333333333, "max_depth": 6, "min_child_weight": 3, "objective": "binary:logistic"}, "model19": {"booster": "gbtree", "gamma": 0.3333333333333333, "max_depth": 6, "min_child_weight": 5, "objective": "binary:logistic"}, "model20": {"booster": "gbtree", "gamma": 0.3333333333333333, "max_depth": 9, "min_child_weight": 1, "objective": "binary:logistic"}, "model21": {"booster": "gbtree", "gamma": 0.3333333333333333, "max_depth": 9, "min_child_weight": 2, "objective": "binary:logistic"}, "model22": {"booster": "gbtree", "gamma": 0.3333333333333333, "max_depth": 9, "min_child_weight": 3, "objective": "binary:logistic"}, "model23": {"booster": "gbtree", "gamma": 0.3333333333333333, "max_depth": 9, "min_child_weight": 5, "objective": "binary:logistic"}, "model24": {"booster": "gbtree", "gamma": 0.6666666666666666, "max_depth": 3, "min_child_weight": 1, "objective": "binary:logistic"}, "model25": {"booster": "gbtree", "gamma": 0.6666666666666666, "max_depth": 3, "min_child_weight": 2, "objective": "binary:logistic"}, "model26": {"booster": "gbtree", "gamma": 0.6666666666666666, "max_depth": 3, "min_child_weight": 3, "objective": "binary:logistic"}, "model27": {"booster": "gbtree", "gamma": 0.6666666666666666, "max_depth": 3, "min_child_weight": 5, "objective": "binary:logistic"}, "model28": {"booster": "gbtree", "gamma": 0.6666666666666666, "max_depth": 6, "min_child_weight": 1, "objective": "binary:logistic"}, "model29": {"booster": "gbtree", "gamma": 0.6666666666666666, "max_depth": 6, "min_child_weight": 2, "objective": "binary:logistic"}, "model30": {"booster": "gbtree", "gamma": 0.6666666666666666, "max_depth": 6, "min_child_weight": 3, "objective": "binary:logistic"}, "model31": {"booster": "gbtree", "gamma": 0.6666666666666666, "max_depth": 6, "min_child_weight": 5, "objective": "binary:logistic"}, "model32": {"booster": "gbtree", "gamma": 0.6666666666666666, "max_depth": 9, "min_child_weight": 1, "objective": "binary:logistic"}, "model33": {"booster": "gbtree", "gamma": 0.6666666666666666, "max_depth": 9, "min_child_weight": 2, "objective": "binary:logistic"}, "model34": {"booster": "gbtree", "gamma": 0.6666666666666666, "max_depth": 9, "min_child_weight": 3, "objective": "binary:logistic"}, "model35": {"booster": "gbtree", "gamma": 0.6666666666666666, "max_depth": 9, "min_child_weight": 5, "objective": "binary:logistic"}, "model36": {"booster": "gbtree", "gamma": 1.0, "max_depth": 3, "min_child_weight": 1, "objective": "binary:logistic"}, "model37": {"booster": "gbtree", "gamma": 1.0, "max_depth": 3, "min_child_weight": 2, "objective": "binary:logistic"}, "model38": {"booster": "gbtree", "gamma": 1.0, "max_depth": 3, "min_child_weight": 3, "objective": "binary:logistic"}, "model39": {"booster": "gbtree", "gamma": 1.0, "max_depth": 3, "min_child_weight": 5, "objective": "binary:logistic"}, "model40": {"booster": "gbtree", "gamma": 1.0, "max_depth": 6, "min_child_weight": 1, "objective": "binary:logistic"}, "model41": {"booster": "gbtree", "gamma": 1.0, "max_depth": 6, "min_child_weight": 2, "objective": "binary:logistic"}, "model42": {"booster": "gbtree", "gamma": 1.0, "max_depth": 6, "min_child_weight": 3, "objective": "binary:logistic"}, "model43": {"booster": "gbtree", "gamma": 1.0, "max_depth": 6, "min_child_weight": 5, "objective": "binary:logistic"}, "model44": {"booster": "gbtree", "gamma": 1.0, "max_depth": 9, "min_child_weight": 1, "objective": "binary:logistic"}, "model45": {"booster": "gbtree", "gamma": 1.0, "max_depth": 9, "min_child_weight": 2, "objective": "binary:logistic"}, "model46": {"booster": "gbtree", "gamma": 1.0, "max_depth": 9, "min_child_weight": 3, "objective": "binary:logistic"}, "model47": {"booster": "gbtree", "gamma": 1.0, "max_depth": 9, "min_child_weight": 5, "objective": "binary:logistic"}, "model48": {"booster": "gbtree", "gamma": 1.3333333333333333, "max_depth": 3, "min_child_weight": 1, "objective": "binary:logistic"}, "model49": {"booster": "gbtree", "gamma": 1.3333333333333333, "max_depth": 3, "min_child_weight": 2, "objective": "binary:logistic"}, "model50": {"booster": "gbtree", "gamma": 1.3333333333333333, "max_depth": 3, "min_child_weight": 3, "objective": "binary:logistic"}, "model51": {"booster": "gbtree", "gamma": 1.3333333333333333, "max_depth": 3, "min_child_weight": 5, "objective": "binary:logistic"}, "model52": {"booster": "gbtree", "gamma": 1.3333333333333333, "max_depth": 6, "min_child_weight": 1, "objective": "binary:logistic"}, "model53": {"booster": "gbtree", "gamma": 1.3333333333333333, "max_depth": 6, "min_child_weight": 2, "objective": "binary:logistic"}, "model54": {"booster": "gbtree", "gamma": 1.3333333333333333, "max_depth": 6, "min_child_weight": 3, "objective": "binary:logistic"}, "model55": {"booster": "gbtree", "gamma": 1.3333333333333333, "max_depth": 6, "min_child_weight": 5, "objective": "binary:logistic"}, "model56": {"booster": "gbtree", "gamma": 1.3333333333333333, "max_depth": 9, "min_child_weight": 1, "objective": "binary:logistic"}, "model57": {"booster": "gbtree", "gamma": 1.3333333333333333, "max_depth": 9, "min_child_weight": 2, "objective": "binary:logistic"}, "model58": {"booster": "gbtree", "gamma": 1.3333333333333333, "max_depth": 9, "min_child_weight": 3, "objective": "binary:logistic"}, "model59": {"booster": "gbtree", "gamma": 1.3333333333333333, "max_depth": 9, "min_child_weight": 5, "objective": "binary:logistic"}, "model60": {"booster": "gbtree", "gamma": 1.6666666666666665, "max_depth": 3, "min_child_weight": 1, "objective": "binary:logistic"}, "model61": {"booster": "gbtree", "gamma": 1.6666666666666665, "max_depth": 3, "min_child_weight": 2, "objective": "binary:logistic"}, "model62": {"booster": "gbtree", "gamma": 1.6666666666666665, "max_depth": 3, "min_child_weight": 3, "objective": "binary:logistic"}, "model63": {"booster": "gbtree", "gamma": 1.6666666666666665, "max_depth": 3, "min_child_weight": 5, "objective": "binary:logistic"}, "model64": {"booster": "gbtree", "gamma": 1.6666666666666665, "max_depth": 6, "min_child_weight": 1, "objective": "binary:logistic"}, "model65": {"booster": "gbtree", "gamma": 1.6666666666666665, "max_depth": 6, "min_child_weight": 2, "objective": "binary:logistic"}, "model66": {"booster": "gbtree", "gamma": 1.6666666666666665, "max_depth": 6, "min_child_weight": 3, "objective": "binary:logistic"}, "model67": {"booster": "gbtree", "gamma": 1.6666666666666665, "max_depth": 6, "min_child_weight": 5, "objective": "binary:logistic"}, "model68": {"booster": "gbtree", "gamma": 1.6666666666666665, "max_depth": 9, "min_child_weight": 1, "objective": "binary:logistic"}, "model69": {"booster": "gbtree", "gamma": 1.6666666666666665, "max_depth": 9, "min_child_weight": 2, "objective": "binary:logistic"}, "model70": {"booster": "gbtree", "gamma": 1.6666666666666665, "max_depth": 9, "min_child_weight": 3, "objective": "binary:logistic"}, "model71": {"booster": "gbtree", "gamma": 1.6666666666666665, "max_depth": 9, "min_child_weight": 5, "objective": "binary:logistic"}, "model72": {"booster": "gbtree", "gamma": 2.0, "max_depth": 3, "min_child_weight": 1, "objective": "binary:logistic"}, "model73": {"booster": "gbtree", "gamma": 2.0, "max_depth": 3, "min_child_weight": 2, "objective": "binary:logistic"}, "model74": {"booster": "gbtree", "gamma": 2.0, "max_depth": 3, "min_child_weight": 3, "objective": "binary:logistic"}, "model75": {"booster": "gbtree", "gamma": 2.0, "max_depth": 3, "min_child_weight": 5, "objective": "binary:logistic"}, "model76": {"booster": "gbtree", "gamma": 2.0, "max_depth": 6, "min_child_weight": 1, "objective": "binary:logistic"}, "model77": {"booster": "gbtree", "gamma": 2.0, "max_depth": 6, "min_child_weight": 2, "objective": "binary:logistic"}, "model78": {"booster": "gbtree", "gamma": 2.0, "max_depth": 6, "min_child_weight": 3, "objective": "binary:logistic"}, "model79": {"booster": "gbtree", "gamma": 2.0, "max_depth": 6, "min_child_weight": 5, "objective": "binary:logistic"}, "model80": {"booster": "gbtree", "gamma": 2.0, "max_depth": 9, "min_child_weight": 1, "objective": "binary:logistic"}, "model81": {"booster": "gbtree", "gamma": 2.0, "max_depth": 9, "min_child_weight": 2, "objective": "binary:logistic"}, "model82": {"booster": "gbtree", "gamma": 2.0, "max_depth": 9, "min_child_weight": 3, "objective": "binary:logistic"}, "model83": {"booster": "gbtree", "gamma": 2.0, "max_depth": 9, "min_child_weight": 5, "objective": "binary:logistic"}, "model84": {"booster": "gbtree", "gamma": 2.333333333333333, "max_depth": 3, "min_child_weight": 1, "objective": "binary:logistic"}, "model85": {"booster": "gbtree", "gamma": 2.333333333333333, "max_depth": 3, "min_child_weight": 2, "objective": "binary:logistic"}, "model86": {"booster": "gbtree", "gamma": 2.333333333333333, "max_depth": 3, "min_child_weight": 3, "objective": "binary:logistic"}, "model87": {"booster": "gbtree", "gamma": 2.333333333333333, "max_depth": 3, "min_child_weight": 5, "objective": "binary:logistic"}, "model88": {"booster": "gbtree", "gamma": 2.333333333333333, "max_depth": 6, "min_child_weight": 1, "objective": "binary:logistic"}, "model89": {"booster": "gbtree", "gamma": 2.333333333333333, "max_depth": 6, "min_child_weight": 2, "objective": "binary:logistic"}, "model90": {"booster": "gbtree", "gamma": 2.333333333333333, "max_depth": 6, "min_child_weight": 3, "objective": "binary:logistic"}, "model91": {"booster": "gbtree", "gamma": 2.333333333333333, "max_depth": 6, "min_child_weight": 5, "objective": "binary:logistic"}, "model92": {"booster": "gbtree", "gamma": 2.333333333333333, "max_depth": 9, "min_child_weight": 1, "objective": "binary:logistic"}, "model93": {"booster": "gbtree", "gamma": 2.333333333333333, "max_depth": 9, "min_child_weight": 2, "objective": "binary:logistic"}, "model94": {"booster": "gbtree", "gamma": 2.333333333333333, "max_depth": 9, "min_child_weight": 3, "objective": "binary:logistic"}, "model95": {"booster": "gbtree", "gamma": 2.333333333333333, "max_depth": 9, "min_child_weight": 5, "objective": "binary:logistic"}, "model96": {"booster": "gbtree", "gamma": 2.6666666666666665, "max_depth": 3, "min_child_weight": 1, "objective": "binary:logistic"}, "model97": {"booster": "gbtree", "gamma": 2.6666666666666665, "max_depth": 3, "min_child_weight": 2, "objective": "binary:logistic"}, "model98": {"booster": "gbtree", "gamma": 2.6666666666666665, "max_depth": 3, "min_child_weight": 3, "objective": "binary:logistic"}, "model99": {"booster": "gbtree", "gamma": 2.6666666666666665, "max_depth": 3, "min_child_weight": 5, "objective": "binary:logistic"}, "model100": {"booster": "gbtree", "gamma": 2.6666666666666665, "max_depth": 6, "min_child_weight": 1, "objective": "binary:logistic"}, "model101": {"booster": "gbtree", "gamma": 2.6666666666666665, "max_depth": 6, "min_child_weight": 2, "objective": "binary:logistic"}, "model102": {"booster": "gbtree", "gamma": 2.6666666666666665, "max_depth": 6, "min_child_weight": 3, "objective": "binary:logistic"}, "model103": {"booster": "gbtree", "gamma": 2.6666666666666665, "max_depth": 6, "min_child_weight": 5, "objective": "binary:logistic"}, "model104": {"booster": "gbtree", "gamma": 2.6666666666666665, "max_depth": 9, "min_child_weight": 1, "objective": "binary:logistic"}, "model105": {"booster": "gbtree", "gamma": 2.6666666666666665, "max_depth": 9, "min_child_weight": 2, "objective": "binary:logistic"}, "model106": {"booster": "gbtree", "gamma": 2.6666666666666665, "max_depth": 9, "min_child_weight": 3, "objective": "binary:logistic"}, "model107": {"booster": "gbtree", "gamma": 2.6666666666666665, "max_depth": 9, "min_child_weight": 5, "objective": "binary:logistic"}, "model108": {"booster": "gbtree", "gamma": 3.0, "max_depth": 3, "min_child_weight": 1, "objective": "binary:logistic"}, "model109": {"booster": "gbtree", "gamma": 3.0, "max_depth": 3, "min_child_weight": 2, "objective": "binary:logistic"}, "model110": {"booster": "gbtree", "gamma": 3.0, "max_depth": 3, "min_child_weight": 3, "objective": "binary:logistic"}, "model111": {"booster": "gbtree", "gamma": 3.0, "max_depth": 3, "min_child_weight": 5, "objective": "binary:logistic"}, "model112": {"booster": "gbtree", "gamma": 3.0, "max_depth": 6, "min_child_weight": 1, "objective": "binary:logistic"}, "model113": {"booster": "gbtree", "gamma": 3.0, "max_depth": 6, "min_child_weight": 2, "objective": "binary:logistic"}, "model114": {"booster": "gbtree", "gamma": 3.0, "max_depth": 6, "min_child_weight": 3, "objective": "binary:logistic"}, "model115": {"booster": "gbtree", "gamma": 3.0, "max_depth": 6, "min_child_weight": 5, "objective": "binary:logistic"}, "model116": {"booster": "gbtree", "gamma": 3.0, "max_depth": 9, "min_child_weight": 1, "objective": "binary:logistic"}, "model117": {"booster": "gbtree", "gamma": 3.0, "max_depth": 9, "min_child_weight": 2, "objective": "binary:logistic"}, "model118": {"booster": "gbtree", "gamma": 3.0, "max_depth": 9, "min_child_weight": 3, "objective": "binary:logistic"}, "model119": {"booster": "gbtree", "gamma": 3.0, "max_depth": 9, "min_child_weight": 5, "objective": "binary:logistic"}}, "precision": {"model0": [0.13333333333333333, 0.42857142857142855, 0.1935483870967742, 0.125, 0.25], "model1": [0.09090909090909091, 0.25, 0.21212121212121213, 0.1875, 0.25], "model2": [0.21052631578947367, 0.46153846153846156, 0.1724137931034483, 0.125, 0.2631578947368421], "model3": [0.15789473684210525, 0.42857142857142855, 0.1935483870967742, 0.13333333333333333, 0.2631578947368421], "model4": [0.25, 0.46153846153846156, 0.2916666666666667, 0.16666666666666666, 0.21428571428571427], "model5": [0.23529411764705882, 0.4666666666666667, 0.2692307692307692, 0.18181818181818182, 0.2222222222222222], "model6": [0.1111111111111111, 0.4375, 0.23809523809523808, 0.2, 0.2222222222222222], "model7": [0.1111111111111111, 0.5, 0.19230769230769232, 0.26666666666666666, 0.2857142857142857], "model8": [0.25, 0.4117647058823529, 0.21052631578947367, 0.16666666666666666, 0.13333333333333333], "model9": [0.21052631578947367, 0.5, 0.2608695652173913, 0.23076923076923078, 0.2222222222222222], "model10": [0.1875, 0.3157894736842105, 0.24, 0.16666666666666666, 0.17647058823529413], "model11": [0.1111111111111111, 0.5, 0.20833333333333334, 0.15384615384615385, 0.13333333333333333], "model12": [0.21428571428571427, 0.3333333333333333, 0.25, 0.13333333333333333, 0.3333333333333333], "model13": [0.1875, 0.3333333333333333, 0.25806451612903225, 0.2, 0.2222222222222222], "model14": [0.2, 0.3076923076923077, 0.1724137931034483, 0.1111111111111111, 0.2631578947368421], "model15": [0.15789473684210525, 0.3333333333333333, 0.17142857142857143, 0.15, 0.2631578947368421], "model16": [0.3125, 0.4375, 0.24, 0.14285714285714285, 0.11764705882352941], "model17": [0.3125, 0.5714285714285714, 0.24, 0.14285714285714285, 0.2777777777777778], "model18": [0.1111111111111111, 0.4166666666666667, 0.2413793103448276, 0.21428571428571427, 0.2631578947368421], "model19": [0.1111111111111111, 0.5, 0.1111111111111111, 0.26666666666666666, 0.2], "model20": [0.18181818181818182, 0.42857142857142855, 0.25925925925925924, 0.1875, 0.14285714285714285], "model21": [0.1875, 0.4444444444444444, 0.18181818181818182, 0.2, 0.14285714285714285], "model22": [0.23529411764705882, 0.4666666666666667, 0.28, 0.17647058823529413, 0.3333333333333333], "model23": [0.13636363636363635, 0.4666666666666667, 0.24, 0.14285714285714285, 0.17647058823529413], "model24": [0.21052631578947367, 0.42105263157894735, 0.2222222222222222, 0.15789473684210525, 0.2777777777777778], "model25": [0.16666666666666666, 0.2727272727272727, 0.1935483870967742, 0.13333333333333333, 0.36363636363636365], "model26": [0.2, 0.375, 0.22580645161290322, 0.16666666666666666, 0.2777777777777778], "model27": [0.19047619047619047, 0.35294117647058826, 0.19444444444444445, 0.17647058823529413, 0.16666666666666666], "model28": [0.2857142857142857, 0.35294117647058826, 0.2413793103448276, 0.14285714285714285, 0.17647058823529413], "model29": [0.2857142857142857, 0.47058823529411764, 0.2, 0.13333333333333333, 0.2727272727272727], "model30": [0.2777777777777778, 0.3333333333333333, 0.28125, 0.2222222222222222, 0.15789473684210525], "model31": [0.14285714285714285, 0.35714285714285715, 0.2647058823529412, 0.1875, 0.23529411764705882], "model32": [0.25, 0.4444444444444444, 0.28125, 0.25, 0.16666666666666666], "model33": [0.2631578947368421, 0.45, 0.23076923076923078, 0.15384615384615385, 0.2222222222222222], "model34": [0.17647058823529413, 0.47058823529411764, 0.2413793103448276, 0.2222222222222222, 0.17647058823529413], "model35": [0.1, 0.3, 0.37037037037037035, 0.1111111111111111, 0.25], "model36": [0.21052631578947367, 0.4444444444444444, 0.16216216216216217, 0.2, 0.2222222222222222], "model37": [0.09090909090909091, 0.3333333333333333, 0.14705882352941177, 0.1111111111111111, 0.25], "model38": [0.19047619047619047, 0.375, 0.21212121212121213, 0.13333333333333333, 0.25], "model39": [0.2222222222222222, 0.4666666666666667, 0.2, 0.21052631578947367, 0.09523809523809523], "model40": [0.13333333333333333, 0.35, 0.21875, 0.29411764705882354, 0.2], "model41": [0.3333333333333333, 0.47619047619047616, 0.25, 0.13333333333333333, 0.2631578947368421], "model42": [0.15, 0.42105263157894735, 0.20689655172413793, 0.29411764705882354, 0.3], "model43": [0.18181818181818182, 0.3684210526315789, 0.23076923076923078, 0.3076923076923077, 0.23809523809523808], "model44": [0.2, 0.4375, 0.2857142857142857, 0.1111111111111111, 0.14285714285714285], "model45": [0.3, 0.2857142857142857, 0.24, 0.1875, 0.21052631578947367], "model46": [0.19047619047619047, 0.4117647058823529, 0.2222222222222222, 0.17647058823529413, 0.17647058823529413], "model47": [0.125, 0.3888888888888889, 0.28, 0.14285714285714285, 0.23529411764705882], "model48": [0.15, 0.36363636363636365, 0.1794871794871795, 0.13333333333333333, 0.2727272727272727], "model49": [0.18181818181818182, 0.3125, 0.17142857142857143, 0.13333333333333333, 0.2727272727272727], "model50": [0.11538461538461539, 0.5, 0.21052631578947367, 0.10526315789473684, 0.25], "model51": [0.17647058823529413, 0.5, 0.16666666666666666, 0.15, 0.23809523809523808], "model52": [0.2, 0.34782608695652173, 0.2857142857142857, 0.13333333333333333, 0.20833333333333334], "model53": [0.38095238095238093, 0.4444444444444444, 0.2857142857142857, 0.06666666666666667, 0.15789473684210525], "model54": [0.16, 0.375, 0.23529411764705882, 0.2222222222222222, 0.25], "model55": [0.18181818181818182, 0.3333333333333333, 0.23529411764705882, 0.14285714285714285, 0.13636363636363635], "model56": [0.20833333333333334, 0.3888888888888889, 0.2571428571428571, 0.16666666666666666, 0.14285714285714285], "model57": [0.2857142857142857, 0.3333333333333333, 0.27586206896551724, 0.15, 0.21052631578947367], "model58": [0.21052631578947367, 0.4, 0.25925925925925924, 0.25, 0.17391304347826086], "model59": [0.19047619047619047, 0.38095238095238093, 0.2222222222222222, 0.1875, 0.1875], "model60": [0.2, 0.2777777777777778, 0.1951219512195122, 0.11764705882352941, 0.30434782608695654], "model61": [0.22727272727272727, 0.2857142857142857, 0.20512820512820512, 0.13333333333333333, 0.3181818181818182], "model62": [0.16666666666666666, 0.4117647058823529, 0.20512820512820512, 0.1111111111111111, 0.24], "model63": [0.21428571428571427, 0.3888888888888889, 0.16216216216216217, 0.14285714285714285, 0.3333333333333333], "model64": [0.19047619047619047, 0.36, 0.2222222222222222, 0.1875, 0.15], "model65": [0.2631578947368421, 0.42857142857142855, 0.21875, 0.2, 0.17647058823529413], "model66": [0.24, 0.3, 0.23529411764705882, 0.23809523809523808, 0.19230769230769232], "model67": [0.17391304347826086, 0.38095238095238093, 0.2777777777777778, 0.25, 0.2916666666666667], "model68": [0.2727272727272727, 0.4117647058823529, 0.2857142857142857, 0.21428571428571427, 0.15789473684210525], "model69": [0.2692307692307692, 0.42857142857142855, 0.25806451612903225, 0.15, 0.1875], "model70": [0.2692307692307692, 0.391304347826087, 0.24242424242424243, 0.23529411764705882, 0.21739130434782608], "model71": [0.10526315789473684, 0.4, 0.3, 0.13333333333333333, 0.23529411764705882], "model72": [0.19047619047619047, 0.35, 0.2, 0.1, 0.24], "model73": [0.25, 0.3181818181818182, 0.16216216216216217, 0.09523809523809523, 0.2608695652173913], "model74": [0.17391304347826086, 0.4375, 0.20512820512820512, 0.1, 0.2], "model75": [0.19230769230769232, 0.36363636363636365, 0.15384615384615385, 0.15789473684210525, 0.125], "model76": [0.25, 0.3157894736842105, 0.17647058823529413, 0.26666666666666666, 0.17391304347826086], "model77": [0.3333333333333333, 0.4090909090909091, 0.30303030303030304, 0.11764705882352941, 0.19230769230769232], "model78": [0.25925925925925924, 0.391304347826087, 0.20512820512820512, 0.19047619047619047, 0.19047619047619047], "model79": [0.19047619047619047, 0.3333333333333333, 0.25925925925925924, 0.16666666666666666, 0.20833333333333334], "model80": [0.2, 0.391304347826087, 0.21212121212121213, 0.2, 0.15], "model81": [0.2, 0.4, 0.23333333333333334, 0.25, 0.15789473684210525], "model82": [0.2727272727272727, 0.42857142857142855, 0.22580645161290322, 0.2, 0.21739130434782608], "model83": [0.08695652173913043, 0.4, 0.17857142857142858, 0.2, 0.23809523809523808], "model84": [0.20833333333333334, 0.2608695652173913, 0.2, 0.09523809523809523, 0.2], "model85": [0.23529411764705882, 0.3181818181818182, 0.1951219512195122, 0.14285714285714285, 0.2916666666666667], "model86": [0.10714285714285714, 0.3684210526315789, 0.18421052631578946, 0.09090909090909091, 0.2727272727272727], "model87": [0.18518518518518517, 0.38095238095238093, 0.1388888888888889, 0.14814814814814814, 0.13636363636363635], "model88": [0.25, 0.4, 0.29411764705882354, 0.1875, 0.20833333333333334], "model89": [0.24, 0.391304347826087, 0.29411764705882354, 0.0625, 0.2], "model90": [0.25925925925925924, 0.34615384615384615, 0.16666666666666666, 0.23809523809523808, 0.30434782608695654], "model91": [0.19230769230769232, 0.35, 0.2571428571428571, 0.16666666666666666, 0.2608695652173913], "model92": [0.25, 0.3333333333333333, 0.2727272727272727, 0.1875, 0.15], "model93": [0.09523809523809523, 0.3, 0.24324324324324326, 0.2, 0.19047619047619047], "model94": [0.15789473684210525, 0.3333333333333333, 0.25, 0.13636363636363635, 0.2608695652173913], "model95": [0.24, 0.3333333333333333, 0.25806451612903225, 0.1875, 0.2222222222222222], "model96": [0.21739130434782608, 0.34782608695652173, 0.21428571428571427, 0.19230769230769232, 0.16666666666666666], "model97": [0.23529411764705882, 0.2916666666666667, 0.2682926829268293, 0.125, 0.16666666666666666], "model98": [0.19230769230769232, 0.3684210526315789, 0.18604651162790697, 0.07407407407407407, 0.1724137931034483], "model99": [0.20689655172413793, 0.3333333333333333, 0.1388888888888889, 0.16, 0.13636363636363635], "model100": [0.2, 0.2727272727272727, 0.2564102564102564, 0.25, 0.17391304347826086], "model101": [0.19230769230769232, 0.4, 0.25, 0.15, 0.16666666666666666], "model102": [0.25, 0.42105263157894735, 0.23684210526315788, 0.19047619047619047, 0.20833333333333334], "model103": [0.16, 0.2916666666666667, 0.2647058823529412, 0.15384615384615385, 0.24], "model104": [0.28, 0.3333333333333333, 0.30303030303030304, 0.14285714285714285, 0.2], "model105": [0.2, 0.34782608695652173, 0.3076923076923077, 0.15789473684210525, 0.15], "model106": [0.2222222222222222, 0.391304347826087, 0.2727272727272727, 0.17391304347826086, 0.08333333333333333], "model107": [0.2608695652173913, 0.3333333333333333, 0.1875, 0.2222222222222222, 0.2857142857142857], "model108": [0.16, 0.3333333333333333, 0.21052631578947367, 0.17391304347826086, 0.21428571428571427], "model109": [0.21739130434782608, 0.2916666666666667, 0.13513513513513514, 0.08333333333333333, 0.16], "model110": [0.15384615384615385, 0.3333333333333333, 0.2, 0.07407407407407407, 0.1875], "model111": [0.22580645161290322, 0.42857142857142855, 0.14705882352941177, 0.125, 0.21739130434782608], "model112": [0.32, 0.36, 0.19444444444444445, 0.13043478260869565, 0.22727272727272727], "model113": [0.28, 0.4230769230769231, 0.21951219512195122, 0.13043478260869565, 0.2608695652173913], "model114": [0.2, 0.3333333333333333, 0.18421052631578946, 0.21052631578947367, 0.28], "model115": [0.15384615384615385, 0.34782608695652173, 0.23684210526315788, 0.058823529411764705, 0.20833333333333334], "model116": [0.2222222222222222, 0.34782608695652173, 0.2631578947368421, 0.16666666666666666, 0.15], "model117": [0.25, 0.38095238095238093, 0.25, 0.11764705882352941, 0.18181818181818182], "model118": [0.2727272727272727, 0.42857142857142855, 0.25, 0.3157894736842105, 0.22727272727272727], "model119": [0.125, 0.3181818181818182, 0.21428571428571427, 0.1111111111111111, 0.23076923076923078]}, "recall": {"model0": [0.09090909090909091, 0.2727272727272727, 0.2608695652173913, 0.09090909090909091, 0.18181818181818182], "model1": [0.045454545454545456, 0.13636363636363635, 0.30434782608695654, 0.13636363636363635, 0.22727272727272727], "model2": [0.18181818181818182, 0.2727272727272727, 0.21739130434782608, 0.09090909090909091, 0.22727272727272727], "model3": [0.13636363636363635, 0.2727272727272727, 0.2608695652173913, 0.09090909090909091, 0.22727272727272727], "model4": [0.13636363636363635, 0.2727272727272727, 0.30434782608695654, 0.09090909090909091, 0.13636363636363635], "model5": [0.18181818181818182, 0.3181818181818182, 0.30434782608695654, 0.09090909090909091, 0.18181818181818182], "model6": [0.09090909090909091, 0.3181818181818182, 0.21739130434782608, 0.13636363636363635, 0.18181818181818182], "model7": [0.09090909090909091, 0.2727272727272727, 0.21739130434782608, 0.18181818181818182, 0.18181818181818182], "model8": [0.18181818181818182, 0.3181818181818182, 0.17391304347826086, 0.09090909090909091, 0.09090909090909091], "model9": [0.18181818181818182, 0.3181818181818182, 0.2608695652173913, 0.13636363636363635, 0.18181818181818182], "model10": [0.13636363636363635, 0.2727272727272727, 0.2608695652173913, 0.09090909090909091, 0.13636363636363635], "model11": [0.09090909090909091, 0.22727272727272727, 0.21739130434782608, 0.09090909090909091, 0.09090909090909091], "model12": [0.13636363636363635, 0.18181818181818182, 0.30434782608695654, 0.09090909090909091, 0.2727272727272727], "model13": [0.13636363636363635, 0.18181818181818182, 0.34782608695652173, 0.13636363636363635, 0.18181818181818182], "model14": [0.13636363636363635, 0.18181818181818182, 0.21739130434782608, 0.09090909090909091, 0.22727272727272727], "model15": [0.13636363636363635, 0.22727272727272727, 0.2608695652173913, 0.13636363636363635, 0.22727272727272727], "model16": [0.22727272727272727, 0.3181818181818182, 0.2608695652173913, 0.09090909090909091, 0.09090909090909091], "model17": [0.22727272727272727, 0.36363636363636365, 0.2608695652173913, 0.09090909090909091, 0.22727272727272727], "model18": [0.09090909090909091, 0.22727272727272727, 0.30434782608695654, 0.13636363636363635, 0.22727272727272727], "model19": [0.09090909090909091, 0.3181818181818182, 0.13043478260869565, 0.18181818181818182, 0.18181818181818182], "model20": [0.09090909090909091, 0.2727272727272727, 0.30434782608695654, 0.13636363636363635, 0.09090909090909091], "model21": [0.13636363636363635, 0.36363636363636365, 0.17391304347826086, 0.13636363636363635, 0.09090909090909091], "model22": [0.18181818181818182, 0.3181818181818182, 0.30434782608695654, 0.13636363636363635, 0.22727272727272727], "model23": [0.13636363636363635, 0.3181818181818182, 0.2608695652173913, 0.09090909090909091, 0.13636363636363635], "model24": [0.18181818181818182, 0.36363636363636365, 0.34782608695652173, 0.13636363636363635, 0.22727272727272727], "model25": [0.13636363636363635, 0.13636363636363635, 0.2608695652173913, 0.09090909090909091, 0.36363636363636365], "model26": [0.18181818181818182, 0.2727272727272727, 0.30434782608695654, 0.13636363636363635, 0.22727272727272727], "model27": [0.18181818181818182, 0.2727272727272727, 0.30434782608695654, 0.13636363636363635, 0.13636363636363635], "model28": [0.2727272727272727, 0.2727272727272727, 0.30434782608695654, 0.09090909090909091, 0.13636363636363635], "model29": [0.2727272727272727, 0.36363636363636365, 0.2608695652173913, 0.09090909090909091, 0.2727272727272727], "model30": [0.22727272727272727, 0.2727272727272727, 0.391304347826087, 0.18181818181818182, 0.13636363636363635], "model31": [0.13636363636363635, 0.22727272727272727, 0.391304347826087, 0.13636363636363635, 0.18181818181818182], "model32": [0.22727272727272727, 0.36363636363636365, 0.391304347826087, 0.18181818181818182, 0.13636363636363635], "model33": [0.22727272727272727, 0.4090909090909091, 0.2608695652173913, 0.09090909090909091, 0.18181818181818182], "model34": [0.13636363636363635, 0.36363636363636365, 0.30434782608695654, 0.18181818181818182, 0.13636363636363635], "model35": [0.09090909090909091, 0.2727272727272727, 0.43478260869565216, 0.09090909090909091, 0.18181818181818182], "model36": [0.18181818181818182, 0.36363636363636365, 0.2608695652173913, 0.13636363636363635, 0.18181818181818182], "model37": [0.09090909090909091, 0.22727272727272727, 0.21739130434782608, 0.09090909090909091, 0.2727272727272727], "model38": [0.18181818181818182, 0.2727272727272727, 0.30434782608695654, 0.09090909090909091, 0.22727272727272727], "model39": [0.18181818181818182, 0.3181818181818182, 0.30434782608695654, 0.18181818181818182, 0.09090909090909091], "model40": [0.09090909090909091, 0.3181818181818182, 0.30434782608695654, 0.22727272727272727, 0.13636363636363635], "model41": [0.2727272727272727, 0.45454545454545453, 0.30434782608695654, 0.09090909090909091, 0.22727272727272727], "model42": [0.13636363636363635, 0.36363636363636365, 0.2608695652173913, 0.22727272727272727, 0.2727272727272727], "model43": [0.18181818181818182, 0.3181818181818182, 0.2608695652173913, 0.18181818181818182, 0.22727272727272727], "model44": [0.18181818181818182, 0.3181818181818182, 0.34782608695652173, 0.09090909090909091, 0.09090909090909091], "model45": [0.2727272727272727, 0.2727272727272727, 0.2608695652173913, 0.13636363636363635, 0.18181818181818182], "model46": [0.18181818181818182, 0.3181818181818182, 0.2608695652173913, 0.13636363636363635, 0.13636363636363635], "model47": [0.09090909090909091, 0.3181818181818182, 0.30434782608695654, 0.09090909090909091, 0.18181818181818182], "model48": [0.13636363636363635, 0.36363636363636365, 0.30434782608695654, 0.09090909090909091, 0.2727272727272727], "model49": [0.18181818181818182, 0.22727272727272727, 0.2608695652173913, 0.09090909090909091, 0.2727272727272727], "model50": [0.13636363636363635, 0.36363636363636365, 0.34782608695652173, 0.09090909090909091, 0.2727272727272727], "model51": [0.13636363636363635, 0.36363636363636365, 0.2608695652173913, 0.13636363636363635, 0.22727272727272727], "model52": [0.18181818181818182, 0.36363636363636365, 0.43478260869565216, 0.09090909090909091, 0.22727272727272727], "model53": [0.36363636363636365, 0.36363636363636365, 0.43478260869565216, 0.045454545454545456, 0.13636363636363635], "model54": [0.18181818181818182, 0.2727272727272727, 0.34782608695652173, 0.18181818181818182, 0.3181818181818182], "model55": [0.18181818181818182, 0.3181818181818182, 0.34782608695652173, 0.09090909090909091, 0.13636363636363635], "model56": [0.22727272727272727, 0.3181818181818182, 0.391304347826087, 0.09090909090909091, 0.09090909090909091], "model57": [0.2727272727272727, 0.3181818181818182, 0.34782608695652173, 0.13636363636363635, 0.18181818181818182], "model58": [0.18181818181818182, 0.36363636363636365, 0.30434782608695654, 0.22727272727272727, 0.18181818181818182], "model59": [0.18181818181818182, 0.36363636363636365, 0.2608695652173913, 0.13636363636363635, 0.13636363636363635], "model60": [0.22727272727272727, 0.22727272727272727, 0.34782608695652173, 0.09090909090909091, 0.3181818181818182], "model61": [0.22727272727272727, 0.2727272727272727, 0.34782608695652173, 0.09090909090909091, 0.3181818181818182], "model62": [0.18181818181818182, 0.3181818181818182, 0.34782608695652173, 0.09090909090909091, 0.2727272727272727], "model63": [0.2727272727272727, 0.3181818181818182, 0.2608695652173913, 0.13636363636363635, 0.36363636363636365], "model64": [0.18181818181818182, 0.4090909090909091, 0.34782608695652173, 0.13636363636363635, 0.13636363636363635], "model65": [0.22727272727272727, 0.4090909090909091, 0.30434782608695654, 0.13636363636363635, 0.13636363636363635], "model66": [0.2727272727272727, 0.2727272727272727, 0.34782608695652173, 0.22727272727272727, 0.22727272727272727], "model67": [0.18181818181818182, 0.36363636363636365, 0.43478260869565216, 0.18181818181818182, 0.3181818181818182], "model68": [0.2727272727272727, 0.3181818181818182, 0.43478260869565216, 0.13636363636363635, 0.13636363636363635], "model69": [0.3181818181818182, 0.4090909090909091, 0.34782608695652173, 0.13636363636363635, 0.13636363636363635], "model70": [0.3181818181818182, 0.4090909090909091, 0.34782608695652173, 0.18181818181818182, 0.22727272727272727], "model71": [0.09090909090909091, 0.36363636363636365, 0.391304347826087, 0.09090909090909091, 0.18181818181818182], "model72": [0.18181818181818182, 0.3181818181818182, 0.34782608695652173, 0.09090909090909091, 0.2727272727272727], "model73": [0.22727272727272727, 0.3181818181818182, 0.2608695652173913, 0.09090909090909091, 0.2727272727272727], "model74": [0.18181818181818182, 0.3181818181818182, 0.34782608695652173, 0.09090909090909091, 0.18181818181818182], "model75": [0.22727272727272727, 0.36363636363636365, 0.2608695652173913, 0.13636363636363635, 0.13636363636363635], "model76": [0.2727272727272727, 0.2727272727272727, 0.2608695652173913, 0.18181818181818182, 0.18181818181818182], "model77": [0.3181818181818182, 0.4090909090909091, 0.43478260869565216, 0.09090909090909091, 0.22727272727272727], "model78": [0.3181818181818182, 0.4090909090909091, 0.34782608695652173, 0.18181818181818182, 0.18181818181818182], "model79": [0.18181818181818182, 0.36363636363636365, 0.30434782608695654, 0.13636363636363635, 0.22727272727272727], "model80": [0.22727272727272727, 0.4090909090909091, 0.30434782608695654, 0.13636363636363635, 0.13636363636363635], "model81": [0.18181818181818182, 0.36363636363636365, 0.30434782608695654, 0.22727272727272727, 0.13636363636363635], "model82": [0.2727272727272727, 0.4090909090909091, 0.30434782608695654, 0.18181818181818182, 0.22727272727272727], "model83": [0.09090909090909091, 0.36363636363636365, 0.21739130434782608, 0.13636363636363635, 0.22727272727272727], "model84": [0.22727272727272727, 0.2727272727272727, 0.34782608695652173, 0.09090909090909091, 0.22727272727272727], "model85": [0.18181818181818182, 0.3181818181818182, 0.34782608695652173, 0.13636363636363635, 0.3181818181818182], "model86": [0.13636363636363635, 0.3181818181818182, 0.30434782608695654, 0.09090909090909091, 0.2727272727272727], "model87": [0.22727272727272727, 0.36363636363636365, 0.21739130434782608, 0.18181818181818182, 0.13636363636363635], "model88": [0.2727272727272727, 0.36363636363636365, 0.43478260869565216, 0.13636363636363635, 0.22727272727272727], "model89": [0.2727272727272727, 0.4090909090909091, 0.43478260869565216, 0.045454545454545456, 0.22727272727272727], "model90": [0.3181818181818182, 0.4090909090909091, 0.2608695652173913, 0.22727272727272727, 0.3181818181818182], "model91": [0.22727272727272727, 0.3181818181818182, 0.391304347826087, 0.13636363636363635, 0.2727272727272727], "model92": [0.22727272727272727, 0.3181818181818182, 0.391304347826087, 0.13636363636363635, 0.13636363636363635], "model93": [0.09090909090909091, 0.2727272727272727, 0.391304347826087, 0.18181818181818182, 0.18181818181818182], "model94": [0.13636363636363635, 0.3181818181818182, 0.391304347826087, 0.13636363636363635, 0.2727272727272727], "model95": [0.2727272727272727, 0.2727272727272727, 0.34782608695652173, 0.13636363636363635, 0.18181818181818182], "model96": [0.22727272727272727, 0.36363636363636365, 0.391304347826087, 0.22727272727272727, 0.18181818181818182], "model97": [0.18181818181818182, 0.3181818181818182, 0.4782608695652174, 0.13636363636363635, 0.18181818181818182], "model98": [0.22727272727272727, 0.3181818181818182, 0.34782608695652173, 0.09090909090909091, 0.22727272727272727], "model99": [0.2727272727272727, 0.3181818181818182, 0.21739130434782608, 0.18181818181818182, 0.13636363636363635], "model100": [0.18181818181818182, 0.2727272727272727, 0.43478260869565216, 0.22727272727272727, 0.18181818181818182], "model101": [0.22727272727272727, 0.45454545454545453, 0.391304347826087, 0.13636363636363635, 0.18181818181818182], "model102": [0.2727272727272727, 0.36363636363636365, 0.391304347826087, 0.18181818181818182, 0.22727272727272727], "model103": [0.18181818181818182, 0.3181818181818182, 0.391304347826087, 0.09090909090909091, 0.2727272727272727], "model104": [0.3181818181818182, 0.36363636363636365, 0.43478260869565216, 0.09090909090909091, 0.22727272727272727], "model105": [0.22727272727272727, 0.36363636363636365, 0.5217391304347826, 0.13636363636363635, 0.13636363636363635], "model106": [0.2727272727272727, 0.4090909090909091, 0.391304347826087, 0.18181818181818182, 0.09090909090909091], "model107": [0.2727272727272727, 0.3181818181818182, 0.2608695652173913, 0.18181818181818182, 0.2727272727272727], "model108": [0.18181818181818182, 0.36363636363636365, 0.34782608695652173, 0.18181818181818182, 0.2727272727272727], "model109": [0.22727272727272727, 0.3181818181818182, 0.21739130434782608, 0.09090909090909091, 0.18181818181818182], "model110": [0.18181818181818182, 0.3181818181818182, 0.34782608695652173, 0.09090909090909091, 0.2727272727272727], "model111": [0.3181818181818182, 0.4090909090909091, 0.21739130434782608, 0.13636363636363635, 0.22727272727272727], "model112": [0.36363636363636365, 0.4090909090909091, 0.30434782608695654, 0.13636363636363635, 0.22727272727272727], "model113": [0.3181818181818182, 0.5, 0.391304347826087, 0.13636363636363635, 0.2727272727272727], "model114": [0.22727272727272727, 0.3181818181818182, 0.30434782608695654, 0.18181818181818182, 0.3181818181818182], "model115": [0.18181818181818182, 0.36363636363636365, 0.391304347826087, 0.045454545454545456, 0.22727272727272727], "model116": [0.2727272727272727, 0.36363636363636365, 0.43478260869565216, 0.13636363636363635, 0.13636363636363635], "model117": [0.2727272727272727, 0.36363636363636365, 0.391304347826087, 0.09090909090909091, 0.18181818181818182], "model118": [0.2727272727272727, 0.5454545454545454, 0.43478260869565216, 0.2727272727272727, 0.22727272727272727], "model119": [0.13636363636363635, 0.3181818181818182, 0.391304347826087, 0.09090909090909091, 0.2727272727272727]}, "f1": {"model0": [0.10810810810810811, 0.3333333333333333, 0.2222222222222222, 0.10526315789473684, 0.21052631578947367], "model1": [0.06060606060606061, 0.17647058823529413, 0.25, 0.15789473684210525, 0.23809523809523808], "model2": [0.1951219512195122, 0.34285714285714286, 0.19230769230769232, 0.10526315789473684, 0.24390243902439024], "model3": [0.14634146341463414, 0.3333333333333333, 0.2222222222222222, 0.10810810810810811, 0.24390243902439024], "model4": [0.17647058823529413, 0.34285714285714286, 0.2978723404255319, 0.11764705882352941, 0.16666666666666666], "model5": [0.20512820512820512, 0.3783783783783784, 0.2857142857142857, 0.12121212121212122, 0.2], "model6": [0.1, 0.3684210526315789, 0.22727272727272727, 0.16216216216216217, 0.2], "model7": [0.1, 0.35294117647058826, 0.20408163265306123, 0.21621621621621623, 0.2222222222222222], "model8": [0.21052631578947367, 0.358974358974359, 0.19047619047619047, 0.11764705882352941, 0.10810810810810811], "model9": [0.1951219512195122, 0.3888888888888889, 0.2608695652173913, 0.17142857142857143, 0.2], "model10": [0.15789473684210525, 0.2926829268292683, 0.25, 0.11764705882352941, 0.15384615384615385], "model11": [0.1, 0.3125, 0.2127659574468085, 0.11428571428571428, 0.10810810810810811], "model12": [0.16666666666666666, 0.23529411764705882, 0.27450980392156865, 0.10810810810810811, 0.3], "model13": [0.15789473684210525, 0.23529411764705882, 0.2962962962962963, 0.16216216216216217, 0.2], "model14": [0.16216216216216217, 0.22857142857142856, 0.19230769230769232, 0.1, 0.24390243902439024], "model15": [0.14634146341463414, 0.2702702702702703, 0.20689655172413793, 0.14285714285714285, 0.24390243902439024], "model16": [0.2631578947368421, 0.3684210526315789, 0.25, 0.1111111111111111, 0.10256410256410256], "model17": [0.2631578947368421, 0.4444444444444444, 0.25, 0.1111111111111111, 0.25], "model18": [0.1, 0.29411764705882354, 0.2692307692307692, 0.16666666666666666, 0.24390243902439024], "model19": [0.1, 0.3888888888888889, 0.12, 0.21621621621621623, 0.19047619047619047], "model20": [0.12121212121212122, 0.3333333333333333, 0.28, 0.15789473684210525, 0.1111111111111111], "model21": [0.15789473684210525, 0.4, 0.17777777777777778, 0.16216216216216217, 0.1111111111111111], "model22": [0.20512820512820512, 0.3783783783783784, 0.2916666666666667, 0.15384615384615385, 0.2702702702702703], "model23": [0.13636363636363635, 0.3783783783783784, 0.25, 0.1111111111111111, 0.15384615384615385], "model24": [0.1951219512195122, 0.3902439024390244, 0.2711864406779661, 0.14634146341463414, 0.25], "model25": [0.15, 0.18181818181818182, 0.2222222222222222, 0.10810810810810811, 0.36363636363636365], "model26": [0.19047619047619047, 0.3157894736842105, 0.25925925925925924, 0.15, 0.25], "model27": [0.18604651162790697, 0.3076923076923077, 0.23728813559322035, 0.15384615384615385, 0.15], "model28": [0.27906976744186046, 0.3076923076923077, 0.2692307692307692, 0.1111111111111111, 0.15384615384615385], "model29": [0.27906976744186046, 0.41025641025641024, 0.22641509433962265, 0.10810810810810811, 0.2727272727272727], "model30": [0.25, 0.3, 0.32727272727272727, 0.2, 0.14634146341463414], "model31": [0.13953488372093023, 0.2777777777777778, 0.3157894736842105, 0.15789473684210525, 0.20512820512820512], "model32": [0.23809523809523808, 0.4, 0.32727272727272727, 0.21052631578947367, 0.15], "model33": [0.24390243902439024, 0.42857142857142855, 0.24489795918367346, 0.11428571428571428, 0.2], "model34": [0.15384615384615385, 0.41025641025641024, 0.2692307692307692, 0.2, 0.15384615384615385], "model35": [0.09523809523809523, 0.2857142857142857, 0.4, 0.1, 0.21052631578947367], "model36": [0.1951219512195122, 0.4, 0.2, 0.16216216216216217, 0.2], "model37": [0.09090909090909091, 0.2702702702702703, 0.17543859649122806, 0.1, 0.2608695652173913], "model38": [0.18604651162790697, 0.3157894736842105, 0.25, 0.10810810810810811, 0.23809523809523808], "model39": [0.2, 0.3783783783783784, 0.2413793103448276, 0.1951219512195122, 0.09302325581395349], "model40": [0.10810810810810811, 0.3333333333333333, 0.2545454545454545, 0.2564102564102564, 0.16216216216216217], "model41": [0.3, 0.46511627906976744, 0.27450980392156865, 0.10810810810810811, 0.24390243902439024], "model42": [0.14285714285714285, 0.3902439024390244, 0.23076923076923078, 0.2564102564102564, 0.2857142857142857], "model43": [0.18181818181818182, 0.34146341463414637, 0.24489795918367346, 0.22857142857142856, 0.23255813953488372], "model44": [0.19047619047619047, 0.3684210526315789, 0.3137254901960784, 0.1, 0.1111111111111111], "model45": [0.2857142857142857, 0.27906976744186046, 0.25, 0.15789473684210525, 0.1951219512195122], "model46": [0.18604651162790697, 0.358974358974359, 0.24, 0.15384615384615385, 0.15384615384615385], "model47": [0.10526315789473684, 0.35, 0.2916666666666667, 0.1111111111111111, 0.20512820512820512], "model48": [0.14285714285714285, 0.36363636363636365, 0.22580645161290322, 0.10810810810810811, 0.2727272727272727], "model49": [0.18181818181818182, 0.2631578947368421, 0.20689655172413793, 0.10810810810810811, 0.2727272727272727], "model50": [0.125, 0.42105263157894735, 0.26229508196721313, 0.0975609756097561, 0.2608695652173913], "model51": [0.15384615384615385, 0.42105263157894735, 0.2033898305084746, 0.14285714285714285, 0.23255813953488372], "model52": [0.19047619047619047, 0.35555555555555557, 0.3448275862068966, 0.10810810810810811, 0.21739130434782608], "model53": [0.37209302325581395, 0.4, 0.3448275862068966, 0.05405405405405406, 0.14634146341463414], "model54": [0.1702127659574468, 0.3157894736842105, 0.2807017543859649, 0.2, 0.28], "model55": [0.18181818181818182, 0.32558139534883723, 0.2807017543859649, 0.1111111111111111, 0.13636363636363635], "model56": [0.21739130434782608, 0.35, 0.3103448275862069, 0.11764705882352941, 0.1111111111111111], "model57": [0.27906976744186046, 0.32558139534883723, 0.3076923076923077, 0.14285714285714285, 0.1951219512195122], "model58": [0.1951219512195122, 0.38095238095238093, 0.28, 0.23809523809523808, 0.17777777777777778], "model59": [0.18604651162790697, 0.37209302325581395, 0.24, 0.15789473684210525, 0.15789473684210525], "model60": [0.2127659574468085, 0.25, 0.25, 0.10256410256410256, 0.3111111111111111], "model61": [0.22727272727272727, 0.27906976744186046, 0.25806451612903225, 0.10810810810810811, 0.3181818181818182], "model62": [0.17391304347826086, 0.358974358974359, 0.25806451612903225, 0.1, 0.2553191489361702], "model63": [0.24, 0.35, 0.2, 0.13953488372093023, 0.34782608695652173], "model64": [0.18604651162790697, 0.3829787234042553, 0.2711864406779661, 0.15789473684210525, 0.14285714285714285], "model65": [0.24390243902439024, 0.4186046511627907, 0.2545454545454545, 0.16216216216216217, 0.15384615384615385], "model66": [0.2553191489361702, 0.2857142857142857, 0.2807017543859649, 0.23255813953488372, 0.20833333333333334], "model67": [0.17777777777777778, 0.37209302325581395, 0.3389830508474576, 0.21052631578947367, 0.30434782608695654], "model68": [0.2727272727272727, 0.358974358974359, 0.3448275862068966, 0.16666666666666666, 0.14634146341463414], "model69": [0.2916666666666667, 0.4186046511627907, 0.2962962962962963, 0.14285714285714285, 0.15789473684210525], "model70": [0.2916666666666667, 0.4, 0.2857142857142857, 0.20512820512820512, 0.2222222222222222], "model71": [0.0975609756097561, 0.38095238095238093, 0.33962264150943394, 0.10810810810810811, 0.20512820512820512], "model72": [0.18604651162790697, 0.3333333333333333, 0.25396825396825395, 0.09523809523809523, 0.2553191489361702], "model73": [0.23809523809523808, 0.3181818181818182, 0.2, 0.09302325581395349, 0.26666666666666666], "model74": [0.17777777777777778, 0.3684210526315789, 0.25806451612903225, 0.09523809523809523, 0.19047619047619047], "model75": [0.20833333333333334, 0.36363636363636365, 0.1935483870967742, 0.14634146341463414, 0.13043478260869565], "model76": [0.2608695652173913, 0.2926829268292683, 0.21052631578947367, 0.21621621621621623, 0.17777777777777778], "model77": [0.32558139534883723, 0.4090909090909091, 0.35714285714285715, 0.10256410256410256, 0.20833333333333334], "model78": [0.2857142857142857, 0.4, 0.25806451612903225, 0.18604651162790697, 0.18604651162790697], "model79": [0.18604651162790697, 0.34782608695652173, 0.28, 0.15, 0.21739130434782608], "model80": [0.2127659574468085, 0.4, 0.25, 0.16216216216216217, 0.14285714285714285], "model81": [0.19047619047619047, 0.38095238095238093, 0.2641509433962264, 0.23809523809523808, 0.14634146341463414], "model82": [0.2727272727272727, 0.4186046511627907, 0.25925925925925924, 0.19047619047619047, 0.2222222222222222], "model83": [0.08888888888888889, 0.38095238095238093, 0.19607843137254902, 0.16216216216216217, 0.23255813953488372], "model84": [0.21739130434782608, 0.26666666666666666, 0.25396825396825395, 0.09302325581395349, 0.2127659574468085], "model85": [0.20512820512820512, 0.3181818181818182, 0.25, 0.13953488372093023, 0.30434782608695654], "model86": [0.12, 0.34146341463414637, 0.22950819672131148, 0.09090909090909091, 0.2727272727272727], "model87": [0.20408163265306123, 0.37209302325581395, 0.1694915254237288, 0.16326530612244897, 0.13636363636363635], "model88": [0.2608695652173913, 0.38095238095238093, 0.3508771929824561, 0.15789473684210525, 0.21739130434782608], "model89": [0.2553191489361702, 0.4, 0.3508771929824561, 0.05263157894736842, 0.2127659574468085], "model90": [0.2857142857142857, 0.375, 0.2033898305084746, 0.23255813953488372, 0.3111111111111111], "model91": [0.20833333333333334, 0.3333333333333333, 0.3103448275862069, 0.15, 0.26666666666666666], "model92": [0.23809523809523808, 0.32558139534883723, 0.32142857142857145, 0.15789473684210525, 0.14285714285714285], "model93": [0.09302325581395349, 0.2857142857142857, 0.3, 0.19047619047619047, 0.18604651162790697], "model94": [0.14634146341463414, 0.32558139534883723, 0.3050847457627119, 0.13636363636363635, 0.26666666666666666], "model95": [0.2553191489361702, 0.3, 0.2962962962962963, 0.15789473684210525, 0.2], "model96": [0.2222222222222222, 0.35555555555555557, 0.27692307692307694, 0.20833333333333334, 0.17391304347826086], "model97": [0.20512820512820512, 0.30434782608695654, 0.34375, 0.13043478260869565, 0.17391304347826086], "model98": [0.20833333333333334, 0.34146341463414637, 0.24242424242424243, 0.08163265306122448, 0.19607843137254902], "model99": [0.23529411764705882, 0.32558139534883723, 0.1694915254237288, 0.1702127659574468, 0.13636363636363635], "model100": [0.19047619047619047, 0.2727272727272727, 0.3225806451612903, 0.23809523809523808, 0.17777777777777778], "model101": [0.20833333333333334, 0.425531914893617, 0.3050847457627119, 0.14285714285714285, 0.17391304347826086], "model102": [0.2608695652173913, 0.3902439024390244, 0.29508196721311475, 0.18604651162790697, 0.21739130434782608], "model103": [0.1702127659574468, 0.30434782608695654, 0.3157894736842105, 0.11428571428571428, 0.2553191489361702], "model104": [0.2978723404255319, 0.34782608695652173, 0.35714285714285715, 0.1111111111111111, 0.2127659574468085], "model105": [0.2127659574468085, 0.35555555555555557, 0.3870967741935484, 0.14634146341463414, 0.14285714285714285], "model106": [0.24489795918367346, 0.4, 0.32142857142857145, 0.17777777777777778, 0.08695652173913043], "model107": [0.26666666666666666, 0.32558139534883723, 0.21818181818181817, 0.2, 0.27906976744186046], "model108": [0.1702127659574468, 0.34782608695652173, 0.26229508196721313, 0.17777777777777778, 0.24], "model109": [0.2222222222222222, 0.30434782608695654, 0.16666666666666666, 0.08695652173913043, 0.1702127659574468], "model110": [0.16666666666666666, 0.32558139534883723, 0.25396825396825395, 0.08163265306122448, 0.2222222222222222], "model111": [0.2641509433962264, 0.4186046511627907, 0.17543859649122806, 0.13043478260869565, 0.2222222222222222], "model112": [0.3404255319148936, 0.3829787234042553, 0.23728813559322035, 0.13333333333333333, 0.22727272727272727], "model113": [0.2978723404255319, 0.4583333333333333, 0.28125, 0.13333333333333333, 0.26666666666666666], "model114": [0.2127659574468085, 0.32558139534883723, 0.22950819672131148, 0.1951219512195122, 0.2978723404255319], "model115": [0.16666666666666666, 0.35555555555555557, 0.29508196721311475, 0.05128205128205128, 0.21739130434782608], "model116": [0.24489795918367346, 0.35555555555555557, 0.32786885245901637, 0.15, 0.14285714285714285], "model117": [0.2608695652173913, 0.37209302325581395, 0.3050847457627119, 0.10256410256410256, 0.18181818181818182], "model118": [0.2727272727272727, 0.48, 0.31746031746031744, 0.2926829268292683, 0.22727272727272727], "model119": [0.13043478260869565, 0.3181818181818182, 0.27692307692307694, 0.1, 0.25]}, "accuracy": {"model0": [0.8023952095808383, 0.8562874251497006, 0.7485029940119761, 0.7951807228915663, 0.8192771084337349], "model1": [0.8143712574850299, 0.8323353293413174, 0.7485029940119761, 0.8072289156626506, 0.8072289156626506], "model2": [0.8023952095808383, 0.8622754491017964, 0.7485029940119761, 0.7951807228915663, 0.8132530120481928], "model3": [0.7904191616766467, 0.8562874251497006, 0.7485029940119761, 0.8012048192771084, 0.8132530120481928], "model4": [0.8323353293413174, 0.8622754491017964, 0.8023952095808383, 0.8192771084337349, 0.8192771084337349], "model5": [0.8143712574850299, 0.8622754491017964, 0.7904191616766467, 0.8253012048192772, 0.8072289156626506], "model6": [0.7844311377245509, 0.8562874251497006, 0.7964071856287425, 0.8132530120481928, 0.8072289156626506], "model7": [0.7844311377245509, 0.8682634730538922, 0.7664670658682635, 0.8253012048192772, 0.8313253012048193], "model8": [0.8203592814371258, 0.8502994011976048, 0.7964071856287425, 0.8192771084337349, 0.8012048192771084], "model9": [0.8023952095808383, 0.8682634730538922, 0.7964071856287425, 0.8253012048192772, 0.8072289156626506], "model10": [0.8083832335329342, 0.8263473053892215, 0.7844311377245509, 0.8192771084337349, 0.8012048192771084], "model11": [0.7844311377245509, 0.8682634730538922, 0.7784431137724551, 0.8132530120481928, 0.8012048192771084], "model12": [0.8203592814371258, 0.844311377245509, 0.7784431137724551, 0.8012048192771084, 0.8313253012048193], "model13": [0.8083832335329342, 0.844311377245509, 0.7724550898203593, 0.8132530120481928, 0.8072289156626506], "model14": [0.8143712574850299, 0.8383233532934131, 0.7485029940119761, 0.7831325301204819, 0.8132530120481928], "model15": [0.7904191616766467, 0.8383233532934131, 0.7245508982035929, 0.7831325301204819, 0.8132530120481928], "model16": [0.8323353293413174, 0.8562874251497006, 0.7844311377245509, 0.8072289156626506, 0.7891566265060241], "model17": [0.8323353293413174, 0.8802395209580839, 0.7844311377245509, 0.8072289156626506, 0.8192771084337349], "model18": [0.7844311377245509, 0.8562874251497006, 0.7724550898203593, 0.8192771084337349, 0.8132530120481928], "model19": [0.7844311377245509, 0.8682634730538922, 0.7365269461077845, 0.8253012048192772, 0.7951807228915663], "model20": [0.8263473053892215, 0.8562874251497006, 0.7844311377245509, 0.8072289156626506, 0.8072289156626506], "model21": [0.8083832335329342, 0.8562874251497006, 0.7784431137724551, 0.8132530120481928, 0.8072289156626506], "model22": [0.8143712574850299, 0.8622754491017964, 0.7964071856287425, 0.8012048192771084, 0.8373493975903614], "model23": [0.7724550898203593, 0.8622754491017964, 0.7844311377245509, 0.8072289156626506, 0.8012048192771084], "model24": [0.8023952095808383, 0.8502994011976048, 0.7425149700598802, 0.7891566265060241, 0.8192771084337349], "model25": [0.7964071856287425, 0.8383233532934131, 0.7485029940119761, 0.8012048192771084, 0.8313253012048193], "model26": [0.7964071856287425, 0.844311377245509, 0.7604790419161677, 0.7951807228915663, 0.8192771084337349], "model27": [0.7904191616766467, 0.8383233532934131, 0.7305389221556886, 0.8012048192771084, 0.7951807228915663], "model28": [0.8143712574850299, 0.8383233532934131, 0.7724550898203593, 0.8072289156626506, 0.8012048192771084], "model29": [0.8143712574850299, 0.8622754491017964, 0.7544910179640718, 0.8012048192771084, 0.8072289156626506], "model30": [0.8203592814371258, 0.8323353293413174, 0.7784431137724551, 0.8072289156626506, 0.7891566265060241], "model31": [0.7784431137724551, 0.844311377245509, 0.7664670658682635, 0.8072289156626506, 0.8132530120481928], "model32": [0.8083832335329342, 0.8562874251497006, 0.7784431137724551, 0.8192771084337349, 0.7951807228915663], "model33": [0.8143712574850299, 0.8562874251497006, 0.7784431137724551, 0.8132530120481928, 0.8072289156626506], "model34": [0.8023952095808383, 0.8622754491017964, 0.7724550898203593, 0.8072289156626506, 0.8012048192771084], "model35": [0.7724550898203593, 0.8203592814371258, 0.8203592814371258, 0.7831325301204819, 0.8192771084337349], "model36": [0.8023952095808383, 0.8562874251497006, 0.7125748502994012, 0.8132530120481928, 0.8072289156626506], "model37": [0.7604790419161677, 0.8383233532934131, 0.718562874251497, 0.7831325301204819, 0.7951807228915663], "model38": [0.7904191616766467, 0.844311377245509, 0.7485029940119761, 0.8012048192771084, 0.8072289156626506], "model39": [0.8083832335329342, 0.8622754491017964, 0.7365269461077845, 0.8012048192771084, 0.7650602409638554], "model40": [0.8023952095808383, 0.8323353293413174, 0.7544910179640718, 0.8253012048192772, 0.8132530120481928], "model41": [0.8323353293413174, 0.8622754491017964, 0.7784431137724551, 0.8012048192771084, 0.8132530120481928], "model42": [0.7844311377245509, 0.8502994011976048, 0.7604790419161677, 0.8253012048192772, 0.8192771084337349], "model43": [0.7844311377245509, 0.8383233532934131, 0.7784431137724551, 0.8373493975903614, 0.8012048192771084], "model44": [0.7964071856287425, 0.8562874251497006, 0.7904191616766467, 0.7831325301204819, 0.8072289156626506], "model45": [0.8203592814371258, 0.8143712574850299, 0.7844311377245509, 0.8072289156626506, 0.8012048192771084], "model46": [0.7904191616766467, 0.8502994011976048, 0.7724550898203593, 0.8012048192771084, 0.8012048192771084], "model47": [0.7964071856287425, 0.844311377245509, 0.7964071856287425, 0.8072289156626506, 0.8132530120481928], "model48": [0.7844311377245509, 0.8323353293413174, 0.7125748502994012, 0.8012048192771084, 0.8072289156626506], "model49": [0.7844311377245509, 0.8323353293413174, 0.7245508982035929, 0.8012048192771084, 0.8072289156626506], "model50": [0.7485029940119761, 0.8682634730538922, 0.7305389221556886, 0.7771084337349398, 0.7951807228915663], "model51": [0.8023952095808383, 0.8682634730538922, 0.718562874251497, 0.7831325301204819, 0.8012048192771084], "model52": [0.7964071856287425, 0.8263473053892215, 0.7724550898203593, 0.8012048192771084, 0.7831325301204819], "model53": [0.8383233532934131, 0.8562874251497006, 0.7724550898203593, 0.7891566265060241, 0.7891566265060241], "model54": [0.7664670658682635, 0.844311377245509, 0.7544910179640718, 0.8072289156626506, 0.7831325301204819], "model55": [0.7844311377245509, 0.8263473053892215, 0.7544910179640718, 0.8072289156626506, 0.7710843373493976], "model56": [0.7844311377245509, 0.844311377245509, 0.7604790419161677, 0.8192771084337349, 0.8072289156626506], "model57": [0.8143712574850299, 0.8263473053892215, 0.7844311377245509, 0.7831325301204819, 0.8012048192771084], "model58": [0.8023952095808383, 0.844311377245509, 0.7844311377245509, 0.8072289156626506, 0.7771084337349398], "model59": [0.7904191616766467, 0.8383233532934131, 0.7724550898203593, 0.8072289156626506, 0.8072289156626506], "model60": [0.7784431137724551, 0.8203592814371258, 0.7125748502994012, 0.7891566265060241, 0.8132530120481928], "model61": [0.7964071856287425, 0.8143712574850299, 0.7245508982035929, 0.8012048192771084, 0.8192771084337349], "model62": [0.7724550898203593, 0.8502994011976048, 0.7245508982035929, 0.7831325301204819, 0.7891566265060241], "model63": [0.7724550898203593, 0.844311377245509, 0.7125748502994012, 0.7771084337349398, 0.8192771084337349], "model64": [0.7904191616766467, 0.8263473053892215, 0.7425149700598802, 0.8072289156626506, 0.7831325301204819], "model65": [0.8143712574850299, 0.8502994011976048, 0.7544910179640718, 0.8132530120481928, 0.8012048192771084], "model66": [0.7904191616766467, 0.8203592814371258, 0.7544910179640718, 0.8012048192771084, 0.7710843373493976], "model67": [0.7784431137724551, 0.8383233532934131, 0.7664670658682635, 0.8192771084337349, 0.8072289156626506], "model68": [0.8083832335329342, 0.8502994011976048, 0.7724550898203593, 0.8192771084337349, 0.7891566265060241], "model69": [0.7964071856287425, 0.8502994011976048, 0.7724550898203593, 0.7831325301204819, 0.8072289156626506], "model70": [0.7964071856287425, 0.8383233532934131, 0.7604790419161677, 0.8132530120481928, 0.7891566265060241], "model71": [0.7784431137724551, 0.844311377245509, 0.7904191616766467, 0.8012048192771084, 0.8132530120481928], "model72": [0.7904191616766467, 0.8323353293413174, 0.718562874251497, 0.7710843373493976, 0.7891566265060241], "model73": [0.8083832335329342, 0.8203592814371258, 0.7125748502994012, 0.7650602409638554, 0.8012048192771084], "model74": [0.7784431137724551, 0.8562874251497006, 0.7245508982035929, 0.7710843373493976, 0.7951807228915663], "model75": [0.7724550898203593, 0.8323353293413174, 0.7005988023952096, 0.7891566265060241, 0.7590361445783133], "model76": [0.7964071856287425, 0.8263473053892215, 0.7305389221556886, 0.8253012048192772, 0.7771084337349398], "model77": [0.8263473053892215, 0.844311377245509, 0.7844311377245509, 0.7891566265060241, 0.7710843373493976], "model78": [0.7904191616766467, 0.8383233532934131, 0.7245508982035929, 0.7891566265060241, 0.7891566265060241], "model79": [0.7904191616766467, 0.8203592814371258, 0.7844311377245509, 0.7951807228915663, 0.7831325301204819], "model80": [0.7784431137724551, 0.8383233532934131, 0.7485029940119761, 0.8132530120481928, 0.7831325301204819], "model81": [0.7964071856287425, 0.844311377245509, 0.7664670658682635, 0.8072289156626506, 0.7891566265060241], "model82": [0.8083832335329342, 0.8502994011976048, 0.7604790419161677, 0.7951807228915663, 0.7891566265060241], "model83": [0.7544910179640718, 0.844311377245509, 0.7544910179640718, 0.8132530120481928, 0.8012048192771084], "model84": [0.7844311377245509, 0.8023952095808383, 0.718562874251497, 0.7650602409638554, 0.7771084337349398], "model85": [0.8143712574850299, 0.8203592814371258, 0.7125748502994012, 0.7771084337349398, 0.8072289156626506], "model86": [0.7365269461077845, 0.8383233532934131, 0.718562874251497, 0.7590361445783133, 0.8072289156626506], "model87": [0.7664670658682635, 0.8383233532934131, 0.7065868263473054, 0.7530120481927711, 0.7710843373493976], "model88": [0.7964071856287425, 0.844311377245509, 0.7784431137724551, 0.8072289156626506, 0.7831325301204819], "model89": [0.7904191616766467, 0.8383233532934131, 0.7784431137724551, 0.7831325301204819, 0.7771084337349398], "model90": [0.7904191616766467, 0.8203592814371258, 0.718562874251497, 0.8012048192771084, 0.8132530120481928], "model91": [0.7724550898203593, 0.8323353293413174, 0.7604790419161677, 0.7951807228915663, 0.8012048192771084], "model92": [0.8083832335329342, 0.8263473053892215, 0.7724550898203593, 0.8072289156626506, 0.7831325301204819], "model93": [0.7664670658682635, 0.8203592814371258, 0.7485029940119761, 0.7951807228915663, 0.7891566265060241], "model94": [0.7904191616766467, 0.8263473053892215, 0.7544910179640718, 0.7710843373493976, 0.8012048192771084], "model95": [0.7904191616766467, 0.8323353293413174, 0.7724550898203593, 0.8072289156626506, 0.8072289156626506], "model96": [0.7904191616766467, 0.8263473053892215, 0.718562874251497, 0.7710843373493976, 0.7710843373493976], "model97": [0.8143712574850299, 0.8083832335329342, 0.7485029940119761, 0.7590361445783133, 0.7710843373493976], "model98": [0.7724550898203593, 0.8383233532934131, 0.7005988023952096, 0.7289156626506024, 0.7530120481927711], "model99": [0.7664670658682635, 0.8263473053892215, 0.7065868263473054, 0.7650602409638554, 0.7710843373493976], "model100": [0.7964071856287425, 0.8083832335329342, 0.7485029940119761, 0.8072289156626506, 0.7771084337349398], "model101": [0.7724550898203593, 0.8383233532934131, 0.7544910179640718, 0.7831325301204819, 0.7710843373493976], "model102": [0.7964071856287425, 0.8502994011976048, 0.7425149700598802, 0.7891566265060241, 0.7831325301204819], "model103": [0.7664670658682635, 0.8083832335329342, 0.7664670658682635, 0.8132530120481928, 0.7891566265060241], "model104": [0.8023952095808383, 0.8203592814371258, 0.7844311377245509, 0.8072289156626506, 0.7771084337349398], "model105": [0.7784431137724551, 0.8263473053892215, 0.7724550898203593, 0.7891566265060241, 0.7831325301204819], "model106": [0.7784431137724551, 0.8383233532934131, 0.7724550898203593, 0.7771084337349398, 0.7469879518072289], "model107": [0.8023952095808383, 0.8263473053892215, 0.7425149700598802, 0.8072289156626506, 0.8132530120481928], "model108": [0.7664670658682635, 0.8203592814371258, 0.7305389221556886, 0.7771084337349398, 0.7710843373493976], "model109": [0.7904191616766467, 0.8083832335329342, 0.7005988023952096, 0.7469879518072289, 0.7650602409638554], "model110": [0.7604790419161677, 0.8263473053892215, 0.718562874251497, 0.7289156626506024, 0.7469879518072289], "model111": [0.7664670658682635, 0.8502994011976048, 0.718562874251497, 0.7590361445783133, 0.7891566265060241], "model112": [0.8143712574850299, 0.8263473053892215, 0.7305389221556886, 0.7650602409638554, 0.7951807228915663], "model113": [0.8023952095808383, 0.844311377245509, 0.7245508982035929, 0.7650602409638554, 0.8012048192771084], "model114": [0.7784431137724551, 0.8263473053892215, 0.718562874251497, 0.8012048192771084, 0.8012048192771084], "model115": [0.7604790419161677, 0.8263473053892215, 0.7425149700598802, 0.7771084337349398, 0.7831325301204819], "model116": [0.7784431137724551, 0.8263473053892215, 0.7544910179640718, 0.7951807228915663, 0.7831325301204819], "model117": [0.7964071856287425, 0.8383233532934131, 0.7544910179640718, 0.7891566265060241, 0.7831325301204819], "model118": [0.8083832335329342, 0.844311377245509, 0.7425149700598802, 0.8253012048192772, 0.7951807228915663], "model119": [0.7604790419161677, 0.8203592814371258, 0.718562874251497, 0.7831325301204819, 0.7831325301204819]}, "roc_auc": {"model0": [0.5774294670846395, 0.622257053291536, 0.6802536231884058, 0.6366792929292929, 0.689709595959596], "model1": [0.6040752351097178, 0.6407523510971788, 0.7065217391304348, 0.5991161616161617, 0.7143308080808081], "model2": [0.6269592476489029, 0.6125391849529781, 0.623792270531401, 0.5643939393939394, 0.7149621212121212], "model3": [0.5711598746081505, 0.670846394984326, 0.6126207729468599, 0.610479797979798, 0.6732954545454546], "model4": [0.6498432601880878, 0.6620689655172414, 0.6887077294685992, 0.6988636363636364, 0.7039141414141414], "model5": [0.6278996865203762, 0.6705329153605016, 0.6826690821256038, 0.6944444444444444, 0.7133838383838385], "model6": [0.6554858934169279, 0.6868338557993731, 0.6962560386473429, 0.702020202020202, 0.7133838383838383], "model7": [0.6163009404388714, 0.6589341692789968, 0.6841787439613526, 0.6537247474747474, 0.6846590909090909], "model8": [0.6269592476489028, 0.7065830721003135, 0.6914251207729468, 0.7190656565656566, 0.7064393939393939], "model9": [0.6620689655172415, 0.681191222570533, 0.6899154589371981, 0.6840277777777778, 0.728219696969697], "model10": [0.6824451410658307, 0.6526645768025079, 0.6878019323671498, 0.6796085858585859, 0.7054924242424243], "model11": [0.6636363636363636, 0.6793103448275863, 0.6790458937198067, 0.6461489898989898, 0.7203282828282829], "model12": [0.5946708463949844, 0.6181818181818182, 0.6618357487922705, 0.6404671717171717, 0.6912878787878789], "model13": [0.6028213166144201, 0.6501567398119124, 0.7071256038647343, 0.6565656565656566, 0.6979166666666666], "model14": [0.5652037617554859, 0.6288401253918495, 0.6394927536231885, 0.5744949494949495, 0.711489898989899], "model15": [0.5711598746081505, 0.6771159874608151, 0.6219806763285024, 0.577020202020202, 0.6732954545454546], "model16": [0.6746081504702194, 0.6605015673981192, 0.6657608695652174, 0.6669823232323232, 0.6682449494949495], "model17": [0.661128526645768, 0.6645768025078369, 0.6935386473429952, 0.6190025252525252, 0.7026515151515152], "model18": [0.6667711598746082, 0.6858934169278997, 0.6859903381642511, 0.6272095959595959, 0.7414772727272728], "model19": [0.65141065830721, 0.6642633228840125, 0.6479468599033816, 0.6568813131313131, 0.7146464646464646], "model20": [0.6504702194357367, 0.6783699059561129, 0.6627415458937197, 0.6893939393939393, 0.6751893939393939], "model21": [0.6670846394984326, 0.6884012539184954, 0.6621376811594203, 0.720959595959596, 0.7305871212121211], "model22": [0.6677115987460815, 0.6849529780564263, 0.7062198067632851, 0.7004419191919192, 0.6900252525252525], "model23": [0.6733542319749216, 0.7037617554858935, 0.6896135265700483, 0.6650883838383839, 0.7108585858585859], "model24": [0.5294670846394984, 0.5987460815047021, 0.6831219806763285, 0.6035353535353535, 0.7178030303030303], "model25": [0.5768025078369906, 0.6542319749216301, 0.6331521739130435, 0.6101641414141414, 0.7339015151515151], "model26": [0.5655172413793104, 0.6112852664576803, 0.6334541062801932, 0.5855429292929293, 0.7070707070707072], "model27": [0.5727272727272728, 0.6404388714733542, 0.6322463768115942, 0.601641414141414, 0.6486742424242424], "model28": [0.631974921630094, 0.6457680250783698, 0.6367753623188406, 0.7064393939393939, 0.6382575757575758], "model29": [0.6626959247648904, 0.6968652037617555, 0.6727053140096618, 0.689709595959596, 0.6777146464646464], "model30": [0.6454545454545454, 0.6959247648902821, 0.6748188405797102, 0.6824494949494949, 0.6631944444444444], "model31": [0.6586206896551725, 0.6476489028213167, 0.6397946859903382, 0.5861742424242424, 0.7061237373737375], "model32": [0.668025078369906, 0.6752351097178684, 0.6576086956521738, 0.6963383838383839, 0.6682449494949496], "model33": [0.6755485893416928, 0.6768025078369907, 0.6696859903381642, 0.6963383838383839, 0.7263257575757576], "model34": [0.6808777429467086, 0.6727272727272727, 0.6769323671497586, 0.7058080808080809, 0.6879734848484849], "model35": [0.6557993730407523, 0.6670846394984326, 0.7032004830917875, 0.6524621212121212, 0.7190656565656566], "model36": [0.5526645768025078, 0.6275862068965518, 0.605072463768116, 0.577020202020202, 0.6663510101010102], "model37": [0.5363636363636364, 0.6050156739811913, 0.6189613526570048, 0.6196338383838385, 0.6660353535353536], "model38": [0.5755485893416928, 0.5909090909090909, 0.6419082125603864, 0.5561868686868687, 0.7339015151515151], "model39": [0.5736677115987461, 0.6868338557993731, 0.6259057971014492, 0.5823863636363636, 0.6429924242424243], "model40": [0.6471786833855799, 0.6090909090909091, 0.6286231884057971, 0.6912878787878789, 0.6477272727272727], "model41": [0.7084639498432602, 0.6752351097178684, 0.7044082125603864, 0.6761363636363636, 0.7039141414141413], "model42": [0.638244514106583, 0.7147335423197492, 0.6621376811594203, 0.6666666666666666, 0.6701388888888891], "model43": [0.5808777429467085, 0.6739811912225706, 0.6410024154589372, 0.6328914141414141, 0.7095959595959596], "model44": [0.622884012539185, 0.6763322884012539, 0.6606280193236714, 0.694760101010101, 0.6829229797979799], "model45": [0.7304075235109718, 0.681191222570533, 0.7047101449275363, 0.6647727272727273, 0.7203282828282829], "model46": [0.6764890282131661, 0.6576802507836991, 0.6986714975845411, 0.6732954545454546, 0.6908143939393939], "model47": [0.6758620689655173, 0.6855799373040752, 0.6805555555555556, 0.6597222222222223, 0.7171717171717171], "model48": [0.5416927899686521, 0.6028213166144201, 0.6150362318840579, 0.5631313131313131, 0.6587752525252526], "model49": [0.5510971786833856, 0.5993730407523512, 0.6017512077294686, 0.5738636363636364, 0.7297979797979798], "model50": [0.5598746081504702, 0.6426332288401253, 0.6410024154589371, 0.5921717171717171, 0.6934974747474747], "model51": [0.593730407523511, 0.7100313479623825, 0.5990338164251208, 0.5886994949494949, 0.6092171717171717], "model52": [0.6858934169278997, 0.6407523510971787, 0.6509661835748792, 0.6783459595959596, 0.6688762626262627], "model53": [0.6905956112852665, 0.6711598746081505, 0.6582125603864734, 0.6246843434343434, 0.665719696969697], "model54": [0.654858934169279, 0.681191222570533, 0.6624396135265701, 0.6600378787878788, 0.6879734848484849], "model55": [0.6231974921630095, 0.6689655172413793, 0.6702898550724637, 0.6227904040404041, 0.6893939393939394], "model56": [0.6789968652037617, 0.6752351097178683, 0.6570048309178744, 0.6966540404040404, 0.6747159090909091], "model57": [0.7401253918495297, 0.6865203761755485, 0.7164855072463767, 0.6856060606060606, 0.7348484848484849], "model58": [0.6974921630094044, 0.6833855799373041, 0.663647342995169, 0.7174873737373737, 0.7178030303030303], "model59": [0.6695924764890282, 0.6949843260188089, 0.692330917874396, 0.6458333333333333, 0.7067550505050505], "model60": [0.5557993730407524, 0.6150470219435737, 0.6440217391304348, 0.5640782828282828, 0.7083333333333334], "model61": [0.5708463949843261, 0.6194357366771159, 0.5942028985507246, 0.5845959595959596, 0.726010101010101], "model62": [0.5777429467084639, 0.6081504702194358, 0.6171497584541062, 0.584280303030303, 0.6483585858585859], "model63": [0.5800940438871474, 0.6554858934169279, 0.5905797101449276, 0.5684974747474748, 0.6281565656565656], "model64": [0.6921630094043887, 0.6833855799373041, 0.6240942028985507, 0.6631944444444445, 0.6717171717171717], "model65": [0.6636363636363636, 0.7090909090909091, 0.6545893719806763, 0.6448863636363636, 0.6534090909090908], "model66": [0.6738244514106583, 0.660501567398119, 0.6654589371980677, 0.6780303030303031, 0.671875], "model67": [0.6592476489028213, 0.666771159874608, 0.6693840579710145, 0.6600378787878788, 0.702020202020202], "model68": [0.670846394984326, 0.7034482758620689, 0.6423611111111112, 0.7035984848484848, 0.6025883838383839], "model69": [0.7438871473354232, 0.6768025078369906, 0.6802536231884058, 0.6960227272727273, 0.6960227272727273], "model70": [0.6642633228840125, 0.7141065830721003, 0.7035024154589372, 0.6783459595959596, 0.6611426767676767], "model71": [0.6586206896551724, 0.6147335423197492, 0.6917270531400966, 0.6458333333333334, 0.7144886363636364], "model72": [0.5752351097178684, 0.5981191222570533, 0.6316425120772946, 0.5918560606060606, 0.6426767676767676], "model73": [0.618025078369906, 0.587460815047022, 0.5932971014492754, 0.6006944444444444, 0.6934974747474748], "model74": [0.5647335423197493, 0.6357366771159875, 0.6195652173913044, 0.564709595959596, 0.6357323232323233], "model75": [0.5996865203761755, 0.6987460815047022, 0.6195652173913043, 0.5470328282828284, 0.6319444444444444], "model76": [0.6293103448275863, 0.6648902821316615, 0.6266606280193237, 0.7133838383838385, 0.6731376262626263], "model77": [0.7090909090909091, 0.7128526645768026, 0.6722524154589372, 0.6587752525252525, 0.6794507575757576], "model78": [0.664576802507837, 0.65141065830721, 0.6533816425120774, 0.685290404040404, 0.6873421717171717], "model79": [0.6021943573667711, 0.6532915360501568, 0.6835748792270532, 0.5918560606060606, 0.6840277777777778], "model80": [0.6984326018808777, 0.7429467084639498, 0.6447765700483092, 0.6553030303030304, 0.6747159090909091], "model81": [0.6746081504702195, 0.6520376175548589, 0.6971618357487923, 0.706439393939394, 0.6781881313131313], "model82": [0.7087774294670847, 0.6978056426332289, 0.6458333333333334, 0.642361111111111, 0.689236111111111], "model83": [0.6489028213166144, 0.6429467084639499, 0.6449275362318841, 0.6335227272727273, 0.6990214646464646], "model84": [0.5379310344827586, 0.6692789968652039, 0.6168478260869565, 0.5943813131313131, 0.6145833333333333], "model85": [0.5959247648902821, 0.5974921630094044, 0.5990338164251208, 0.5918560606060606, 0.7241161616161615], "model86": [0.5689655172413793, 0.5974921630094043, 0.6141304347826086, 0.6344696969696969, 0.75], "model87": [0.602037617554859, 0.6880877742946709, 0.5904287439613527, 0.608270202020202, 0.6388888888888888], "model88": [0.661128526645768, 0.6708463949843261, 0.6630434782608697, 0.7054924242424243, 0.6661931818181819], "model89": [0.7094043887147337, 0.7083072100313479, 0.668780193236715, 0.6777146464646465, 0.6336805555555555], "model90": [0.6764890282131661, 0.7090909090909091, 0.6370772946859904, 0.678030303030303, 0.704229797979798], "model91": [0.6554858934169279, 0.6363636363636365, 0.6654589371980677, 0.670770202020202, 0.7512626262626262], "model92": [0.7090909090909091, 0.7213166144200627, 0.6884057971014492, 0.7162247474747475, 0.6695075757575758], "model93": [0.7040752351097178, 0.6752351097178684, 0.6476449275362319, 0.6903409090909091, 0.6837121212121212], "model94": [0.6846394984326019, 0.6846394984326019, 0.6832729468599034, 0.6893939393939394, 0.6649305555555556], "model95": [0.680564263322884, 0.6523510971786833, 0.6696859903381642, 0.6357323232323232, 0.7544191919191919], "model96": [0.5489028213166144, 0.6639498432601881, 0.6416062801932367, 0.5804924242424242, 0.6720328282828282], "model97": [0.5959247648902821, 0.6109717868338558, 0.6407004830917874, 0.579229797979798, 0.6720328282828282], "model98": [0.5554858934169279, 0.6072100313479624, 0.6183574879227053, 0.5811237373737373, 0.6092171717171717], "model99": [0.5904388714733543, 0.6852664576802507, 0.6091485507246377, 0.601010101010101, 0.6502525252525252], "model100": [0.664576802507837, 0.6573667711598746, 0.6808574879227053, 0.7421085858585859, 0.6519886363636365], "model101": [0.6952978056426333, 0.6733542319749217, 0.6776871980676329, 0.7039141414141414, 0.7234848484848485], "model102": [0.6655172413793103, 0.7029780564263323, 0.6458333333333334, 0.7099116161616161, 0.6941287878787878], "model103": [0.6379310344827587, 0.6617554858934169, 0.68131038647343, 0.6275252525252525, 0.7138573232323232], "model104": [0.7399686520376175, 0.7064263322884012, 0.6986714975845411, 0.7073863636363636, 0.6685606060606061], "model105": [0.7241379310344828, 0.6918495297805642, 0.6947463768115942, 0.6966540404040404, 0.6770833333333334], "model106": [0.658307210031348, 0.6818181818181819, 0.6829710144927537, 0.6742424242424243, 0.6447285353535355], "model107": [0.6990595611285266, 0.6642633228840126, 0.6503623188405796, 0.6553030303030303, 0.7331123737373738], "model108": [0.5409090909090909, 0.6677115987460815, 0.6301328502415459, 0.5735479797979798, 0.6912878787878788], "model109": [0.5545454545454546, 0.6137931034482759, 0.6159420289855072, 0.5637626262626263, 0.6464646464646465], "model110": [0.5702194357366771, 0.5984326018808777, 0.6044685990338163, 0.5899621212121212, 0.6044823232323232], "model111": [0.59858934169279, 0.6796238244514107, 0.607487922705314, 0.5855429292929293, 0.6338383838383839], "model112": [0.6485893416927899, 0.6648902821316615, 0.6822161835748792, 0.6871843434343434, 0.6136363636363636], "model113": [0.6952978056426332, 0.7253918495297806, 0.6431159420289855, 0.6000631313131313, 0.6459911616161615], "model114": [0.6774294670846395, 0.7040752351097179, 0.6594202898550725, 0.6982323232323232, 0.7143308080808082], "model115": [0.6410658307210032, 0.6880877742946708, 0.6829710144927537, 0.6493055555555556, 0.6827651515151516], "model116": [0.7003134796238244, 0.7000000000000001, 0.6710446859903383, 0.6878156565656566, 0.6374684343434343], "model117": [0.7231974921630094, 0.6846394984326019, 0.6843297101449276, 0.6559343434343434, 0.6969696969696969], "model118": [0.7391849529780564, 0.6945141065830721, 0.6733091787439613, 0.6773989898989898, 0.6786616161616161], "model119": [0.6429467084639499, 0.6536050156739812, 0.669987922705314, 0.6328914141414141, 0.7163825757575758]}}